{
    "ACEI": 579,
    "愊愊": 250,
    "习习": 197,
    "怵惕思虑": 155,
    "夕发旦": 123,
    "陈橘皮": 1423,
    "古云": 1892,
    "骎骎": 30,
    "安若": 29,
    "金匮栝蒌": 29,
    "辛温": 63334,
    "标实": 947,
    "惕惕": 456,
    "阳黄\n": 44,
    "溏垢": 86,
    "少阳": 67768,
    "\n元": 106,
    "黄赤": 3643,
    "\n明": 1143,
    "鬲塞": 60,
    "飒然": 39,
    "\n修园": 37,
    "宋元": 1910,
    "漉漉": 1789,
    "兀兀然": 39,
    "安蛔": 8606,
    "戌亥子丑": 49,
    "俱秘": 21,
    "霍然": 1838,
    "方连九一丹": 35,
    "苷元": 6525,
    "暑湿": 3279,
    "王不留行子": 26,
    "荜苃": 32,
    "脘痞": 3256,
    "膨隆": 5311,
    "min": 8435,
    "kg": 26504,
    "嗳腐": 2438,
    "梦遗": 2030,
    "惕惕然": 1007,
    "君火": 2703,
    "金烁": 192,
    "涎盛": 142,
    "澹澹": 690,
    "筑筑然": 51,
    "楼全善": 65,
    "梦寝": 109,
    "丸桐子": 982,
    "振振": 665,
    "津唾": 467,
    "惕然": 541,
    "丸黍子": 50,
    "奄奄": 136,
    "阳黄": 1768,
    "邱": 21,
    "阳": 327,
    "黄浊": 1654,
    "肛栓": 55,
    "炙煿": 1735,
    "载云": 29,
    "金代": 255,
    "\n丹": 249,
    "卑惵\n卑惵": 18,
    "金代成无己": 215,
    "干哕": 185,
    "温阳清利方": 18,
    "\n积": 18,
    "Ｇｒａｖｅ": 15,
    "马宝\n": 4,
    "疟母": 4099,
    "\n清": 448,
    "嘉言": 352,
    "涤浊涎": 8,
    "厥疾": 167,
    "篇云": 2464,
    "诸痿": 2,
    "经云": 74,
    "秽洁": 102,
    "\n大青": 3,
    "\n阳": 788,
    "箕裘世绍": 7,
    "\n先生": 900,
    "黎庶": 77,
    "盖儿": 228,
    "简静": 68,
    "张仲虎客邸耽": 33,
    "陈逐垢斯无忌": 46,
    "华君松岩惠余": 46,
    "藜藿": 419,
    "凛凛": 189,
    "愦愦": 317,
    "荊芥": 80,
    "镑犀": 46,
    "金克木": 2239,
    "\n寒沉藏": 16,
    "言言典": 19,
    "潜阳": 1422,
    "眩奇": 38,
    "斯易": 50,
    "夫涕唾": 25,
    "余言": 1049,
    "冤哉": 69,
    "\n朔": 23,
    "日晡": 205,
    "郁极": 96,
    "清·武之望": 20,
    "戊己": 1672,
    "\n录": 15,
    "论云": 215,
    "甘辛": 1117,
    "厥疾弗瘳": 58,
    "范郎中夫人": 11,
    "幸蒙": 18,
    "予言": 34,
    "夫古": 11,
    "痹论云": 26,
    "延仆": 38,
    "余曰": 3455,
    "余蹙": 25,
    "尔躁": 18,
    "梅丸": 13,
    "簧簧": 23,
    "五苓": 493,
    "厥阴少阳": 62,
    "范少参长倩": 31,
    "翁弃养。君": 31,
    "苏锡常太同道": 31,
    "徐评": 46,
    "元礼本震亨": 12,
    "何哉": 508,
    "安道之": 12,
    "涎唾": 1483,
    "饮子": 12,
    "方通": 227,
    "言微": 47,
    "君": 64,
    "火铄": 121,
    "金化滋": 116,
    "莫晓": 128,
    "苟不平": 229,
    "芎": 392,
    "王太仆云": 256,
    "吴车驾澜公岳": 17,
    "诘予": 23,
    "孙曰": 173,
    "茹素": 191,
    "哽哽": 172,
    "孙诊": 71,
    "孙诊之": 22,
    "余甫": 26,
    "谭支顺阑横": 17,
    "务尔": 17,
    "拘拘然": 18,
    "何尤": 18,
    "\n余": 487,
    "\n生": 918,
    "尤乘": 246,
    "滑寿": 892,
    "安可致肾安": 36,
    "庚壬": 27,
    "子寅辰午申戊": 24,
    "乙丁己辛癸": 33,
    "辰戊": 27,
    "丁得壬": 24,
    "金·刘完素": 27,
    "霍司承君祥": 26,
    "暄暖": 34,
    "嚏呕": 22,
    "衄衊语": 8,
    "王气": 315,
    "眚苍": 23,
    "左胠": 16,
    "金余": 8,
    "郁痿": 8,
    "瞀昧": 84,
    "瞀闷懊": 37,
    "冨瘛": 8,
    "丹熛": 89,
    "寒淫": 779,
    "疡科": 110,
    "砒鸩": 68,
    "怫怫然": 80,
    "熇熇然": 42,
    "\n成无己云": 8,
    "谚云": 1059,
    "何遽": 245,
    "公余": 6,
    "正阳阳明": 9,
    "\n少阳": 301,
    "余揆": 12,
    "适余": 49,
    "愚侄林": 6,
    "二氏": 140,
    "方宗喻嘉言": 15,
    "乌犀": 70,
    "原注云": 137,
    "铁樵": 58,
    "罗司徒知悌": 4,
    "盛寒": 4,
    "滋肱": 4,
    "懊喘": 4,
    "谏君": 139,
    "\n经云": 215,
    "踰垣": 299,
    "镏洪私淑": 4,
    "古明医": 24,
    "常公仲明辈": 19,
    "唐太宗李世民": 151,
    "亢旱": 33,
    "炎威": 275,
    "暑月": 1045,
    "室庐": 12,
    "安伯云": 13,
    "安伯察": 13,
    "猝仆": 195,
    "芎苓": 75,
    "王汝言": 99,
    "陈辈": 48,
    "尤烈": 93,
    "盖子阳": 47,
    "二公": 53,
    "余晓": 115,
    "子何愚": 47,
    "甘旨": 48,
    "予愀然": 47,
    "井田": 48,
    "尚尔": 292,
    "汝安": 47,
    "馋涎": 47,
    "寐兴陨": 47,
    "莹洁": 80,
    "\n愚": 1307,
    "罗太无": 104,
    "成注": 70,
    "二阳": 2010,
    "余初": 181,
    "\n通": 29,
    "光绪": 1208,
    "盖诚": 15,
    "方注云": 90,
    "痉湿": 107,
    "趺蹶": 193,
    "濡": 65,
    "释云": 62,
    "汪诊脉濡缓": 6,
    "劳思": 182,
    "曲蘖": 16,
    "何怪": 7,
    "悽悽": 62,
    "鬓霜": 40,
    "　　　": 1185,
    "丹参酮ⅡA": 1119,
    "\n医　　德\n": 14,
    "\n泄卫": 7,
    "吴湿": 96,
    "喘康速": 6,
    "次晨": 684,
    "清富察敦崇": 1,
    "矢数道明氏": 1,
    "\n兹": 325,
    "\n暑": 368,
    "苓芍": 54,
    "郁思": 78,
    "汤本求真云": 6,
    "喻嘉言云": 115,
    "宣壅": 137,
    "扶羸": 8,
    "俾郁": 12,
    "阳辅": 1176,
    "秽浊": 380,
    "郁炼稠浊": 9,
    "藿": 6,
    "夜梦": 1631,
    "苍苍然": 212,
    "鸣濯濯": 248,
    "\n迨": 36,
    "王": 888,
    "阳伤液涸": 1,
    "贞妣庚虯": 78,
    "王疾": 287,
    "贞妇好疛延虯": 39,
    "贞翌辛酉侑": 12,
    "贞妇貍娩余子": 12,
    "\n贞": 46,
    "丁未": 339,
    "酉卜": 238,
    "子卜辞": 211,
    "乙卯": 320,
    "岁祖乙子祝": 64,
    "乙卯卜": 131,
    "癸子": 152,
    "贞父乙異隹": 64,
    "卜妇亡祟爵": 18,
    "隹母庚害子安": 28,
    "吴取任伐弗": 17,
    "贞妇婐娩妿": 34,
    "贞妇婐娩妿隹": 34,
    "贞翌庚辰王": 28,
    "\n第": 48,
    "大丁子大甲": 28,
    "贞王弗条戈": 35,
    "隹庚娩弘吉": 24,
    "廿十\n": 12,
    "兹迺": 12,
    "余子": 128,
    "余弗": 45,
    "卜妇": 22,
    "旬壬妇姪妿": 22,
    "贞翌戊辰王": 7,
    "帝隹兹邑龙": 26,
    "帝隹玆邑龙": 26,
    "牲侑祭妣癸": 26,
    "乙岁牡妣庚": 34,
    "妣己豰卯牝": 7,
    "贞子娩妿隹": 12,
    "牡": 124,
    "\n梅": 21,
    "燥矢": 47,
    "郁郁": 130,
    "龙葵": 989,
    "哕逆": 210,
    "胃癌": 7,
    "大肠癌": 7,
    "胰腺癌": 24,
    "王孟英云": 316,
    "九一丹": 185,
    "甘辛温": 110,
    "曲周颞颥": 60,
    "腑阳": 96,
    "烊化": 253,
    "庚合": 359,
    "辛合": 274,
    "壬合": 143,
    "癸合": 100,
    "瞳神": 8948,
    "脓垢": 6,
    "唐": 6,
    "mmHg": 284,
    "黄脓": 402,
    "叶舌段斑": 2,
    "百骸": 1,
    "温肾阳": 1,
    "刘完素云": 76,
    "八二丹": 41,
    "渍形": 299,
    "匡郭": 270,
    "揆度": 214,
    "石云": 3,
    "寂兮寥兮": 85,
    "阴精": 191,
    "胞睑司": 1,
    "万寂": 86,
    "\n亚": 41,
    "火克金": 50,
    "紫贝齿": 7,
    "辛凉": 555,
    "寒哮": 377,
    "峻效宏": 48,
    "陶陶": 20,
    "姜辛温": 7,
    "  ": 377,
    "高蕊 　陆芳": 8,
    "\n犬子": 17,
    "月余": 1322,
    "\n拙": 18,
    "金匮": 673,
    "沫月余": 23,
    "　 智照林": 1,
    "18727": 1,
    "雷火": 299,
    "朱茯神远志": 1,
    "怒郁": 191,
    "瞀闷": 178,
    "伏温": 62,
    "姜枇": 2,
    "杷叶": 291,
    "淋沥": 602,
    "步屣": 2,
    "譬犹户枢": 31,
    "梦语": 220,
    "焦楂": 1511,
    "峻消": 9,
    "郁热清": 26,
    "克伐": 94,
    "辛微温": 147,
    "目连劄": 43,
    "目劄": 67,
    "方中四苓": 43,
    "肥甘": 109,
    "申酉": 1040,
    "刁吵": 32,
    "\n培": 4,
    "方中生军": 19,
    "涕绝": 9,
    "82817": 1,
    "80279": 1,
    "0702923": 1,
    "方中萹蓄": 14,
    "紫晦": 12,
    "诸恙悉平": 154,
    "体康步健": 2,
    "荆防诸": 1,
    "80008": 1,
    "泾云": 290,
    "李自小": 1,
    "李父日": 1,
    "汤头": 65,
    "891271": 2,
    "871103": 2,
    "\n甘": 33,
    "濡暑": 24,
    "温炙": 12,
    "温炙衣": 5,
    "天癸竭": 6,
    "方后注云": 172,
    "譬犹": 627,
    "绵昧": 9,
    "目窠": 164,
    "芎藭": 429,
    "漐漐微": 118,
    "解语丹": 64,
    "吭喀": 27,
    "黄脉": 25,
    "予忆古": 13,
    "丹波元简云": 4,
    "浛浛": 5,
    "沈注": 10,
    "種種盗擾": 4,
    "寅時": 9,
    "卯時": 4,
    "無勝衰則當明": 4,
    "熱惡寒戰慄": 5,
    "狂禽異獸戲": 4,
    "對三光濡溺": 4,
    "負四重深恩": 4,
    "觸冒風寒暑濕": 4,
    "蒼术芍藥湯": 23,
    "崔宣武通聖散": 23,
    "黄連瀉心湯": 75,
    "當歸承氣湯": 119,
    "導氣枳殼丸": 49,
    "斷魔如聖丹": 23,
    "風當歸飲子": 30,
    "黄連香薷飲": 119,
    "劉庭瑞通聖散": 23,
    "龍腦潤肌散": 23,
    "麥門冬飲子": 56,
    "密補固真丹": 49,
    "調胃承氣湯": 84,
    "罌粟神聖散": 23,
    "梔子檗皮湯": 23,
    "梔子厚朴湯": 126,
    "追風托裏散": 23,
    "\n三一承氣湯": 84,
    "梔子檗皮湯\n大梔子": 52,
    "將藥貼傷處": 52,
    "兒痞積疳癆": 52,
    "乾藥\n白礬": 52,
    "茵": 53,
    "温濕": 120,
    "黄連阿膠湯": 56,
    "吴勉學校\n": 40,
    "湯　": 130,
    "無問風寒暑濕": 103,
    "諸邪": 295,
    "譫語": 760,
    "畜熱": 191,
    "茵陳蒿湯調": 46,
    "桂苓甘露飲": 84,
    "據此藥品種": 40,
    "當歸\n發黄\n": 40,
    "枳殼\n剛柔二痓\n": 40,
    "桂五苓桂苓": 40,
    "後氣閉欬嗽": 40,
    "季夏戊己傷": 26,
    "小兒諸疳積熱": 26,
    "小兒風熱瘡疥": 26,
    "劉庭瑞通聖": 26,
    "\n換骨丹\n": 26,
    "癱瘓": 26,
    "風癎": 559,
    "頌曰": 26,
    "氣壯": 26,
    "芎术芷": 26,
    "龍麝": 26,
    "萬": 27,
    "龍腦": 355,
    "湯調補": 26,
    "鉛紅": 26,
    "癮疹": 64,
    "白礬灰": 26,
    "臨臥": 31,
    "金　荆芥穗": 26,
    "紅豆": 26,
    "産後風熱搐搦": 26,
    "\n勝金丸\n": 26,
    "\n厥逆證\n膺腫頸": 41,
    "風氣與陽明": 41,
    "風熱與陽明": 41,
    "何首烏防風": 41,
    "腦風證\n風氣": 41,
    "\n首風證\n新沐": 41,
    "併風毒壅滯": 41,
    "痹證\n風寒濕": 41,
    "\n熱痹證\n陽氣": 41,
    "\n膽癉證\n謀慮": 41,
    "馬練花陳皮": 41,
    "諸痹證\n痹": 41,
    "據本藥名稱": 97,
    "岐伯稽首對": 33,
    "\n諸證標目": 33,
    "熱盛則陽絡": 33,
    "據文義醫理": 33,
    "煎厥證\n陽氣煩勞": 33,
    "薄厥證\n陽氣": 33,
    "麥門冬檳榔": 33,
    "\n脹證\n濁氣": 33,
    "吴茱萸湯\n": 33,
    "\n風厥證\n一陽一陰發": 33,
    "\n結陽證\n": 33,
    "\n結陰證\n結陰": 33,
    "解證\n冬脈": 33,
    "勞風證\n發": 33,
    "鼻淵證\n膽移熱": 33,
    "衄衊證\n膽": 33,
    "\n防風當歸飲子": 20,
    "裏多則發熱": 20,
    "丹\n補養腎氣": 20,
    "何首烏丸\n": 20,
    "痔瘻痃癖氣塊": 20,
    "六氣變": 13,
    "\n子午歲": 78,
    "凜冽": 34,
    "暑將": 13,
    "蟄蟲復": 13,
    "爲風雨凝寒": 13,
    "羽蟲": 76,
    "寒風": 100,
    "爲天正舒榮": 13,
    "應順": 13,
    "雲趨": 13,
    "瘡發": 74,
    "熱昏憒": 13,
    "膿瘡": 26,
    "癘疾": 14,
    "\n辰戌": 38,
    "巳亥歲": 49,
    "間熱": 13,
    "華霜雪": 13,
    "殺氣": 13,
    "寒雨數": 13,
    "厥陰包絡鄉": 13,
    "少陰脈貫腎": 13,
    "陽明與太陰": 58,
    "\n論標本\n經言": 13,
    "見子": 52,
    "\n歲會\n運": 13,
    "戊爲火運": 67,
    "惡寒瞀悶悸驚": 13,
    "陽明燥勝木爲殃": 13,
    "蓋日光曦輝": 13,
    "七曜緯虚": 13,
    "玄生神": 179,
    "風火暑濕": 13,
    "銷鑠炎赫": 13,
    "肅殺慘悽": 13,
    "凜冽嚴凝": 13,
    "清聖祖玄燁諱": 13,
    "眩支脇驚駭": 13,
    "歲太商金勝": 13,
    "尻陰股膝髀腨": 13,
    "聖祖玄燁諱": 36,
    "熱瘡瘍疿疹癰痤": 13,
    "復則名木蒼凋": 13,
    "復則大風": 13,
    "埃濕": 13,
    "霧朦": 13,
    "騖溏": 15,
    "燥爍": 13,
    "繇復": 13,
    "黅穀": 13,
    "勝無必": 13,
    "陽明裏熱極": 33,
    "山澤埃昏": 4,
    "霿霧數": 4,
    "殺氣來": 4,
    "蒼乾": 41,
    "金勝": 14,
    "山澤": 4,
    "林莽聲悽": 4,
    "寒雰結爲": 4,
    "大關節": 10,
    "痞堅": 56,
    "白埃": 4,
    "鳴眩轉": 10,
    "山澤燔燎": 4,
    "材木": 32,
    "廣厦騰煙": 4,
    "風行惑言": 4,
    "臚脹": 16,
    "瘍疿嘔": 4,
    "瘛瘲": 79,
    "温瘧": 415,
    "瞀悶": 10,
    "動復": 4,
    "華發": 4,
    "焰陽午澤": 4,
    "危然": 4,
    "奇狀": 4,
    "松虎　": 4,
    "後報": 4,
    "發無": 16,
    "金發": 8,
    "曛昧": 28,
    "熱過極": 5,
    "爲注烈風": 4,
    "淫潰": 4,
    "亢則": 53,
    "斯道": 248,
    "悉明": 27,
    "憒憒": 139,
    "胠脇氣併": 4,
    "飲食": 79,
    "熱甚": 279,
    "氣遊": 4,
    "火勝": 4,
    "熱客": 129,
    "善驚譫妄": 4,
    "介蟲": 19,
    "左胠脇": 5,
    "華英": 7,
    "毛蟲": 166,
    "嗌塞": 4,
    "寒勝則凝凓": 4,
    "濕復": 8,
    "濕變": 4,
    "火復則大熱將": 4,
    "驚瘛": 4,
    "數憎風": 4,
    "寒極": 55,
    "嗌絡": 4,
    "爲胕腫": 4,
    "燥復": 4,
    "森木蒼乾": 4,
    "氣歸": 16,
    "寒復": 26,
    "厥氣": 30,
    "厥　": 4,
    "謂司天金": 4,
    "餘氣": 91,
    "\n主勝爲": 4,
    "頸項": 188,
    "爲丹熛瘡瘍": 4,
    "瞀熱": 4,
    "爲鶩溏": 26,
    "復罷": 4,
    "復氣": 4,
    "瞑甚": 4,
    "則熱": 171,
    "嗌腫": 17,
    "適氣": 9,
    "金爲": 18,
    "鹹補": 10,
    "鴨溏": 89,
    "勝氣": 4,
    "傷寒標": 44,
    "傷風\n傷風": 44,
    "肢節煩": 44,
    "乾嘔": 393,
    "脈陽浮": 44,
    "陽明傷寒": 44,
    "解明": 44,
    "熱頭": 153,
    "發熱煩": 61,
    "裏熱甚": 44,
    "脈沈": 355,
    "關節煩": 44,
    "\n風寒": 44,
    "爲傷寒": 265,
    "爲傷風": 50,
    "風則傷衛": 46,
    "寒則傷營": 44,
    "營衛俱傷": 50,
    "大青龍湯": 128,
    "爲裏": 96,
    "風寒暑濕": 158,
    "覺身熱頭": 44,
    "傷寒疫癘": 73,
    "風氣雜": 59,
    "裏熱極甚": 44,
    "煩渴譫妄": 70,
    "湯爲": 44,
    "餘熱": 662,
    "遺熱勞復": 59,
    "風眩頭": 78,
    "産後諸疾": 44,
    "小兒驚風積熱": 59,
    "瘡瘍疹痘諸證": 59,
    "無問日數": 44,
    "通聖散": 44,
    "\n裏證\n凡裏證": 44,
    "實數": 129,
    "脈雖浮數": 44,
    "據本書": 1797,
    "許復熱煩": 44,
    "濕熱利": 44,
    "諸濕熱": 57,
    "頻併": 64,
    "陰脈漸生": 44,
    "喪明": 100,
    "譫語遺": 50,
    "\n兩感\n兩感謂": 44,
    "陽明與": 57,
    "瘈瘲": 130,
    "無問風寒暑濕雜": 44,
    "潮熱屬陽明": 44,
    "陽明裏熱極甚": 70,
    "熱甚欬悶亂": 44,
    "三一承氣湯": 182,
    "無問痞脈浮沈": 44,
    "裏熱勢惡": 50,
    "約三時許": 44,
    "譫妄昏": 44,
    "關脈沈數": 44,
    "譫語\n譫語發狂": 44,
    "傷寒過經譫語": 44,
    "\n發黄\n陽明": 44,
    "\n發斑\n發斑": 44,
    "\n發狂\n傷寒": 44,
    "\n發厥\n": 44,
    "煩冤悶亂": 51,
    "脈雖疾數": 57,
    "畜熱極": 50,
    "脈沈細": 64,
    "兩感勢": 57,
    "殘陰": 53,
    "蓋陽氣後竭": 44,
    "積熱漸": 44,
    "脈漸": 80,
    "脈復": 59,
    "熱極厥": 44,
    "敝芾甘棠": 44,
    "牀\n陽明": 44,
    "濕熱痞閉積滯": 14,
    "補五勞七傷": 20,
    "注顔延壽": 14,
    "飢飽勞損": 20,
    "憂愁思慮": 24,
    "陰虚熱": 14,
    "穢垢": 14,
    "解利傷寒發熱": 14,
    "産母": 29,
    "則熱結頓開": 14,
    "産後諸": 69,
    "無熱": 220,
    "豈知": 55,
    "时審": 14,
    "將爲": 31,
    "濕熱痞悶積滯": 14,
    "療小兒驚疳積熱": 14,
    "阿膠梅連丸\n": 14,
    "黄連　當歸": 25,
    "小兒驚疳積熱": 32,
    "膩脂肥發熱": 14,
    "\n二勝丸\n": 14,
    "御米殼　當歸": 14,
    "熱消穀善飢": 26,
    "\n調胃承氣湯": 41,
    "熱甚喘欬悶亂": 32,
    "陽明胃熱發斑": 26,
    "則裏熱亢極": 26,
    "\n十棗湯\n": 26,
    "見證將發黄": 26,
    "小兒吐瀉驚風": 26,
    "梔子豉湯\n": 26,
    "則無大段熱": 26,
    "熱毒煩悶　": 26,
    "進益美飲食": 26,
    "\n狀元丸\n": 26,
    "結胸證狀補": 26,
    "痃癖堅積腸垢": 26,
    "導滯定功丸": 26,
    "積食積諸積": 26,
    "狀若山嵐時": 26,
    "金鍼丸\n治陽絶": 12,
    "吴葛劉勉雍": 49,
    "則嗌乾頷腫": 30,
    "\n十干夫婦": 30,
    "諸痛癢瘡瘍": 50,
    "厥陰風木肝譫": 30,
    "脈見諸陽爲": 30,
    "夫脈沈數爲裏熱": 30,
    "沈遲爲裏寒": 30,
    "沈數爲裏熱": 30,
    "\n結代脈\n": 30,
    "金火合則熱": 8,
    "夫陰陽與衰": 8,
    "豈知腸胃燥熱怫": 8,
    "與大腸熱結": 22,
    "熱藥温補腎": 15,
    "謂陽實陰虚": 15,
    "寒藥養陰瀉熱": 8,
    "爲瀉實補衰": 8,
    "言標與本異": 8,
    "變水腫腹脹": 8,
    "將層級壓籬": 8,
    "霍司承君祥處": 8,
    "詳爲刊正云": 15,
    "悟公師親驗過": 15,
    "當歸龍骨丸\n治月": 22,
    "産後寒熱運悶": 22,
    "枳實檳榔丸": 22,
    "夏熱則萬物濕潤": 18,
    "厥陰與少陽爲": 5,
    "爲消狂瘡腫": 9,
    "減續命湯隨證": 9,
    "小兒驚癎搐": 9,
    "陽脈與陽明脈": 9,
    "\n夫傷寒陰陽": 6,
    "乾陽特爲熱": 6,
    "安危壽夭併": 6,
    "謂腎藏陰難": 6,
    "陽熱變爲陰寒": 6,
    "證\n夫傷寒": 19,
    "遺熱勞復諸疾": 6,
    "證\n夫傷風": 6,
    "風寒\n頭項": 6,
    "無問傷寒雜": 18,
    "傷寒陽明胃熱發斑": 12,
    "傷寒熱極將": 6,
    "\n大承氣湯": 6,
    "發熱爲裏熱": 11,
    "與小承氣湯": 32,
    "\n謂胃承氣湯": 6,
    "裏兩證熱勢": 6,
    "類善開結滯": 6,
    "論善開結怫熱": 6,
    "緊斂堅結滯": 6,
    "傷寒裏熱極": 6,
    "俗醫妄謂陰寒": 6,
    "\n梔子豉湯": 6,
    "則萬物濕潤": 6,
    "裏證\n傷寒": 13,
    "風熱火爲陽": 13,
    "寒濕燥爲陰": 13,
    "小青龍湯\n": 13,
    "細辛　乾薑": 13,
    "開怫熱結滯": 28,
    "馬\n劉宗守素真": 12,
    "傳庚桑楚六衍": 12,
    "六衍": 12,
    "吉兇徵兆": 12,
    "戊癸離宫號": 12,
    "甲丙戊庚壬": 14,
    "乙辛丁癸己": 12,
    "戊爲太徵火": 12,
    "亢氐昴畢庚": 12,
    "張翼婁胃辛": 12,
    "從卯辰巳午": 12,
    "從酉亥子丑寅": 12,
    "言陽氣": 13,
    "將復": 12,
    "甲己黅": 12,
    "乙庚素": 12,
    "丁壬青蒼爲角木": 12,
    "戊癸丹赤應徵火": 12,
    "五太甲丙戊庚壬": 12,
    "丁癸辛己": 12,
    "氣積": 214,
    "運風清熱": 12,
    "清熱勝復": 12,
    "丁乃木": 12,
    "金章宗明昌": 12,
    "從子": 28,
    "厥陰司天": 75,
    "春風勝": 21,
    "夏熱勝": 42,
    "太陰司天": 42,
    "秋金旺": 28,
    "陽明司天": 58,
    "太陽司天": 21,
    "子午少陰君火暑": 21,
    "卯酉陽明": 42,
    "巳亥厥陰木風舉": 21,
    "子爲陽氣": 42,
    "午爲陰氣": 42,
    "周普天": 21,
    "陰終": 21,
    "陽終": 21,
    "災危": 42,
    "後學醫流": 42,
    "少陰君火司天": 21,
    "司天與運": 21,
    "壬爲木運": 21,
    "癸爲": 42,
    "庚爲": 56,
    "丁與壬": 42,
    "申子辰": 82,
    "巳酉丑": 21,
    "寅午戌": 85,
    "亥卯未": 42,
    "丁與年運": 21,
    "丙與辛合": 21,
    "丁與壬合": 21,
    "戊與癸合": 21,
    "時見發凝慘": 21,
    "申未": 144,
    "子午卯酉": 72,
    "夏熱當午": 21,
    "秋凉當": 21,
    "丑寅": 46,
    "土運司天": 21,
    "爲主運": 63,
    "金司天": 615,
    "木司天": 126,
    "廢癰腫瘡瘍": 21,
    "據文義乙轉": 21,
    "子午少陰君火": 21,
    "巳亥厥陰風木": 21,
    "子少陰君火": 21,
    "東北兖司當": 21,
    "四維發埃昏": 21,
    "丁與壬爲夫婦": 21,
    "夏熱皮膚癢": 32,
    "瘡疹總論　": 31,
    "風熱上客陽明": 31,
    "憂思則氣結": 31,
    "熱毒瘰癧腫": 31,
    "龍腦潤肌散\n": 31,
    "紅玉梃子\n": 31,
    "膽熱": 40,
    "負任擔荷": 31,
    "郤子": 31,
    "蘆葦葉": 31,
    "葵子": 393,
    "臨時": 50,
    "栝蔞湯": 31,
    "興陽固腎補虚": 31,
    "石蓮子": 31,
    "箋香": 31,
    "痔瘻總論\n夫腸風": 8,
    "與石榴研細後": 8,
    "厥陰爲風木": 3,
    "總論": 80,
    "墜涎": 27,
    "栝蔞丸\n": 27,
    "煩喘": 27,
    "壯熱": 1874,
    "連進": 95,
    "栝蔞丸": 27,
    "據本藥製": 27,
    "葶藶散\n": 27,
    "補養": 176,
    "孕婦": 104,
    "五勞七傷": 27,
    "\n神應丹": 27,
    "涎嗽喘滿": 27,
    "畜熱發戰": 27,
    "無問寒濕濕熱": 27,
    "瀉利": 27,
    "\n揀桂": 27,
    "爲餅子": 27,
    "御米殼": 54,
    "熱嗽喘": 27,
    "蘿蔔子湯臨": 27,
    "涎喘滿": 27,
    "紫團參": 27,
    "磁合子": 27,
    "則結滯頓開": 15,
    "從意續續飲": 15,
    "茵陳蒿湯\n茵陳蒿": 15,
    "黄　山梔子": 15,
    "傷寒濕熱極甚": 15,
    "\n泛論\n凡傷寒熱": 15,
    "則陽盛陰衰": 15,
    "\n戰汗\n夫熱": 15,
    "陽氣怫熱結": 15,
    "惡寒戰慄譫妄": 15,
    "謂少陰君火熱氣": 15,
    "爲陽勝陰虚": 30,
    "爲陰勝陽虚": 15,
    "爲兩重發熱": 15,
    "經云戰慄動搖": 15,
    "爲陽火熱氣": 15,
    "陽熱易爲畜熱": 15,
    "\n汗候\n雙": 15,
    "億覺身熱頭": 15,
    "據本藥炮製": 15,
    "論\n夫傷寒": 15,
    "兒急驚風搐": 15,
    "則無勝復淫泆災眚": 6,
    "聾渾渾焞焞": 6,
    "猶君刑臣過": 8,
    "當瀉脾補腎": 6,
    "熱争則狂言": 6,
    "經云風熱火": 5,
    "金燥雖屬秋陰": 5,
    "經云諸澀枯涸": 5,
    "臨卧時併進": 5,
    "寒戰爲裏熱": 4,
    "\n古聖訓陰陽爲": 4,
    "何暇數日哉": 1,
    "從標則太陽發熱": 1,
    "從標則肌熱": 1,
    "從本則脈沈實": 1,
    "吴勉學校\n平陽馬宗素": 2,
    "傷寒六經傳": 4,
    "無問傷風傷寒": 2,
    "經云諸痛癢瘡瘍": 2,
    "無妄謂傷寒": 2,
    "蓋藥氣從順": 2,
    "爲嚏嘔瘡瘍": 5,
    "鼽尻陰股膝髀腨": 5,
    "毛羽倮介鱗": 5,
    "司天風勝藥": 5,
    "藥歸五藏體": 5,
    "則霿霧清瞑": 5,
    "則凝肅慘慄": 5,
    "蓋肺爲華蓋": 5,
    "雖小兒誕生": 13,
    "爲火熱過極": 13,
    "鶩溏爲利當": 9,
    "太陽爲協熱利": 9,
    "陽明爲痼瘕": 9,
    "\n雜例\n溲": 9,
    "陽明二經證": 9,
    "仲景論厥陰經": 9,
    "枳實飲子\n": 11,
    "罌粟神聖散\n": 11,
    "當歸木香湯": 11,
    "鎔黄蠟爲丸": 5,
    "廢則神機化滅": 2,
    "無愆陽伏陰": 1,
    "\n夫仁固衛": 1,
    "齒爲鳴天鼓": 2,
    "熱争則狂驚脇滿": 11,
    "變生風熱諸": 11,
    "柴胡飲子\n": 11,
    "小兒疳積熱": 11,
    "當歸龍膽丸": 22,
    "熱客毒逐經諸變": 13,
    "閭閻　民間": 13,
    "連六國從親": 13,
    "驕陽化爲霖": 13,
    "當歸承氣湯\n當歸": 7,
    "雷頭風\n夫": 3,
    "餅爲丸桐子": 5,
    "云虙瘕爲沈": 1,
    "雖瘧論言陰勝": 1,
    "陽實則脈當實數": 1,
    "屬少陰君火": 1,
    "視龍馬靈龜": 3,
    "謂兩體容儀": 3,
    "劉守真謹序\n": 1,
    "將太古靈文": 1,
    "太陰經風藥": 2,
    "當利刺厥陰": 2,
    "發寒熱無時": 2,
    "濕爲積飲痞": 1,
    "聞木音則惕": 1,
    "嚏則壅滯開": 1,
    "經言消癉熱": 1,
    "則衆邪難傷": 1,
    "石藥發癲狂": 1,
    "金雖屬秋陰": 1,
    "陽熱易爲結": 1,
    "辛熱開衝風熱結滯": 1,
    "猶陽明證熱": 1,
    "當大承氣湯": 1,
    "則爲積飲痞": 1,
    "仲景言傷寒裏熱": 1,
    "經言動物神機": 1,
    "熱則息數氣麤": 1,
    "熱甚則爲嘔": 1,
    "湯類甘辛熱藥發": 1,
    "熱極則日晡": 1,
    "法當大承氣湯": 1,
    "錢氏香連丸": 1,
    "辛甘熱藥屬陽": 1,
    "則腸胃怫熱結": 1,
    "間則陰氣衰殘": 1,
    "惡寒戰慄論": 1,
    "爲驟注烈風雨淫潰": 1,
    "熱生癰腫瘡瘍": 1,
    "小滿屬君火": 1,
    "陽氣與邪熱": 1,
    "\n諸痛癢瘡瘍": 1,
    "太過則赫曦": 1,
    "\n諸濕腫滿": 1,
    "尻陰股髀腨胻": 1,
    "厥陰風木勢甚": 1,
    "熱氣甚則然": 1,
    "\n諸澀枯涸": 1,
    "澀涸乾勁皴": 1,
    "莫漫多方立紀綱": 2,
    "當歸　檳榔": 2,
    "當從太陰經": 2,
    "\n文武實\n": 1,
    "王冰次注序云": 1,
    "與天師岐伯": 1,
    "與夫史稱扁鵲": 1,
    "云腎經積熱": 1,
    "金代完顔亮": 1,
    "雖軒岐復生": 1,
    "荀吴帥師敗狄": 1,
    "發明太古靈文": 2,
    "臑盡處爲肘": 2,
    "毛際兩傍動脈": 2,
    "郄疵對智伯": 2,
    "劉完素醫術": 1,
    "醫廟劉完素祀": 1,
    "縱觀劉完素": 1,
    "仲景三陽經": 1,
    "發揮劉河間": 1,
    "傷寒三陽經": 1,
    "劉河間傷寒": 1,
    "簡稱懷德堂": 1,
    "對古奥難明": 1,
    "沈伏則陽虚陰實": 1,
    "黄水灸脾俞": 1,
    "古聖訓陰陽爲": 1,
    "\n脈循脇絡": 1,
    "觀萬物熱極": 1,
    "況法曰身熱爲熱": 1,
    "蓋水火陰陽寒熱": 1,
    "嘗聞鶡冠子": 1,
    "宋臣高保衡": 10,
    "舛文": 14,
    "杜注": 201,
    "营泣卫": 43,
    "弛缓": 275,
    "盖痿跛": 12,
    "菀莝陈": 48,
    "亢强": 6,
    "啖饴": 2,
    "悒悒": 112,
    "郁迳": 2,
    "暑胜": 131,
    "夏飧": 59,
    "劳逸": 56,
    "沥淅": 50,
    "岁木": 663,
    "灸脾俞": 50,
    "艾炷子安": 92,
    "艾烟": 299,
    "甘辛平": 125,
    "甘酸平": 118,
    "王不留行": 2740,
    "艾卷": 792,
    "艾条": 219,
    "中华中医药协会常务理事": 14,
    "Marnae Ergil": 8,
    "痫瘛": 99,
    "譩譆": 135,
    "榔槌": 12,
    "季秋痹": 82,
    "火木": 78,
    "击仆": 1,
    "\n帝": 2116,
    "\nJX": 1,
    "\nJ\\天癸": 1,
    "养慎": 1,
    "干忤": 1,
    "寂然": 1,
    "喑喑然": 54,
    "耀山云": 1,
    "\n俞": 28,
    "二宫献彦可": 17,
    "谷实蒌苽": 2,
    "\n胫": 12,
    "布绵": 2,
    "膒脂": 2,
    "芩　芎": 2,
    "\nJT渍": 2,
    "JU渍": 2,
    "\nJV生": 2,
    "\nJZ龙": 2,
    "髀楗": 11,
    "陈石灰": 6382,
    "李　顺　录\n辨": 2,
    "僭肆": 1,
    "锲胫": 1,
    "言灸": 1,
    "旋踵": 3,
    "jie介": 1,
    "二陈": 1,
    "胡葈": 6,
    "葈耳实": 1,
    "茈音": 17,
    "味辛温": 152,
    "蚳母": 46,
    "蝭母": 41,
    "味辛平": 66,
    "味辛寒": 29,
    "巅顶": 92,
    "癥坚": 512,
    "檀桓": 70,
    "安志": 117,
    "梅实": 393,
    "桃蠹": 8,
    "卷舒": 44,
    "\n振梃": 1,
    "振梃": 20,
    "\n通木": 1,
    "杉篱": 6,
    "楗JV": 1,
    "JT讫": 1,
    "夏令": 572,
    "妇曰": 1,
    "妇亟": 1,
    "何奇": 30,
    "翟义": 103,
    "巧屠": 110,
    "索痉": 32,
    "戍卒": 2,
    "\nJU": 1,
    "\nJV": 1,
    "陈麝香": 1,
    "梁·释家深": 1,
    "隋·巢元方": 9,
    "RE⁃LY": 55,
    "希氏束电图研究": 55,
    "0718⁃9306": 13,
    "宋神宗赵顼": 2,
    "宋哲宗赵熙": 2,
    "胫纵": 150,
    "暓昧": 1,
    "矇昧": 24,
    "暓瘈": 2,
    "亸曳": 11,
    "暓闷": 1,
    "\n予": 59,
    "僭燥": 1,
    "　僭": 1,
    "郁积": 43,
    "　颙伺": 1,
    "　矢": 1,
    "何吾子": 14,
    "睑眦": 180,
    "\n生犀": 3,
    "阿佉尼阿毗罗莫多梨婆地梨娑诃": 1,
    "\nIgA": 43,
    "俾邪": 133,
    "炒子芩": 54,
    "子芩": 2028,
    "脉泣": 290,
    "俞注": 212,
    "方中生龙牡": 18,
    "宗筋弛缓": 7,
    "糖尿病": 163,
    "金创": 1,
    "陈瘀": 124,
    "060801": 1,
    "嗽自平": 1,
    "翁老喜": 19,
    "白癞赤癞": 3,
    "拜糖苹": 4,
    "痹祺": 1,
    "060811": 1,
    "060822": 7,
    "黄腻苔": 299,
    "法平": 1,
    "涵濡": 93,
    "太罗": 1,
    "莱": 1,
    "箕子": 125,
    "金曰": 507,
    "洛书\n洛": 2,
    "\n二": 60,
    "林气": 71,
    "牝牡": 238,
    "王音": 1,
    "雉鸣": 2,
    "获麟": 55,
    "感麟": 1,
    "牝脏": 3,
    "牡牝": 136,
    "亢氐昴毕": 128,
    "燕曰": 2,
    "月廓": 127,
    "清辉": 1,
    "穹窒": 18,
    "形寒寒": 2,
    "皏然": 9,
    "焦绝": 17,
    "泝然": 16,
    "洒淅": 53,
    "鸡鹜": 1,
    "阳经": 325,
    "马鸣": 373,
    "牛鸣": 13,
    "宗祀": 1,
    "盱衡": 1,
    "悉言": 13,
    "乐": 1,
    "宦世安": 26,
    "张子和书云": 1,
    "大冢敬节": 104,
    "白薇泽兰": 1,
    "全国人大副委员长": 4,
    "扑尔敏": 29,
    "息斯敏": 53,
    "宦老": 2,
    "唾涎沫": 451,
    "荣虚": 490,
    "愦愦然": 613,
    "怳怳": 271,
    "沽漉漉": 21,
    "痂癞": 32,
    "暮躁": 125,
    "聂聂动": 141,
    "瘅疟牝": 10,
    "云何": 196,
    "瘕言": 10,
    "疟寒": 69,
    "柔痉": 657,
    "食顷": 14,
    "陈寒": 1211,
    "方\n薤": 33,
    "尸蹶": 38,
    "叁风": 12,
    "肆悸": 12,
    "蛔厥": 521,
    "益躁疾": 5,
    "洁洁": 18,
    "丸梧子": 200,
    "陈滞": 80,
    "濈然": 49,
    "凝坚": 37,
    "癥痼害": 48,
    "癥痼": 234,
    "蒲灰": 30,
    "林檎": 466,
    "安石榴": 115,
    "胡荽": 113,
    "子余": 22,
    "叶圆": 52,
    "黍穰": 49,
    "荠苨": 317,
    "疾疢竞": 50,
    "王时": 20,
    "麋脂": 36,
    "葫荽": 34,
    "方\n鲙": 16,
    "江水": 43,
    "王色青": 3,
    "信斯道": 1,
    "斯喘": 93,
    "\n文": 111,
    "麝絮": 53,
    "藤晶": 4,
    "夜寒": 4,
    "皮苓": 196,
    "邕空七军": 1,
    "朱夫妇二人": 1,
    "兴未艾": 1,
    "昭彰": 6,
    "梁·陶弘景": 102,
    "金元四大家": 169,
    "厥阴蚘厥": 5,
    "蚘厥": 167,
    "灸厥阴": 314,
    "阳郁生": 1,
    "阳复神安": 18,
    "懊烦郁": 9,
    "腐秽": 28,
    "培母": 18,
    "温温愦愦": 16,
    "君何": 26,
    "泾注云": 57,
    "温涤": 22,
    "辛烈": 218,
    "涎清": 5,
    "寒郁阳": 20,
    "袒衣露": 1,
    "昔喻嘉言": 13,
    "姜附": 165,
    "赵养葵云": 21,
    "趺阳脉": 9,
    "神佑": 22,
    "润濡": 58,
    "苓泽": 284,
    "苍气达": 26,
    "余细察": 2,
    "炎帝神农氏": 83,
    "余揆度": 1,
    "秽腐": 1,
    "憺憺": 315,
    "潜风阳": 14,
    "拇趾": 1490,
    "夫寒客": 1,
    "阳煦": 15,
    "痞鞕": 98,
    "荣阴": 57,
    "金成": 1,
    "林亿精": 1,
    "云霓": 60,
    "醽醁": 8,
    "阙毋煚": 5,
    "叶痿": 25,
    "涤衣垢": 2,
    "颜枯肌馁": 3,
    "七癥八瘕": 56,
    "菇荑": 1,
    "成丸": 134,
    "抿子": 2,
    "垍器盛": 1,
    "痁疟": 22,
    "齁鼾嗽": 1,
    "苏薄荷": 864,
    "\n松萝": 2,
    "槐荚": 9,
    "阳蹻": 185,
    "黄赤脂": 4,
    "锐眦": 85,
    "\n桂": 1,
    "陈白梅": 4,
    "陈栗": 1,
    "余消澄": 1,
    "榴子": 67,
    "米糖": 1,
    "沐风": 4,
    "陈神曲": 56,
    "溺垢": 1,
    "江子": 60,
    "陈槐花": 2,
    "痖疯": 1,
    "陈糙米": 1,
    "陈莱菔英": 4,
    "愦怖": 1,
    "壅涎": 4,
    "石燕子": 4,
    "涎涕": 301,
    "\n柏枝": 1,
    "候涎": 1,
    "陈阿胶": 224,
    "风客阳": 14,
    "蠷螋": 101,
    "糁粟": 23,
    "陈物": 1,
    "安惊": 2,
    "盛子": 1,
    "陈小粉": 766,
    "陈细茶": 29,
    "沐发": 212,
    "沆瀣丹": 161,
    "幸毋": 86,
    "黄芒瘴": 120,
    "陈香椽": 45,
    "诃黎": 46,
    "托里": 605,
    "姜滓": 2,
    "夏宣": 1,
    "秋宣": 1,
    "齁䶎": 2,
    "荈音舛": 25,
    "陆羽": 435,
    "杨慎": 55,
    "荼茗": 25,
    "凌冬": 99,
    "凌露": 44,
    "涵澹然": 23,
    "柳芽": 13,
    "茅芦竹箬": 5,
    "尤奇": 27,
    "姚伯道云": 17,
    "谢赐茶启云": 17,
    "桑苎": 17,
    "滓厥": 17,
    "秋雨冽": 17,
    "皓皓然": 17,
    "斯沟渎": 17,
    "麰麳": 17,
    "厥咎悭": 17,
    "厥咎怠": 17,
    "汲泉": 17,
    "云光滟潋": 17,
    "徒豪": 17,
    "罂铫鉒": 17,
    "衡鉴": 17,
    "襜然": 17,
    "罗膏土": 17,
    "叶少": 18,
    "莫若余": 17,
    "睹芝芬": 17,
    "眠云跂石": 17,
    "瓯\n瓯": 24,
    "唐毋炅云": 1,
    "涤垢": 110,
    "方龙潭": 58,
    "江麓平云": 1,
    "炙膊": 1,
    "壶公": 2,
    "咀啜": 7,
    "唐本注云": 20,
    "唐补阙毋炅": 7,
    "颜师古云": 21,
    "\n戊": 6,
    "匝月": 506,
    "沉菏": 1,
    "莱菔": 476,
    "瞑眩": 143,
    "俾坤元": 1,
    "斯日健": 1,
    "孝廉华卓卿": 2,
    "\n雅": 1,
    "茶铛": 1,
    "膺脘痞": 1,
    "\n杨": 2,
    "酉戌": 91,
    "霞蔚云": 1,
    "何乐": 508,
    "云索": 16,
    "哕恶": 28,
    "养愚": 1,
    "\n祖愚": 1,
    "日铸": 1,
    "疟痢安": 1,
    "痧秽": 2,
    "予索": 1,
    "芎䓖": 6,
    "啜安": 3,
    "梦梦": 1,
    "痢生": 1,
    "纤芥滓秽": 5,
    "涎丹": 789,
    "徽歙金子陶": 1,
    "荼声": 1,
    "松罗": 12,
    "叶曰苦丁": 1,
    "山岚瘴障疠": 1,
    "金成无己": 95,
    "夜思": 133,
    "祷祀": 20,
    "弗福": 20,
    "俞桥": 108,
    "郁多": 31,
    "凌德": 20,
    "昔云": 22,
    "毋意驰": 37,
    "毋志": 37,
    "于斯": 323,
    "余历": 54,
    "乐子": 20,
    "思习": 20,
    "莫易": 26,
    "卒尔": 116,
    "叶萎": 432,
    "愚鲁": 20,
    "思虑": 42,
    "过喜": 29,
    "喜乐": 65,
    "唾清涎": 29,
    "黄宫绣": 895,
    "湛然": 219,
    "神斯清": 132,
    "方寤": 78,
    "氟哌噻": 52,
    "成天癸": 29,
    "延嗣丹": 23,
    "\n梦遗": 39,
    "济火延嗣丹": 23,
    "瞀螈": 23,
    "嘈烦": 14,
    "毋怵惕": 104,
    "曲察劳": 39,
    "庄言": 71,
    "危言": 58,
    "习见习": 27,
    "谭曰": 84,
    "煌思": 27,
    "翁谓": 35,
    "王大怒": 31,
    "王怒": 157,
    "悉陈": 17,
    "秋忿": 60,
    "言无音": 18,
    "封君": 63,
    "艾治": 168,
    "涤唾": 12,
    "莫甚": 9,
    "癸元": 9,
    "许曰": 495,
    "金枯": 32,
    "眩瞀": 19,
    "涎结": 60,
    "予童": 15,
    "孔圣枕中丹": 224,
    "耽延": 11,
    "哕痞": 14,
    "贲豚": 199,
    "怫逆": 25,
    "淋溲": 15,
    "譬君王明圣": 15,
    "涸阳": 21,
    "瘕聚痃痞": 11,
    "黄云之笼翠岫": 11,
    "谭自此": 14,
    "厥旦": 71,
    "戃慌": 28,
    "君惝然": 14,
    "怊惝恍": 14,
    "宫蟾杉慈葵": 1,
    "蓟茅榆": 1,
    "姜枣喑痱济": 7,
    "芎苍神曲栀": 3,
    "陈佛荔楝子": 1,
    "芪饴": 1,
    "杜　": 28,
    "癥积康": 1,
    "荆防芷": 1,
    "藁夷": 1,
    "柴葛升": 2,
    "荆　": 1,
    "葛　": 10,
    "蹙踘": 17,
    "小溲涸": 1,
    "渠云": 6,
    "狂言": 212,
    "棠谿乐彦刚": 1,
    "企曰": 1,
    "乐初": 1,
    "邢争": 1,
    "卜曰": 66,
    "阳干": 12,
    "腥脍": 1,
    "绯绢": 21,
    "毋畏": 22,
    "君火司天": 133,
    "余复": 86,
    "俛卧儿": 1,
    "\n俚谚": 1,
    "\n凡膏粱": 1,
    "庸讵知": 103,
    "庸讵": 107,
    "形羸": 244,
    "聋瞽痿": 1,
    "枯涸皴": 8,
    "文云": 320,
    "盖君": 5,
    "伏龙": 70,
    "毋遗": 1,
    "余昔": 201,
    "田夫": 8,
    "渠素": 13,
    "忽晓": 2,
    "云风": 89,
    "余烈": 2,
    "金铃川栋": 1,
    "审言": 1,
    "青绿沫": 1,
    "濡润": 17,
    "济众云": 1,
    "缪哉": 1,
    "何讶": 1,
    "眦眶": 3,
    "木茂": 3,
    "痺塞": 7,
    "鼽衂": 4,
    "阳羸": 3,
    "面角儿": 1,
    "云伏瘕": 2,
    "镕矾": 1,
    "启玄子注云": 1,
    "谢轩岐万世恩": 1,
    "寒淫合": 6,
    "热淫合": 6,
    "湿淫合": 6,
    "火淫合": 6,
    "温淫合": 6,
    "暑淫合": 6,
    "600826": 2,
    "粱肥甘": 5,
    "麻杏": 54,
    "壅胪": 2,
    "风胜": 111,
    "迨寤": 5,
    "凶危": 111,
    "目蒙": 13,
    "壅塞": 626,
    "胫痠": 83,
    "滞生": 1,
    "叶茂枝荣": 19,
    "孟秋旭旦广东南海管炎威季耀": 2,
    "何竹林道盟惠": 2,
    "飚风": 2,
    "王　文　黄　荷　陈　民": 1,
    "王志群　焦　扬　王　辉": 1,
    "周　波　赵　晖　赵　晶": 1,
    "丑未辰戌土": 8,
    "  爱因斯坦": 9,
    "盛国荣论云": 5,
    "  皇甫燕": 8,
    "87491": 6,
    "刘张李朱子": 1,
    "033255": 1,
    "sellhheim氏": 13,
    "戚王熙斋君": 1,
    "讵意濯足甫毕": 1,
    "胥门马生泰": 1,
    "巴甫洛各夫": 1,
    "戚郑桐芳君": 1,
    "100021": 1,
    "712083": 22,
    "712046": 11,
    "衷中参西\n": 7,
    "\n热郁寒凝": 3,
    "植村藤治郎": 7,
    "侄婿天一仇澐": 7,
    "宋宁宗赵扩": 6,
    "施护\n施护": 28,
    "许　红　许　昕": 3,
    "孙忠人　严　芳": 3,
    "沈敏鹤　张　宁": 3,
    "张　冰　张　红": 3,
    "卢主任医师": 36,
    "元·曾世荣": 22,
    "江诚江抱一": 38,
    "ROCKⅡ": 17,
    "布特弗利卡": 12,
    "埃德加斯诺": 12,
    "安倍晋太郎": 13,
    "宗道臣二世": 13,
    "优秀毕业生": 42,
    "董德懋先生": 8,
    "全国人大常委会副委员长": 32,
    "  钦传光": 3,
    "  池述广": 1,
    "  原思通": 5,
    "白犀Cottoni": 1,
    "  臣君芳": 2,
    "嚏根草苷元": 1,
    "脂蟾毒苷元": 1,
    "野村新四郎": 1,
    "  尚志钧": 2,
    "Carrel JE": 1,
    "　　　龙　飞　史红专": 2,
    "杨　全　杨　滨": 2,
    "杨　柯　芳": 2,
    "王德立　朱　平": 2,
    "苏　钛　图　雅　布": 2,
    "龚　艺　青　鹏": 2,
    "龙　飞　钟世红": 2,
    "张　瑜　严　辉　陈　钢　石　芸": 2,
    "张水利　俞　冰": 2,
    "亮　孙　芳　赵　丽": 2,
    "黄　丹　徐　菲": 2,
    "汪　兰　易　艳": 2,
    "唐宋八大家": 30,
    "夏茂秋零阳主生": 3,
    "\n论　　脉\n凡": 6,
    "\n下　利\n凡": 187,
    "杂　证　谟\n呕　　": 8,
    "杂　证　谟": 6,
    "仲景云狐惑": 6,
    "\n论　积　垢\n凡": 13,
    "杂　证　谟\n": 26,
    "\n针　　灸\n凡": 5,
    "厥阳司天客胜": 4,
    "王守道风噤": 12,
    "\n论　惊　恐\n": 5,
    "余幸逢明盛": 11,
    "\n述　　古\n启玄子": 6,
    "0005860": 7,
    "\nLyon": 17,
    "清光绪皇帝": 37,
    "急性心肌炎": 1,
    "斯巴德何辞": 34,
    "丹波元胤云": 1,
    "金阊书林际云": 8,
    "唐廷扬梓行": 8,
    "蒲生贵子　": 1,
    "少阴君火司天": 411,
    "二十八九君": 1,
    "章庆云先生": 2,
    "08327": 2,
    "秦之济伯未": 6,
    "吴其浚宦游": 1,
    "宋仁宗景佑": 1,
    "陈砂麻竺麝": 2,
    "思君怀远志": 1,
    "华佗子歼厥魁": 1,
    "\nE\n二阳": 1,
    "柏茜茅丹荷": 1,
    "787491": 6,
    "袁世凯称帝": 1,
    "壁奎娄胃昴": 1,
    "\nAFLP": 2,
    "\nNgan": 7,
    "\nISSR\n": 2,
    "\nRAPD": 9,
    "  和志娇": 3,
    "  思彬彬": 3,
    "cyrrhiza uralensis": 3,
    "Marderosian AD": 3,
    "时珍国医国药": 120,
    "Lorenz JG": 3,
    "Kalanchoe laciniata": 1,
    "子Kadsura anamosma": 1,
    "CATCAAAAAAGATGATCAATGGTAGGAATTGCACTCTTTTTTTTGGTAATTTT\nGTAGAGAGTAGGGGG": 4,
    "AGAATCATCAAAAAAGATGATCAATGGTAGGAATTGCACTCTTTTTTTTGG\nTAATTTTGTAGAGAGTAGGGGG": 4,
    "A\nTCAATTTTTTTATTTAGGTCCTTGTTT": 4,
    "GTTAATTTATGGCAATGTCAT\nTTTTACCTGTGGTCTCAACCGGGAAGGATCTGTATAAACCAATTATACAATCATTCCCT\nCGACATTCTGGGCTATCTATCAAGTGCGCGGCTAAACCCTT": 4,
    "  Jo IH": 1,
    "Kim K": 1,
    "  Nagata": 1,
    "曹　月　曲　锋": 36,
    "0081607": 6,
    "0131539": 6,
    "0131506": 6,
    "\nShulman": 12,
    "黄　燕　李　俊": 7,
    "韩　云\n程　兰": 6,
    "\nER　　": 1,
    "获森规矩夫": 5,
    "辛甘温振卫阳": 23,
    "南朝宋文帝": 20,
    "北魏孝武帝": 12,
    "古贺十二郎": 12,
    "  曾聪彦": 6,
    "\na\nb\nc\nd\ne\nf\n": 4,
    "北京夜读轩": 2,
    "\nTinel": 1,
    "3022738": 1,
    "\n司徒红林": 1,
    "0133632": 1,
    "　　　　　": 45,
    "羟基尼奥宁": 1,
    "兴阳振凄栓": 23,
    "E.F.Adair": 16,
    "方后小注云": 1,
    "丁壬寅卯八": 18,
    "戊癸巳午七": 55,
    "甲己子午九": 34,
    "乙庚丑未八": 18,
    "丙辛寅申七": 67,
    "安-舒二氏": 76,
    "衄　　蛭　虻　谛": 1,
    "益见微文灿": 1,
    "朱子晦庵云": 1,
    "溷　龂　嚏　湫　疹　痂　癞": 1,
    "Sjögren": 76,
    "久保田晴光": 9,
    "王文选锡鑫": 2,
    "山田正珍云": 7,
    "叶大椿子容": 2,
    "辰刻诊脉濡": 1,
    "殷品之\n殷": 17,
    "隋•巢元方": 9,
    "66407": 8,
    "  F64\nFig": 1,
    "Tongue description": 1,
    "L\nlassitude": 23,
    "\nUACS": 7,
    "周仲瑛教授": 1,
    "栀曲　气畅郁舒": 16,
    "芩连砂朴实": 20,
    "芒硝义亦尔　": 9,
    "痔疟狂癫疾": 2,
    "陈石灰水澄": 7,
    "族祖灵文公": 7,
    "昔邑孝廉李": 4,
    "迨余久历斯": 9,
    "痼炼霞霞疴痼": 1,
    "椿樗椿樗乾樗樗": 1,
    "穄稷蕃稷伦稷啾唧友招稷": 1,
    "猎鹿絷鹿沈": 1,
    "蝥勺蝥廿蝥靛": 1,
    "德漠克利特": 40,
    "罗吉尔·培根": 30,
    "Roger Bacon": 30,
    "夏心火阳王": 1,
    "尻阴股膝髀腨䯒": 1,
    "宋徽宗赵佶": 97,
    "\n窦　　默": 1,
    "成无己注云": 1,
    "王太仆注云": 1,
    "葑酮": 7,
    "西托皂苷元": 4,
    "黄Ⅱ": 54,
    "黄Ⅲ": 54,
    "山茞": 7,
    "蔚香": 12,
    "桧烯": 7,
    "\n卯菱": 5,
    "子": 5,
    "\n苄": 9,
    "20ng": 9,
    "慎弗": 20,
    "异丁酰氧基哥伦比亚苷元": 16,
    "萹苻": 10,
    "岑皮": 17,
    "澄寒清碧": 6,
    "6g": 6,
    "王　茜　王　淳": 1,
    "上海市药理学会临床药理专业委员会主任委员": 1,
    "上海市药学会医院药学专业委员会副主任委员": 1,
    "上海交通大学医学院药学专业学术管理委员会主任委员": 1,
    "《中国新药杂志》": 1,
    "《国际药学研究杂志》": 1,
    "芩连栀郁朱": 4,
    "吉兰-巴雷": 8,
    "Ober氏": 56,
    "心理咨询医师": 1,
    "坤乾坎组合": 1,
    "\n元·罗天益": 11,
    "王旭高释云": 15,
    "杨上善著　内经太素": 2,
    "岐黄妙道朴": 2,
    "寿斯世夭札": 1,
    "刘明府少君": 4,
    "鲍觉生宫詹郁": 2,
    "疗风瘙瘾疹": 2,
    "杨右\n怀麟": 1,
    "\n四诊\n诸恙": 1,
    "唐左\n夭疽": 2,
    "施右\n怀麟": 2,
    "丁右\n血生": 1,
    "朱女\n痧子": 1,
    "今哲嗣仲英君": 1,
    "赵左\n厥阴": 1,
    "兹特首录陈": 2,
    "周甘仁甫志": 2,
    "元彦仲英谨": 1,
    "汪右\n怀麟": 1,
    "\nKuwabara": 10,
    "Nelken氏": 13,
    "Jose Barraquer": 5,
    "关泉廓": 179,
    "八廓": 119,
    "风廓": 41,
    "天廓": 9,
    "火廓": 17,
    "泽廓": 49,
    "山廓": 26,
    "胡\n": 922,
    "    ": 89,
    "秽浊垢": 1,
    "\n午": 15,
    "005854": 3,
    "02317": 1,
    "橘 Blanco": 4,
    "丹波元简氏": 9,
    "唐明皇李隆基": 2,
    "太谷广升蔚": 4,
    "谥荣康惠肃": 6,
    "清乾隆皇帝": 6,
    "新五子衍宗": 2,
    "\n明·薛己": 5,
    "江礼科次媳": 1,
    "吴抚台济寰公": 1,
    "40616": 1,
    " 　　生龙牡": 13,
    "\n厥阴司天": 1,
    "\n太阴司天": 2,
    "\n少阴司天": 7,
    "\n少阳司天": 6,
    "熇熇暍暍然": 4,
    "尻阴股膝髀腨胻": 15,
    "武川彦太郎": 1,
    "\n曲坊三轩": 1,
    "金花堂佐助": 1,
    "該縣原轄舊": 25,
    "給臨床帶來": 25,
    "對奇經學説": 25,
    "五臟風寒積": 25,
    "風發熱煩嘔": 25,
    "對校訂仲景遺": 25,
    "龍興道儒學據": 25,
    "楊守敬景鄰蘇園": 25,
    "茱萸當歸湯": 25,
    "林億對本書": 25,
    "從前後文來": 25,
    "余贏鰲研究員": 25,
    "後補述十四脈": 1,
    "陽湖惲敬子": 1,
    "廣本舉朱本": 1,
    "集仲景評脈": 1,
    "季節時令來": 1,
    "種脈象歸納爲": 1,
    "陰與少陽經": 31,
    "葶藶子茱萸圓": 1,
    "據證論治爲": 1,
    "脈陰陽虚實": 2,
    "與病變臟腑": 2,
    "\n趺陽脈微": 2,
    "爲中醫獨特": 2,
    "論述姙娠諸": 1,
    "則腹滿脇鳴": 1,
    "當宣達陽氣": 1,
    "栝樓桂枝湯": 1,
    "\n諸浮數脈": 1,
    "葶藶大棗瀉肺湯": 5,
    "趺陽脈浮緩": 1,
    "\n凡診脈當視": 1,
    "脈極虚芤遲": 1,
    "\n婦女陰寒": 1,
    "\n少陰脈數": 1,
    "後陰潰爛爲": 1,
    "對月經期間": 1,
    "濡則陽氣微": 2,
    "氣衝髀裏熱": 1,
    "當與小建中湯": 1,
    "黄蘗梔子芒": 1,
    "尺脈浮爲傷腎": 1,
    "趺陽脈緊爲傷": 1,
    "張仲景論脈": 2,
    "尤當詳察寸關": 2,
    "洪則衛氣實": 1,
    "實則氣無從": 1,
    "魏晉醫學家皇甫謐": 1,
    "脈復數": 1,
    "羸長": 1,
    "復欬": 1,
    "乍劇": 1,
    "脈診": 11,
    "聞診": 4,
    "爲正確": 1,
    "論述運": 1,
    "斷預後": 42,
    "掣衣掇": 28,
    "妄語錯亂": 2,
    "陰陽俱絶": 15,
    "亂經": 30,
    "當風邪": 1,
    "膽氣": 54,
    "兩脇": 2,
    "陰結陽絶": 15,
    "陰陽絶竭": 1,
    "陰陽俱竭": 1,
    "榮衛竭絶": 1,
    "鵝羽": 15,
    "診寒熱瘰癧": 1,
    "見三脈": 37,
    "診齲齒": 1,
    "獨熱": 15,
    "齒垢": 44,
    "尤爲": 29,
    "論述脈與證": 1,
    "絶止復頓來": 1,
    "則五臟敗壞": 1,
    "則熱甚痸瘲": 1,
    "髀胻": 3,
    "癎痸筋攣": 2,
    "爲腸澼": 13,
    "熱見": 1,
    "懸鈎": 1,
    "爲經氣予": 1,
    "腎氣予": 1,
    "棗華": 1,
    "榆莢": 16,
    "味韭英": 2,
    "五臟菀": 1,
    "寒熱獨": 13,
    "臨證時應隨": 1,
    "這一理論後來": 2,
    "革與實相類": 3,
    "直秘閣臣林億": 1,
    "楊守敬景鄰園": 1,
    "葉氏廣勤書堂": 1,
    "經餘": 6,
    "顯係": 84,
    "則訂": 1,
    "與醫理統": 1,
    "則擇": 16,
    "關聯較": 1,
    "振慄": 26,
    "丁日": 8,
    "與榮脈": 1,
    "辛日": 8,
    "腎氣絶": 3,
    "踵疽": 2,
    "尻癰": 1,
    "瞳子青": 51,
    "丙丁屬火": 1,
    "丙爲": 1,
    "終陰復還陽": 1,
    "\n夫實則譫語": 1,
    "凡屬印裝質量問題請與本社市場營銷中心聯繫": 1,
    "\n趺陽脈遲": 1,
    "數脈當遲緩": 1,
    "太陽與陽明": 1,
    "\n臟結無陽證": 1,
    "與禹餘粮圓": 2,
    "屬承氣湯證": 6,
    "\n脈雙弦遲": 1,
    "屬茵陳蒿湯": 1,
    "屬茵陳蒿湯證": 2,
    "瀉腸胃實熱": 1,
    "當針足陽明": 1,
    "與桂枝湯則": 1,
    "\n太陽與少陽併": 1,
    "爲轉屬陽明": 1,
    "洪大則榮氣長": 1,
    "當歸四逆湯": 1,
    "屬桂枝湯證": 7,
    "朴杏子湯證": 1,
    "屬麻黄湯證": 7,
    "屬大青龍湯": 1,
    "傷寒脈浮緩": 1,
    "屬小青龍湯證": 3,
    "與小柴胡湯": 1,
    "須依據證候": 1,
    "應結合客觀證狀": 1,
    "\n傷寒發熱": 12,
    "後轉屬陽明": 1,
    "陰陽氣併竭": 1,
    "無陽則陰獨": 14,
    "梔子厚樸湯": 1,
    "屬梔子湯證": 4,
    "屬柴胡桂枝乾薑湯": 5,
    "屬旋覆代赭湯": 1,
    "屬梔子乾薑湯": 1,
    "龍骨牡蠣湯": 2,
    "屬赤石脂禹餘粮湯": 5,
    "惡寒後發熱": 1,
    "\n足厥陰氣絶": 14,
    "與手陽明爲": 1,
    "\n形寒寒飲": 1,
    "趺陽脈麤麤": 1,
    "謂腎間動氣": 2,
    "\n七診雖見": 2,
    "\n夫醫藥爲": 1,
    "與足陽明爲": 1,
    "夢築垣蓋屋": 1,
    "關論述歸類": 1,
    "經適當調攝": 1,
    "況與證候預後": 1,
    "論述損脈與": 1,
    "謂脈來沉濇": 1,
    "無數虚太陰": 1,
    "APACHEⅡ": 56,
    "稗邦︽柏爸︽﹀\nThe": 1,
    "Amitabha Buddah": 1,
    "霸︽惭︽贬半︽贬扳": 1,
    "晨︽扳避邦": 1,
    "稗︽惩半︽吹": 2,
    "苍丹黅素玄": 1,
    "明太祖朱元璋": 137,
    "氐房心尾箕": 1,
    "李延寿北史云": 20,
    "叶批全生集云": 11,
    "\n文　魁\n": 9,
    "211027": 19,
    "\nSARS": 1,
    "汉高祖刘邦": 98,
    "魏太医令丞": 1,
    "北宋宋仁宗": 22,
    "齇鼻 　　": 13,
    "燎疱 　　": 13,
    "安能霾蔽青天": 7,
    "方  源　王子昭": 1,
    "林安石国榴": 8,
    "昔皇甫玄晏": 1,
    "呼素华同志": 1,
    "何拉得苷元": 17,
    "喹喏里西啶": 6,
    "唐松草坡芬": 25,
    "lematoside S": 3,
    "060812": 6,
    "060806": 4,
    "痹琪": 3,
    "060803": 2,
    "髎\n": 178,
    "按摩师": 1,
    "推拿师": 1,
    "理疗师": 3,
    "康复治疗师": 1,
    "推拿科": 1,
    "按摩科": 1,
    "康复科": 1,
    "理疗科": 1,
    "针灸科": 1,
    "\n斛": 1,
    "　　川萹": 1,
    "痫厥": 2,
    "畅怀珍": 1,
    "姜\n恙缘鄙": 1,
    "毋劳尔": 72,
    "毋摇尔": 1,
    "毋俾尔": 1,
    "宗金代张": 1,
    "谷麦芽\n恙原": 1,
    "　　袾秫穗": 1,
    "矧时序暑湿": 1,
    "　　川萹蓄": 1,
    "100078": 2,
    "琉　璃　痘\n痘": 96,
    "\n癫　　蛊\n": 19,
    "\n失　　荣\n": 25,
    "\n横　　痃\n": 25,
    "\n发　　癥\n": 13,
    "\n慢　　惊\n庄": 5,
    "　　   ": 2,
    "侯右\n怀麟": 2,
    "韩右\n怀妊": 3,
    "塔移影林氏": 24,
    "王　彬　杨　杰": 3,
    "\nWeiss": 2,
    "528437": 3,
    "510006": 4,
    "4042401": 1,
    "夫轩圣岐圣景圣": 1,
    "轩圣岐圣仲圣": 1,
    "\n七癥八瘕": 2,
    "温病四大家": 2,
    "阿米娜·阿不都热依木": 2,
    "艾克包姆氏": 2,
    "华岑公子云": 4,
    "张仁主任医师": 1,
    "Meige氏": 3,
    "心血管系统": 1,
    "张太史锦芳": 2,
    "颅内压增高症": 3,
    "　　肘弛节": 1,
    "戚雷友仁浼余": 1,
    "聊子振太尊": 1,
    "李县尊令岳": 1,
    "诸厥": 8,
    "蔍苜": 1,
    "恳黎友岸": 1,
    "左　": 2,
    "剌谬": 1,
    "剌缪": 1,
    "初伊": 7,
    "翁喜言": 1,
    "公云": 4,
    "谱伯王若怀": 1,
    "石北涯仲媳": 1,
    "光禄柴黼庵": 2,
    "俄不勒吉吉": 1,
    "杜　仲　Duzhon": 2,
    "菥\n菥　蓂　Ximin": 3,
    "艾　叶　Aiye": 2,
    "叶　Anye": 2,
    "叶　Chɑye": 2,
    "龙　Dilon": 2,
    "辛　夷　Xinyi": 2,
    "芥　子　Jiezi": 2,
    "orientalis Noack": 2,
    "朱　砂　Zhush": 2,
    "沙　棘　Shɑji\n": 2,
    "胡　椒　Huji": 2,
    "王\n王不　": 3,
    "珊　瑚　Shɑnhu\n": 2,
    "磁　石　Cishi": 2,
    "砒　石　Pishi": 2,
    "黄　Liuhu": 2,
    "秦\n秦　艽　Qinji": 2,
    "紫　贝　Zibei": 2,
    "辛　Xixin": 2,
    "芜　荑　Wuyi": 2,
    "荆　芥　Jin": 2,
    "谷　芽　Guy": 2,
    "苓　Fulin": 2,
    "陈　Yinchen": 2,
    "蒺　藜　Jili": 2,
    "麝　香　Shexi": 2,
    "040601": 3,
    "040301": 1,
    "040901": 2,
    "040902": 2,
    "040602": 2,
    "  Eike Reich": 1,
    "Anne Schibli": 1,
    "Jixuetenɡ\nCAULIS SPATHOLOBI": 1,
    "戴敬　王璐": 1,
    "明·罗周彦": 42,
    "金元·王好古": 12,
    "黄门令史游": 47,
    "2PbCO": 21,
    "陆细埤雅云": 7,
    "萨曼·海德": 3,
    "方药廉效奇": 20,
    "宋英宗讳曙": 9,
    "黄常山碱甲": 9,
    "罗语ankwa": 3,
    "何翼云孝廉": 68,
    "安知歇貌林": 31,
    "尹公子凤巢": 20,
    "丹波元坚云": 23,
    "龙野一雄氏": 3,
    "耶律文正王": 2,
    "王皱石广文": 2,
    "太仆寺员外郎": 2,
    "童幼天癸未": 16,
    "\nSolnitzky": 2,
    "Tinel氏": 1,
    "梁·阮孝绪": 14,
    "汉殇帝刘隆": 17,
    "Behcet氏": 22,
    "chajek氏": 22,
    "喜多村直宽": 4,
    "浅田贺寿卫": 4,
    "左　琪　黄　金": 4,
    "槜李沈目南": 1,
    "衢雷丰少逸氏": 1,
    "阿诺德·利伯尔": 7,
    "司马相如梦": 12,
    "张子颜少卿": 2,
    "二陈咽　辘辘鸣": 49,
    "田中吉左卫门": 5,
    "赵燏黄先生": 1,
    "附怒复\n静": 1,
    "容川唐宗海": 1,
    "方龙马定痛丹": 4,
    "龙马定痛丹": 4,
    "颜老哲嗣乾麟兄": 1,
    "\nAIHA": 6,
    "86257": 1,
    "醴酌": 12,
    "亚伯拉罕·科雷": 34,
    "\n明·刘宗厚": 11,
    "石筱山伤科": 1,
    "Reichert PJ": 1,
    "  Laquerriere": 6,
    "桂甘辛甘化阳": 1,
    "贞帚欝育子": 13,
    "丑辰未戌土": 7,
    "酉戌亥子丑寅": 4,
    "丁己辛癸乙": 1,
    "癸乙丁己辛": 1,
    "龙六继嗣丹": 13,
    "长春广嗣丹": 26,
    "开郁毓麟丹": 13,
    "逐瘀衍嗣丹": 67,
    "济阴衍宗丹": 14,
    "宣志祥春丹": 26,
    "济脾育嗣丹": 54,
    "温射突泉丹": 19,
    "肾癸续嗣丹": 14,
    "\n清·尤在泾": 1,
    "宛宛中三壮": 2,
    "孙真人海上方": 1,
    "石武选谦伯": 1,
    "黃耆建中湯": 57,
    "　　夫尊榮": 57,
    "　　　諸黃": 8,
    "　　產後風續": 1,
    "　　趺陽脈當伏": 4,
    "赵老大夫诊毕": 1,
    "丁壬卯酉六": 19,
    "张效伊芳翁": 1,
    "吴春麓仪曹": 1,
    "吴车驾涌澜公岳": 6,
    "鲍觉生宫詹": 1,
    "坎罗君玉文": 1,
    "培生生初阳": 1,
    "予思仲景云": 1,
    "少泉公目微瞬": 1,
    "戊癸辰戌五": 1,
    "明隆庆皇帝": 2,
    "勉冲孺氏梓": 1,
    "清嘉庆皇帝": 1,
    "\n矢数道明": 1,
    "山之内梅节": 2,
    "袁氏复脉静": 1,
    "袁氏苏心醒": 1,
    "袁氏镇心痛": 1,
    "赵炳如先生": 13,
    "巴里·马歇尔": 8,
    "罗宾·沃伦因": 2,
    "莱诺伊•胡德": 2,
    "努尔买买提": 1,
    "曾钧堂孝廉": 1,
    "雪峰仁兄雅鉴": 1,
    "剑华仁兄雅鉴": 1,
    "尹彭子益君": 1,
    "汪洋沧海阔": 1,
    "尹之哲嗣凤巢": 2,
    "近藤平三郎": 1,
    "中村纯九郎": 1,
    "高桥源太郎": 1,
    "安井小太郎": 1,
    "文颜小屡氏": 1,
    "益蕃延盛茂": 1,
    "钱君颖国宾": 1,
    "玄奥师希夷": 1,
    "乌赫托拇斯基": 56,
    "Janet Travell": 2,
    "风瘙隐胗候": 12,
    "尼科利斯基": 17,
    "林　鹏　李　": 8,
    "阿莫尔·汉森": 36,
    "石香葇条云": 2,
    "左慈秘诀云": 4,
    "厥贡岱畎丝枲": 3,
    "神农轩辕氏": 6,
    "朝野佥载云": 1,
    "庵摩洛迦果": 1,
    "范子计然云": 1,
    "陈氏宗仲景": 45,
    "俟天明延余": 67,
    "闵君文思延余": 67,
    "李坑口裕成": 67,
    "乔梓阁捷庵": 67,
    "龚玉屏子椿": 25,
    "任广信大导": 25,
    "廖参谋伯铭": 23,
    "危阳": 12,
    "遽蒙": 12,
    "沉迟": 13,
    "恙初": 12,
    "脊髀": 12,
    "脊髀痠": 12,
    "夜遗": 12,
    "橘窗书影云": 6,
    "\n明·兰茂": 6,
    "许明·江瓘": 1,
    "秋微毛": 6,
    "革革": 9,
    "吉吉": 7,
    "尺肤": 37,
    "孙侍御潇湘夫人": 1,
    "大宗伯罗公": 1,
    "贰尹闵介眉甥媳": 1,
    "阃克相夫志": 1,
    "仲景脉法云": 1,
    "昔先文敏公": 1,
    "陈　岚　邵　萍": 1,
    "soybean phospholipid": 1,
    "David Wang": 1,
    "齐　菲　周　芳　裴　华": 1,
    "吴　晋　张　荣": 1,
    "徐　轩　干　千": 1,
    "列御寇行云": 1,
    "一丸济世德": 3,
    "赵学敏恕轩": 198,
    "臞仙神隐云": 28,
    "Ignaz Zadek": 24,
    "J.J.Virey": 24,
    "韦以宗教授": 1,
    "赵淳　叶勇": 1,
    "　　小川贝": 1,
    "067287": 92,
    "920825": 4,
    "203657": 2,
    "\nASAB": 2,
    "复思华岫云": 7,
    "道光帝太后": 2,
    "\nNBZDs": 10,
    "思尧\n2005Ʊ09Ʊ01\n赠言十一\nDear": 34,
    "\nMoved": 34,
    "恭惟主上丕": 2,
    "林檎 　果": 1,
    "王　栋　李　浩": 1,
    "余述丹溪云": 1,
    "阳痧": 17,
    "荅剌知": 5,
    "目瞀言謇": 1,
    "小活络丹": 6,
    "柔髆二七": 1,
    "任氏心脉康": 22,
    "任氏脑脉苏": 4,
    "经颅多普勒": 39,
    "诞弥厥月": 148,
    "延年益嗣丹": 148,
    "夏月火嗽": 185,
    "疳蚀": 82,
    "汤浴": 58,
    "鄙念斯慰": 20,
    "\n疹　脉\n凡": 20,
    "安能胜": 20,
    "徐徐升": 20,
    "疹　涕": 20,
    "二火司天": 20,
    "疹　": 20,
    "鬓　疽\n立斋": 44,
    "\n痄　腮\n立斋": 44,
    "\n论　证\n凡": 32,
    "\n败　毒\n": 32,
    "\n泻　痢\n立斋": 32,
    "痘　疹　诠\n痘　疮\n": 21,
    "安　胎\n凡": 13,
    "痘　疹　诠\n": 27,
    "药师资格认证中心命审题专家": 1,
    "岐黄\n伯臾": 10,
    "25006": 1,
    "厥阴风木司天": 297,
    "尻股膝髀腨": 3,
    "陈振孙亦云": 1,
    "顾天花瑞雪": 1,
    "夏仲决明生": 1,
    "240847": 1,
    "慈禧皇太后": 21,
    "孝淑睿皇后": 3,
    "孝成慎皇后": 1,
    "孝全成皇后": 1,
    "安固伦公主": 1,
    "张则梗梗然": 1,
    "路志正医林": 1,
    "埃勃斯坦氏": 6,
    "心理咨询师": 78,
    "王启玄子序云": 11,
    "\n料　简\n": 42,
    "\n料　简\n凡": 15,
    "傅药\n景天": 5,
    "鹰崖馗·何塞": 1,
    "托马斯·阿尔科塞尔": 1,
    "丹羽日出夫": 1,
    "韩懋医通云": 1,
    "王执中母氏": 4,
    "土贝母苷甲": 54,
    "黄萆硇银清": 4,
    "时珍国医国": 1,
    "壬膀": 5,
    "枚十二效堪嘉": 4,
    "史目月池翁": 5,
    "六十二风义": 4,
    "六十二风": 8,
    "\n休讶": 4,
    "唾涎沫月余": 4,
    "饴绝": 4,
    "\n饴": 4,
    "饴温": 4,
    "姜芩扇妇朴苇": 7,
    "方\nⅠ号方": 5,
    "全国劳动模范": 29,
    "燮理阴阳\n林": 3,
    "徐仲才先生": 1,
    "张光煜先生": 2,
    "\n明·万全": 7,
    "庾慧梁凤鸣": 1,
    "韩云\n程　兰": 1,
    "\n益营伐卫": 1,
    "余宗东垣甘温": 1,
    "阳益胜益炽": 1,
    "包金七层楼": 2,
    "白狗公茨蔸": 2,
    "方·第二辑": 2,
    "干九令杠叶": 2,
    "陈石灰　韭菜蔸": 2,
    "陈粉壁土　": 1,
    "米泔水　水杨柳": 1,
    "應怎樣選擇": 1,
    "從鄭玄與陸": 21,
    "唐高祖李淵": 22,
    "唐高祖李淵賜": 21,
    "宋欽宗諱桓": 42,
    "唐肅宗後傳": 21,
    "楊上善應爲": 21,
    "魏高貴鄉公": 21,
    "范行準則認爲": 21,
    "楊上善注云": 78,
    "觀音應夢散": 17,
    "沈金鼇坎離": 17,
    "與鳥獸蟲魚": 17,
    "延壽不老丹": 17,
    "\n傳統訓詁學": 17,
    "訓釋實踐爲": 17,
    "詞義\n訓詁學": 17,
    "范子計然云": 17,
    "將文字訓詁與審物責實": 17,
    "程瑤田繼續對蠮螉": 17,
    "訛爲破故紙": 17,
    "樊將軍首與燕督亢": 17,
    "何莫學夫詩": 11,
    "爲正確閲讀": 11,
    "類書與當代辭書": 11,
    "方劑類\n方劑": 11,
    "爲質疑糾謬": 17,
    "仲景麻黃湯": 17,
    "蓋謂脉見流蕩虛": 17,
    "\n3.釋讀疑難\n": 17,
    "對孫詒讓論": 17,
    "孫詒讓論證": 17,
    "讀云費當爲": 17,
    "陸德明釋文": 18,
    "糾謬正誤\n通過對": 17,
    "理淺顯易明": 17,
    "黴瘡毒蘊陽明": 17,
    "札記後注云": 17,
    "\n本條札記": 17,
    "山陰劉大化": 17,
    "\n3.輯補遺闕\n陸": 17,
    "錢國賓案注云": 17,
    "杭太史堇甫處": 17,
    "謂時世異邪": 17,
    "\n校讀針對": 17,
    "對校讀問題": 17,
    "補陽則陰竭": 21,
    "尹咸校數術": 19,
    "王冰祇認爲": 19,
    "陽明一證云": 19,
    "訛誤\n訛誤": 19,
    "段玉裁注云": 21,
    "\n下圖剪輯": 19,
    "羅振玉傳森立": 19,
    "將竹簡編錯": 19,
    "皇甫士安甞": 19,
    "違亂\n圖一\n圖二\n": 19,
    "唐高宗李治年": 19,
    "尚志鈞重輯該書": 19,
    "這兩個短語顯然": 19,
    "舊文則錯亂": 19,
    "陽明太隂橫": 19,
    "王冰號啓玄子": 28,
    "林億與掌禹錫": 28,
    "繡谷書林周": 28,
    "張志聰注云": 28,
    "文學臣楊上善奉敕": 28,
    "黃元御諸醫": 28,
    "東漢末劉熙": 28,
    "楊守敬處獲": 28,
    "唐寫卷子影": 28,
    "楊大令葆初倣": 28,
    "仲景諸家奚若": 28,
    "周貞亮評騭": 28,
    "湯散膏丸類": 28,
    "則陰陽俱虛": 28,
    "成無己注云": 29,
    "小青龍湯發": 28,
    "歷陽張孝忠": 28,
    "跋成無己書云": 28,
    "裏虛實陰陽": 28,
    "陰陽易差後勞復": 28,
    "白燕堂陸氏": 28,
    "標明爲扁鵲": 28,
    "謂該書輯呂廣": 28,
    "\n規範異文": 28,
    "劉宋雷斅編": 24,
    "爲藥物炮炙專書": 24,
    "宋徽宗趙佶": 24,
    "醫官許國禎": 24,
    "杜思敬輯錄": 48,
    "爲虛損癆瘵證": 24,
    "爲治虛勞專": 24,
    "攝揚下津編": 24,
    "據偶齋序稱": 24,
    "鄧學禮編次爲": 24,
    "王景華重訂": 24,
    "醫案醫話類\n": 24,
    "紹興裘吉生": 24,
    "柳寶詒選評": 24,
    "醫話醫論類": 24,
    "原題南齊褚澄": 24,
    "民國陳存仁輯": 24,
    "陳存仁從數百種": 24,
    "俞樾認爲這": 11,
    "當惡寒發熱": 12,
    "惡寒發熱關": 11,
    "脱離語境來": 11,
    "\n熱氣淳盛": 11,
    "大青龍湯證": 11,
    "將前後詞語": 11,
    "爲述賓結構": 11,
    "黃蕘圃丕烈": 10,
    "牡蠣　須\n燒爲": 10,
    "\n據葉德輝": 10,
    "書體六七變": 10,
    "經師無竹帛": 10,
    "將諸本異文": 10,
    "見零璧斷珪": 10,
    "將諸本異文羅列迨盡": 10,
    "當代中醫藥": 18,
    "爲萬世湯液": 3,
    "陳修園編寫": 3,
    "單音詞佔據": 12,
    "王冰注文隱": 12,
    "俱視獨見適": 12,
    "王冰認爲應": 12,
    "闡述醫理\n": 12,
    "文義便頓時顯豁": 12,
    "風從東北來": 8,
    "風從東方來": 8,
    "閲讀古醫籍時": 6,
    "從清顧尚之": 6,
    "譫語發潮熱": 6,
    "從詞组結構來": 6,
    "爲化玄奧爲": 6,
    "厥後博物稱華": 6,
    "葵根莖子無": 11,
    "後人多誤認": 11,
    "郭靄春認爲": 11,
    "本條後句云": 11,
    "絶弊弊綽綽": 11,
    "後處一重文當參": 11,
    "\n首疽發0熱0": 11,
    "顛颼風齒齲": 11,
    "\n榮衛俱虛": 11,
    "丹波元簡僅": 11,
    "諸經滎輸藏腧": 23,
    "擺舉身頓仆": 11,
    "戰國時鄭國": 5,
    "從腕關節橫紋": 5,
    "明姑蘇叢書堂": 6,
    "吴縣黃蕘圃": 6,
    "這對於閲讀": 5,
    "爲陽石剛齊": 5,
    "無陽則陰無": 18,
    "無陰則陽無": 18,
    "與太陽諸症獨舉頭項": 5,
    "郭靄春校云": 5,
    "言補寫氣調": 5,
    "與本條相應": 5,
    "證醫學六經": 5,
    "顯然應連屬": 12,
    "總體結構理當": 12,
    "神安則百體": 12,
    "\n心怵惕思慮": 12,
    "丹波元堅云": 12,
    "這兩個短語應": 12,
    "\n本條楊注祇": 12,
    "結句處當云": 12,
    "從腕中太澤文": 12,
    "經濕熱諸證": 11,
    "當屬膽經鬱熱": 11,
    "\n陽氣煩勞": 11,
    "熱厥與煎厥": 11,
    "\n密補固真丹": 11,
    "方劑\n醫書": 11,
    "舉孝弟惇厚": 11,
    "高世栻認爲": 11,
    "俞樾認爲兩": 11,
    "細檢敦煌原卷實爲": 11,
    "丹波元簡介紹": 11,
    "郭靄春對後": 11,
    "丹波元簡認爲": 11,
    "類書舊注應": 2,
    "與泄藥爲君": 2,
    "猶馳騁鄭衛": 2,
    "俞樾堪稱具體運": 2,
    "明季顧炎武": 2,
    "從漢代抄本遺": 2,
    "爲後人閲讀": 2,
    "明刊無名氏": 2,
    "天漢係漢武帝": 2,
    "泝泝然寒栗": 2,
    "文生薑瀉心湯": 2,
    "蒼舒隤敳檮戭大臨龐降庭堅仲容叔達": 2,
    "爲名爾雅龐洪": 2,
    "與爾臨衝韓詩": 2,
    "隆衝漢書地理志隆慮": 2,
    "小雅頍弁爾淆": 2,
    "皇甫謐博綜": 1,
    "金木當": 2,
    "書類": 1,
    "豬脂": 1,
    "譬猶豫章生": 4,
    "言形氣榮衛": 4,
    "丙丁巳午戊暑": 42,
    "\n戊癸辰戌": 12,
    "\n寅申少阳": 1,
    "祁坤\n善成堂": 1,
    "雷丰少逸甫": 1,
    "肖山竹林寺禅": 1,
    "王之本经云": 1,
    "\n少陰脈繫": 2,
    "灸療一會兒": 2,
    "從那時以來": 9,
    "爲詞義訓詁": 9,
    "古義對我們": 9,
    "音義\n這類": 24,
    "聲訓與義訓": 24,
    "爲中醫經典": 24,
    "烈烈猶栗列": 10,
    "\n這個術語": 10,
    "\n這三個術語": 10,
    "張壽頤認爲": 11,
    "諸儒應詔會": 11,
    "談音義問題": 11,
    "湯之爲言蕩": 12,
    "\n這一類聲訓": 11,
    "爲雙聲爲訓": 11,
    "滑壽對這個": 11,
    "張介賓注云": 11,
    "宇津木益夫": 22,
    "顧觀光認爲": 11,
    "張嘯山認爲": 11,
    "\n張壽頤醫文": 11,
    "當屬東漢許慎": 9,
    "闡釋義理類": 9,
    "學風對後來": 9,
    "爲補充東漢": 9,
    "論楊上善云": 13,
    "訓詁條例嚴": 13,
    "文壇宇宮廷": 13,
    "\n3.類編": 13,
    "單味藥專類藥": 5,
    "\n司馬遷論莊子": 13,
    "海運則將徙": 13,
    "輪扁斲輪喻讀書": 13,
    "蝸角觸蠻喻諸侯": 13,
    "誇張\n莊子": 13,
    "對吮癰舐痔": 13,
    "對東施效顰": 13,
    "單純詞疊音": 7,
    "從司馬遷寫": 9,
    "司馬遷責無": 9,
    "寫韓信虜魏": 9,
    "寫韓信無謀": 9,
    "陳涉抱負遠": 9,
    "王侯將相甯": 9,
    "子毋讀書遊": 9,
    "項羽怨懷王": 9,
    "諷刺漢武帝": 9,
    "江講絳覺\n": 5,
    "\n真軫震質\n諄準稕術\n臻": 5,
    "櫛\n文吻問物\n欣隱焮迄\n元阮願月\n魂混慁沒\n痕": 5,
    "寒旱翰曷\n桓緩換末\n刪潸諫黠\n山產襉轄\n": 5,
    "霰屑\n仙獮線薛\n蕭筱嘯": 5,
    "\n陽養漾藥": 5,
    "唐蕩宕鐸\n庚梗敬陌": 5,
    "蒸拯證職\n": 5,
    "覃感勘合\n談": 5,
    "闞盍\n鹽琰豔葉\n添忝帖": 5,
    "嚴儼釅業\n凡範梵乏\n": 5,
    "六十一韻類": 5,
    "三聲爲陽聲韻": 15,
    "與此性質類": 5,
    "這六十一韻類": 5,
    "學子臨文選韻苦": 5,
    "古漢語文獻": 14,
    "句讀\n句讀": 14,
    "壺飱從徑餒": 14,
    "蓋非獨屈子": 4,
    "\n晉代陸機": 4,
    "涔陽兮極浦": 4,
    "隱思君兮陫側": 4,
    "石瀨兮淺淺": 4,
    "折芳馨兮遺": 4,
    "余處幽篁兮終": 4,
    "晏兮孰華予": 4,
    "騎隨從赤豹文狸": 4,
    "斑斕鮮豔與眾": 4,
    "列子貴虛尚玄": 4,
    "公扈趙齊嬰": 4,
    "扁鵲謂公扈": 4,
    "這種大膽設": 4,
    "偃師謁見王": 4,
    "虛構": 10,
    "厭惡": 10,
    "弗禁": 4,
    "龜卜": 4,
    "案五帝本紀贊云": 3,
    "聶政姊聶榮": 3,
    "節選": 31,
    "悲壯慘烈": 3,
    "聶政爲報嚴仲子": 3,
    "杖劍": 3,
    "殺俠": 3,
    "毀容": 3,
    "屍體": 3,
    "聶政": 3,
    "聶榮": 6,
    "聶政屍體": 3,
    "悲劇達": 3,
    "聾子養育嬰兒": 3,
    "燀熱則理塞": 3,
    "爲飲食酏醴": 3,
    "劉師培認爲": 3,
    "晉代韓康伯": 6,
    "爲純陽純陰": 6,
    "動靜與剛柔": 6,
    "蓋魏晉間人僞託": 3,
    "蓋九爲陽數": 3,
    "爾尚克羞饋祀": 3,
    "棐徂邦君御": 3,
    "誕惟厥縱淫泆": 3,
    "魯國從隱公": 4,
    "沈和川神臺駘": 4,
    "晉侯聞子產": 4,
    "淫則生內熱惑蠱": 4,
    "范宣子輕幣": 4,
    "范宣子執政": 4,
    "原來魯莊公": 6,
    "亂臣賊子懼": 6,
    "寫晉國呂甥": 6,
    "秦穆公談判時": 6,
    "屈完說服齊桓公": 6,
    "寫鄭國子產帶信": 6,
    "晉國範宣子": 6,
    "諸侯國貢納": 6,
    "惠子諸斷處": 3,
    "這四個正齒音": 1,
    "江戶醫學影": 3,
    "當依治歷節": 3,
    "稱爲陰陽易": 3,
    "虛實冷熱爲": 3,
    "聽覺視覺暢達": 4,
    "孝廉郎終軍": 1,
    "孝廉郎竇攸": 1,
    "實則尹知章": 3,
    "養禽獸植樹木": 3,
    "豬饲彦博云": 3,
    "漢初司馬談將諸子": 10,
    "屬文學範圍": 10,
    "王先謙認爲此處爲": 4,
    "莊子繼承並發揮": 7,
    "桓公富國強": 7,
    "趎願聞衛生": 7,
    "兒子終日嗥": 7,
    "嗁極無聲爲嗄": 7,
    "養生學産生": 7,
    "莊子臨終與": 7,
    "爲氣無聲無慮": 3,
    "關雎\n關關雎鳩": 9,
    "雙聲聯綿詞": 9,
    "禹舜時代佐禹": 9,
    "史倉頡見鳥獸蹏迒": 1,
    "秦燒滅經書": 1,
    "隸書訛變後": 1,
    "謂稟氣渥薄": 4,
    "夫稟氣渥則": 4,
    "願車馬衣輕裘": 12,
    "鑽子鑽木燧": 4,
    "子貢機智善辯": 4,
    "王爲過堯舜": 4,
    "王飲酒酣樂": 4,
    "司馬貞索隱": 4,
    "小兒則爲癎": 1,
    "五臟風積熱": 1,
    "諸侯國吳王劉濞": 1,
    "安車蒲輪徵": 1,
    "況直眇小煩懣": 1,
    "內心空虛煩悶": 1,
    "吳王殺子胥": 1,
    "聲祭泰夬廢": 1,
    "楚騷諸子秦漢": 1,
    "孔廣森陰陽對轉": 1,
    "時魯國國君": 1,
    "闡述智仁勇": 1,
    "後則論勞風": 1,
    "串講式語譯": 1,
    "從晉代皇甫謐": 6,
    "漢高祖劉邦": 1,
    "從公孫光學醫": 1,
    "\n齊中御府長": 1,
    "莒橋梁頗壞": 1,
    "信則擥車轅": 1,
    "湯火齊逐熱": 1,
    "熱阻礙陽氣運行": 1,
    "左大陽明脈": 1,
    "風寒濕氣阻滯": 1,
    "記述淳于意": 1,
    "\n敘錄體內容詳略": 4,
    "張建吉甫序": 4,
    "搏陽則爲巔疾": 1,
    "搏陰則爲痞": 1,
    "顧從德本爲": 2,
    "侯景之亂後": 1,
    "寧夏靈武縣": 1,
    "諡為壯節侯": 1,
    "毛遂隨平原君": 1,
    "從孫權稱帝": 1,
    "扁鵲望齊侯": 3,
    "神醫華佗奇": 3,
    "戴德從中輯錄": 1,
    "灑掃應對進": 1,
    "養馬並備車輛": 1,
    "章統論綱領": 1,
    "對方當禽獸來": 1,
    "搆怨於諸侯": 1,
    "案灌夫項令謝": 1,
    "元耶律楚材": 6,
    "宋儒譏訓詁": 1,
    "\n臣聞朋黨": 1,
    "東漢末帝劉協": 1,
    "稱舜爲聰明": 1,
    "\n夫興亡治亂": 1,
    "韓非子校釋": 1,
    "與中國國家圖書館": 3,
    "罕爲舊辭書": 1,
    "小屯甲骨拾遺": 5,
    "脫漏稱爲脫": 1,
    "應古論簡脫": 1,
    "屬文爲蘭臺": 2,
    "章帝時爲蘭臺": 2,
    "與司馬長卿": 2,
    "穀子雲筆劄": 2,
    "會己則嗟諷": 2,
    "蓋聞蘭爲國香": 2,
    "文質疏內兮": 2,
    "理論對後世文學評論": 2,
    "\n聲調符號標": 3,
    "筆畫繁簡異": 1,
    "微廢文欣元嚴凡": 1,
    "魚虞真諄仙陽": 1,
    "韋應物並稱": 1,
    "劉禹錫輯爲": 1,
    "實爲萬世學術爭鳴": 1,
    "何爲紛紛然": 1,
    "賢則豪桀歸": 1,
    "麻縷絲絮輕": 1,
    "言幼小無知": 1,
    "對方這個軟肋": 1,
    "\n本文節選": 1,
    "嘗竊觀陰陽": 1,
    "司馬談對陰陽": 1,
    "許應元評論": 1,
    "勸賀舉進士": 1,
    "賀不舉進士爲": 1,
    "章帝時爲齊國": 1,
    "玄宗李隆基": 1,
    "韓愈仗義執言": 1,
    "羹齊眡夏時": 1,
    "\n瘍醫掌腫瘍": 1,
    "從瘍醫處領": 1,
    "獸醫掌療獸": 1,
    "傾慕藺相如": 1,
    "\n孝武皇帝": 1,
    "巫蠱祠祭呪詛": 1,
    "宮商角徵羽": 1,
    "\n該賦鋪陳敍": 1,
    "揆度奇恒\n揆": 27,
    "仲景青龙苓桂": 5,
    "乔对其友云": 2,
    "枢折挈胫纵": 2,
    "中毒性菌痢": 2,
    "脑血管意外": 2,
    "洛兹·克莱本": 57,
    "汉穆希密特": 50,
    "\n厥阴少阳": 1,
    "蒋　茜　李　梅": 1,
    "檗谷王大用": 1,
    "淳母炮豚炮牂": 1,
    "\n双荷圣惠": 1,
    "芎脑檀羗藿": 1,
    "\n大顺桂生": 1,
    "毘沙门天王": 2,
    "芦巴床子晚娥": 1,
    "\n濬川郁李": 1,
    "参苓诃麦蘗": 1,
    "秘元龙骨君": 2,
    "\n诜诜术桂": 1,
    "\n奇効黑龙": 1,
    "俾医卫世杰": 1,
    "何先圣后圣": 5,
    "\n仲景巅眩": 1,
    "观仲师小建": 1,
    "马援诫侄语": 3,
    "\n灵寿云祥": 2,
    "甘辛上达夫": 1,
    "赵院长子小四": 1,
    "虞阴盛戢阳": 1,
    "赵桐仲琴氏": 1,
    "俾火息金清": 99,
    "清阳明少阳": 34,
    "姜泽六味群": 32,
    "丁沉蔻泽行": 32,
    "丹栀苓泽匡": 8,
    "艾附暖宫桂萸良": 6,
    "白合提尼沙": 27,
    "申盛恒茶栈": 28,
    "郑重光素圃": 1,
    "华格拉立克": 7,
    "昔贤观公主": 1,
    "冶仲景天士": 3,
    "\nT⁃T皮神经节": 1,
    "文通龙忠迪墨": 78,
    "\n砚　　匣\n": 78,
    "\n论　　琴": 78,
    "\n雪霁策蹇": 75,
    "太上大道君": 78,
    "\n隐　　几\n": 79,
    "\n云　　舄\n": 79,
    "\n瘿　　杯\n": 79,
    "\n瘿　　瓢\n": 79,
    "葫　　芦\n": 79,
    "\n提　　盒\n余": 79,
    "安能栖栖役曳": 80,
    "黄　蔷　薇": 228,
    "青　珊　瑚\n": 228,
    "宿妆殷　　": 228,
    "　　倚阑娇": 228,
    "黄　香　萱": 169,
    "\n蒌　　蒿": 169,
    "东　风　荠": 169,
    "仲尼颜子乐": 70,
    "\n玄　　牝\n": 61,
    "熙载敝衣芒屦": 27,
    "\n松　　轩\n": 26,
    "太上律令敕": 26,
    "\n循机扪塞": 7,
    "任应秋道兄": 1,
    "傅菊仙年伯": 1,
    "承大塚敬节": 1,
    "老朽遵业师耕": 1,
    "明·金正希": 3,
    "戴葆元心田书": 1,
    "参桂茴椒薢": 1,
    "丁沈蟾雄苍": 1,
    "姜痞松\n脈缓": 1,
    "延泽丹芎査": 1,
    "苑紫粮脂茴仲弥": 1,
    "芩菔丹青栀": 1,
    "杞参苑味苓": 1,
    "香蒂参苓萸": 1,
    "梅赭参苓椒": 1,
    "陈姜豉丸豁": 1,
    "桃延茴韭楝": 2,
    "桂苓泽蛎楝": 2,
    "杞神苑栢紫": 1,
    "参耆草苑杞": 1,
    "高士宗云凡": 1,
    "楝萸苓桂良": 1,
    "佐宣畅少阳": 1,
    "\n参瓜诃芍": 1,
    "戟菟味脂芡莲": 1,
    "苑柏杞茴苁": 1,
    "苓姜朴菓桂": 1,
    "夏枯郁芥蒌栀康": 1,
    "丹菖芍沥匡": 1,
    "栀豉降蒌痞": 1,
    "藿朴蔻苓陈": 1,
    "郁菖栀斛沥": 1,
    "姜桂夏苓椒": 1,
    "苓楝朴莪姜夏延": 1,
    "青菓息风神揕安": 1,
    "犀羚蒌栀菊": 1,
    "菖羚星犀郁钩沥": 1,
    "参苓菖夏沥": 1,
    "夏志斛菖陈": 1,
    "枇蒌豉郁杏栀啜": 1,
    "杜枸苑延苓": 1,
    "菀味夏辛欵": 1,
    "实蒌桔杏沥": 1,
    "舒郁椒槟瘥": 1,
    "郁通杏朴苑栀": 1,
    "\n萸良延夏": 1,
    "延苓郁蔻桃": 1,
    "\n宣通痺窒": 1,
    "桃延楝杞桂": 1,
    "蔻味参莲襄": 1,
    "萆苓桔泽柏连苡": 1,
    "\n苓丹萆胆泽": 1,
    "胡桃脂志节苓杞": 1,
    "\n翘贝澡昆芎": 1,
    "少阳寅卯辰": 5,
    "伊里扎洛夫": 58,
    "平乐部氏正氏": 6,
    "暑湿余邪稽": 9,
    "王普耀香岩": 9,
    "蒿芩瓜翠佐": 1,
    "Wick ham": 1,
    "方加淡大云": 1,
    "黄冠缁衣辈": 1,
    "黄帝内經太素": 2,
    "金匱玉函經": 2,
    "傷寒論　　": 2,
    "傷寒論釋義": 2,
    "江蘇省中醫學校傷寒": 2,
    "宋本傷寒論校註": 2,
    "\n脈經校釋": 2,
    "孫星衍校　商務印書館": 2,
    "劉涓子鬼遺方": 2,
    "\n群書校補": 2,
    "諸病源候論　清": 2,
    "陸心源輯　光緒刊本\n諸病源候論校釋": 2,
    "\n傷寒六書纂": 2,
    "童養學纂輯": 2,
    "\n小兒藥證直訣": 2,
    "\n儒門事親": 2,
    "\n醫方類聚　朝鮮": 2,
    "\n簡明醫彀": 2,
    "\n類經圖翼": 2,
    "\n醫宗金鑑　清": 2,
    "證治全生集　清": 2,
    "\n醫心方　日·丹波康賴": 2,
    "\n十三經註疏": 2,
    "汪紹楹點校": 2,
    "\n文選　梁": 2,
    "\n爾雅義疏　清": 2,
    "\n爾雅音訓": 2,
    "\n廣雅疏證　清": 2,
    "\n釋名疏證補　清": 2,
    "據清·光緒": 2,
    "\n説文解字註　漢": 2,
    "許慎著　清": 2,
    "\n説文釋例　清": 2,
    "\n經典釋文": 2,
    "據光緒丙子": 2,
    "黄三八郎書鋪本": 2,
    "\n龍龕手鏡　遼": 2,
    "釋行均編　中華書局據高麗本影印\n四庫全書簡明目録　清": 2,
    "\n經傳釋詞　清": 4,
    "\n經詞衍釋　清": 2,
    "\n經義述聞": 2,
    "項絪玉淵堂": 2,
    "\n經典釋文彙校": 2,
    "\n古漢語虚詞": 2,
    "宋元語言詞典": 2,
    "龍潜庵編著": 2,
    "導引養生方　　": 2,
    "吴景則無從考證": 18,
    "酌源堂本影寫": 18,
    "瘡腫癰疽諸": 18,
    "婦科與産褥": 18,
    "嬰兒與臍瘡": 18,
    "金瘡成癰候云": 18,
    "霍亂候\n陰陽清濁": 40,
    "胞轉候\n胞轉": 40,
    "遺尿候\n腎與": 40,
    "數候\n腎與": 82,
    "論證較此詳備": 40,
    "陰癢候\n婦": 40,
    "陰腫候\n陰腫": 40,
    "龍膽瀉肝湯瀉": 40,
    "懷娠發乳癰腫": 40,
    "則肉敗爲膿": 40,
    "方養生方導": 65,
    "穀糟粕變敗": 40,
    "牛頸項架軛": 30,
    "腐壞潰爛較遲緩": 30,
    "疽候\n熛疽": 30,
    "從本候文義": 30,
    "疽發口齒候": 30,
    "風疽候\n腫": 30,
    "蓋風勝則動": 30,
    "謂數處腫塊": 30,
    "屬足三陽經": 30,
    "屬足三陰經": 30,
    "閑處　猶謂": 30,
    "爲當時認識": 30,
    "\n本候治療法則源": 30,
    "據本候標題補": 63,
    "風冷濕氣搏": 30,
    "爲歷史文獻對": 36,
    "後文蟲瘻候云": 36,
    "則爲多數瘻證": 36,
    "據蜣蜋瘻候": 36,
    "蟲瘻候\n諸瘻": 36,
    "腫核邊緣屈曲": 36,
    "膿瘻候\n諸瘻": 36,
    "嘔噦諸方稱爲": 7,
    "熱候\n榮衛": 7,
    "陽明諸經脈": 14,
    "陽明爲大腸": 14,
    "長髮候\n髮": 14,
    "則異毛惡髮": 14,
    "則異色惡髮": 14,
    "秦末與綺里季": 1,
    "語\n本候論": 37,
    "丁瘡候爲詳": 14,
    "熱則腠理開": 54,
    "據本候標題": 310,
    "憂思則傷志": 27,
    "謂脈象陣陣躍動": 27,
    "腎冷發沉厥": 27,
    "結氣候\n結氣": 27,
    "確爲産生積": 27,
    "遊氣候\n夫五臟": 27,
    "范汪録華佗": 24,
    "\n養生方導": 323,
    "爲風濕陰陽": 9,
    "養生方導引法云": 73,
    "云食生魚後": 45,
    "氣癭候\n氣癭": 44,
    "頭瘡候\n腑臟": 44,
    "小兒頭櫛沐": 44,
    "白秃候詳細": 44,
    "瘡候\n小兒爲風熱毒氣": 44,
    "癰瘡候\n六腑": 44,
    "語\n癰腫詳": 44,
    "癤候\n腫結長": 44,
    "疽候\n五臟": 44,
    "語\n本候論疽": 44,
    "語\n赤疵爲嬰幼兒": 44,
    "臍瘡候\n臍瘡": 44,
    "傷經脈轉變": 44,
    "噤候\n小兒": 80,
    "凍爛瘡候\n小兒": 44,
    "金瘡候\n小兒爲金刃": 44,
    "瘡候\n小兒": 44,
    "王灼惡瘡候\n腑臟": 44,
    "疳濕瘡候\n疳濕": 44,
    "\n養生方云": 167,
    "脣白齒齗生瘡": 41,
    "候\n夫春陽氣": 41,
    "廩丘公説云": 41,
    "見病身體發熱": 41,
    "當與理中湯": 41,
    "冷熱痢候\n夫": 41,
    "跗陽脈微澀": 41,
    "澀爲氣機澀滯": 41,
    "煩候\n春傷": 41,
    "痢後虚煩候\n夫體虚": 41,
    "膚腠還相搏臟腑　猶言膚腠": 41,
    "腫候\n痢後": 41,
    "後噦候\n夫風": 41,
    "蟯蟲狀極細微": 41,
    "對後世論痢": 41,
    "這個鑑别診斷": 23,
    "徧體盡腫滿": 23,
    "瘡瘥復發諸候": 61,
    "語\n本候統論瘡": 61,
    "诸惡瘡候\n諸瘡": 61,
    "語\n稱爲惡瘡": 61,
    "瘡候\n膚腠虚": 122,
    "瘡候\n瘑瘡積": 61,
    "雖寥寥數言": 61,
    "癬瘡皮膚乾": 61,
    "敍述症狀來": 61,
    "圓癬候\n圓癬": 61,
    "濕疥候\n濕疥": 61,
    "熱瘡候\n諸陽氣": 61,
    "冷瘡候\n凡身體發瘡": 61,
    "疽瘡候\n此疽瘡": 61,
    "棖疽候\n棖疽": 61,
    "體虚帶風熱": 61,
    "瘡候\n諸瘡": 61,
    "瓠毒瘡候\n俗云": 61,
    "語\n攝領瘡": 61,
    "雞督瘡候\n雞": 61,
    "逸風瘡候\n逸風瘡": 61,
    "瘡瘥復發候": 61,
    "凍爛腫瘡候": 61,
    "凍瘡與凍傷": 61,
    "歷節風候\n歷節風": 32,
    "論養生方導": 32,
    "風熱候\n風熱": 32,
    "變欬嗽唾膿": 32,
    "肺臟氣陰虧損": 32,
    "諸陽經脈爲風": 32,
    "頭掖髆肘風": 32,
    "瘡候養生方導": 32,
    "子爲巔癎疾": 32,
    "語\n風癲疾": 32,
    "尉佗魁結箕踞": 32,
    "惛亂　聯綿": 32,
    "懷容媚諂魅": 32,
    "\n東方震爲長": 32,
    "夫風邪客熱": 32,
    "風瘙身體隱軫候": 64,
    "洪則爲氣强": 32,
    "風瘙癢候稱爲": 32,
    "斷米穀肴鮭": 32,
    "雞子彈丸許": 32,
    "風瘙隱軫生瘡候": 32,
    "熱候\n時氣": 35,
    "瘧候\n時氣": 35,
    "應明確診斷": 35,
    "後猶熱候\n時氣": 35,
    "發復候\n時氣": 35,
    "則頭痛壯熱": 35,
    "瘧後餘熱候\n夫": 35,
    "秋復爲風邪": 70,
    "爲寒熱結實": 35,
    "説明當時對": 35,
    "小兒臟腑實": 35,
    "小兒神氣軟": 70,
    "餘勢　猶言餘邪": 35,
    "膽主謀慮決斷": 15,
    "無漸變過程": 15,
    "與現代醫學": 15,
    "鬱冒　鬱悶": 15,
    "與揮霍繚亂": 25,
    "衍文據本候文義": 25,
    "謂陰陽卒厥絶": 25,
    "關節氣脈舒": 25,
    "風熱則弛縱": 25,
    "顖張　顖門脹": 36,
    "臨牀當審證": 36,
    "熱氣隨脈衝": 55,
    "滯頤候\n滯頤": 36,
    "繞兩目連額": 78,
    "隨候\n夫風邪": 36,
    "語\n本候論述小兒": 36,
    "欬逆候\n欬": 53,
    "腫滿候\n小兒腫滿": 36,
    "雖云兒科雜": 36,
    "臟内客熱與": 36,
    "馬痹候\n馬痺": 36,
    "隨日數血脈骨節備": 36,
    "禀生　義猶": 36,
    "小兒攧撲損瘀": 36,
    "與胎産月經": 34,
    "經帶胎産諸": 34,
    "候敍述較詳": 34,
    "羸瘠　聯綿": 34,
    "則欬嗽喘悶": 34,
    "瘙癢爲邪微": 34,
    "寒温乖適　": 34,
    "任脈爲經脈": 55,
    "文諸候論月經": 34,
    "黄候\n勞傷": 55,
    "傷寒候\n經": 39,
    "當針補陽明": 39,
    "滙集諸陽經": 39,
    "云冬時嚴寒": 39,
    "傷寒三陽三陰經": 39,
    "語\n本候論述傷寒": 39,
    "諸陰陽經絡": 39,
    "傷寒斑瘡候\n傷寒": 39,
    "發斑瘡隱軫": 39,
    "豆瘡候\n傷寒熱": 39,
    "豆瘡後滅瘢候": 39,
    "傷寒謬語候\n傷寒": 39,
    "爲陽氣來復": 39,
    "傷寒煩悶候": 39,
    "傷寒嘔候\n傷寒陽明": 39,
    "這些辨證論": 39,
    "傷寒噦候\n傷寒": 39,
    "這與熱毒極盛": 37,
    "伊火丹候\n丹": 37,
    "鬱火丹候\n丹發從": 37,
    "廢竈火丹候\n丹發從足趺": 37,
    "螢火丹候\n丹發": 37,
    "爲兒科臨牀": 65,
    "風瘙隱胗候": 37,
    "語\n本候類": 37,
    "小兒爲風冷": 37,
    "則五臟調適": 37,
    "語\n本候詳論": 37,
    "將茱萸火丹": 13,
    "語\n室火丹": 13,
    "從天竈火丹": 13,
    "廢竈火丹候\n廢竈火丹": 13,
    "語\n瘑火丹": 13,
    "對瘑瘡形態": 13,
    "猶言寒熱連綿": 42,
    "劇悶頓　猶言": 42,
    "語\n本候論小兒嘔": 42,
    "哯候\n小兒": 42,
    "結候\n五臟": 42,
    "云癥瘕癖結": 42,
    "冷甚則利青": 42,
    "冷熱利候\n小兒": 42,
    "則變爲赤白滯利": 42,
    "蓋病機見證": 42,
    "毫毛髮鬇鬡": 42,
    "實屬小兒營養": 42,
    "這裏歸納爲": 42,
    "與氣機壅塞": 9,
    "脹滿則内見氣滯": 9,
    "噎候\n夫陰陽": 9,
    "語\n本候將": 9,
    "張雞峯亦云": 9,
    "轉轉　猶謂": 9,
    "爲風邪冷熱": 6,
    "絡脈爲風邪": 6,
    "腎三經支脈": 7,
    "對後世論證欬嗽": 17,
    "後文久欬嗽": 17,
    "小兒諸欬嗽": 17,
    "語\n本候論述欬嗽": 17,
    "瘧氣隨經絡": 15,
    "熱則　原無": 15,
    "臨證還當根據具體": 15,
    "温瘧候\n夫": 15,
    "間日瘧候\n": 15,
    "風瘧候\n夫瘧": 15,
    "無時瘧候\n夫衛氣": 15,
    "久瘧候\n夫瘧": 15,
    "夫瘧歲歲發": 15,
    "\n夫五臟調": 12,
    "\n關脈細微": 12,
    "參閲飲癖候": 12,
    "語\n對食魚鱠": 12,
    "\n尻太陽脈": 18,
    "總結歸納爲": 18,
    "語\n從本候敍證來": 18,
    "據本候文義補": 18,
    "寒熱雜説認": 18,
    "項　爲三陽經": 18,
    "釘疽發兩髆": 18,
    "脈疽發環項": 18,
    "澤頗腫處淺": 18,
    "俠榮疽發脅": 18,
    "疽發赤白膿": 18,
    "宋光宗趙惇": 18,
    "癰候大體類": 18,
    "聾候論述較詳": 8,
    "聾候\n腎爲": 8,
    "陽明大腸脈": 8,
    "萬物陽氣傷": 20,
    "條養生方導": 20,
    "\n勞傷腎氣": 20,
    "候\n夫勞傷": 20,
    "謂卒然傷損": 20,
    "謂墜墮損傷": 20,
    "語\n本候叙": 20,
    "竭則經絡澀": 20,
    "經絡澀則榮衛": 20,
    "後損候\n夫": 20,
    "後發瘡候\n": 20,
    "\n養生方導引法云": 72,
    "瘀熱與宿穀": 29,
    "茵陳蒿湯證": 31,
    "黄候\n瘀熱": 29,
    "據本候文義": 57,
    "黄發癖候\n夫": 29,
    "勞倦飲食過": 10,
    "與卷四虚勞嘔": 10,
    "瘻　原義爲頸部生瘡": 4,
    "痂疕疥癘癡聾盲": 4,
    "語\n九蟲爲腸道": 4,
    "諸癰疽癬瘻瘑疥齲蟲": 4,
    "雖稱爲三蟲": 4,
    "嘔吐候\n嘔": 7,
    "言冬時觸冒風寒": 15,
    "據本書卷二風頭眩候": 36,
    "毛羽倮鱗介": 36,
    "敍證則較複雜": 36,
    "風頭眩候養生方導": 36,
    "頦　本書卷二風頭眩候": 36,
    "漸侵食腑臟盡": 36,
    "風濕痺候參閲": 36,
    "言五臟雖隱": 7,
    "喻脈象堅搏": 7,
    "隋煬帝楊廣": 7,
    "運氣時舒緩": 7,
    "緩從容與柔暢": 7,
    "枝條阿阿然": 7,
    "況實數與輕緩": 7,
    "言脛則統胻": 7,
    "個時辰屬土": 7,
    "云三尸諸蟲": 12,
    "季夏瘥春劇": 7,
    "候養生方導": 77,
    "痼結候\n積": 7,
    "爲寒氣與陰陽": 7,
    "猶言恩澤廣": 1,
    "風寒濕三氣雜": 91,
    "風從柬方來": 30,
    "風癔候\n風邪": 30,
    "雙聲叠韻聯綿": 30,
    "諸陽爲風寒": 30,
    "與風口噤候": 30,
    "風痙候\n風痙": 30,
    "張候\n風邪": 30,
    "疽候養生方導": 30,
    "風身體　原無": 30,
    "白髮候養生方導": 30,
    "風痹候養生方導": 30,
    "風不仁候\n風": 30,
    "風驚候\n風驚": 30,
    "傷寒餘熱候\n傷": 46,
    "傷寒五臟熱候\n傷": 46,
    "黄候\n陽明": 46,
    "傷寒陰陽毒候\n夫": 46,
    "飲柴胡證罷": 46,
    "洪大榮氣長": 46,
    "語\n壞傷寒": 46,
    "二爲陽熱亢盛": 46,
    "肛爛見五臟": 46,
    "\n夫衛氣晝": 46,
    "范汪療傷寒熱": 46,
    "語\n本候謂": 46,
    "陽勝則發熱": 46,
    "傷寒勞復候": 46,
    "傷寒陰陽易候": 46,
    "漢司馬長卿長門賦": 46,
    "詣華旉視脈": 46,
    "小兒發育障礙": 28,
    "養小兒候\n經": 28,
    "從未見一兒": 28,
    "屬陽明胃實": 28,
    "小兒非時竄": 28,
    "發癎候\n夫小兒": 28,
    "發癎瘥後身體頭": 56,
    "驚癎與食癎": 28,
    "癎發時身體柔軟": 28,
    "爲小兒氣血軟": 28,
    "爲兒科傷寒": 28,
    "傷寒挾實壯熱候\n傷寒": 28,
    "語\n傷寒頭": 28,
    "驚候\n傷寒": 28,
    "傷寒腹滿候\n傷寒": 28,
    "傷寒嗽候\n傷寒": 28,
    "嗽候\n傷寒": 28,
    "論述傷寒欬嗽": 28,
    "兒傷寒餘熱": 28,
    "論述小兒傷寒餘熱": 28,
    "瘡候\n傷寒": 28,
    "語\n傷寒衄": 28,
    "語\n灸瘡膿潰": 5,
    "鍼灸瘡發洪候\n夫": 5,
    "風痺候養生方導": 19,
    "則微腫濕爛": 19,
    "爲風邪濕熱": 19,
    "雖勁風嚴寒": 19,
    "懸癰腫候\n懸癰": 19,
    "蠶齧候\n蠶": 15,
    "鰭骨刺傷後": 15,
    "爲蜱蟎類昆蟲": 15,
    "蜱蟎類昆蟲": 15,
    "現代醫學證實": 15,
    "僕公英莖葉": 15,
    "臨證當具體": 21,
    "氣壅塞爲痞": 21,
    "榮衛經絡斷絶": 21,
    "胞門子户勞傷": 21,
    "熱搏於腑臟": 6,
    "據養生方導": 6,
    "寒熱候\n夫陽虚": 6,
    "則腹脹腸鳴": 6,
    "寒熱厥候\n夫厥": 6,
    "認爲縱慾傷腎": 6,
    "對此臨床應": 6,
    "發爲頭眩仆": 6,
    "語\n流飲從": 17,
    "飲候養生方導": 17,
    "語\n本候實爲諸飲": 17,
    "溢飲候\n溢飲": 17,
    "懸飲候\n懸飲": 17,
    "將虚勞稱爲": 42,
    "勞則榮氣竭": 42,
    "謂毛髮肌膚": 42,
    "乾燥候養生方導": 42,
    "飲候\n勞傷": 42,
    "對症狀敍述則": 42,
    "對客熱證候": 42,
    "虚勞無子候": 42,
    "虚勞則腎氣": 42,
    "衝脈爲陰脈": 42,
    "\n夫風寒濕": 42,
    "聾候\n腎候": 42,
    "勞脈結候\n脈動": 42,
    "虚勞浮腫候\n腎": 38,
    "痢候\n臟腑": 38,
    "虚勞秘澀候": 38,
    "白濁候\n勞傷": 38,
    "明張景岳謂": 38,
    "夢見山嶽熛火": 38,
    "陰萎候\n腎開竅": 38,
    "虚勞陰腫候": 38,
    "發生陰部瘙癢": 38,
    "虚勞陰瘡候\n腎榮": 38,
    "惡風瘮癝寒熱": 11,
    "謂將射工毒蟲": 11,
    "與現代觀察烏頭": 29,
    "據本書目録": 29,
    "將藥汁曝曬": 29,
    "語\n毒蕈種類": 29,
    "過飲腐腸爛": 29,
    "論述姙娠脈": 22,
    "姙娠候\n經云": 22,
    "周后妃妊成王": 22,
    "當慎護驚動": 22,
    "續縷　嗣續": 22,
    "姙娠惡阻候\n惡": 22,
    "猶謂將適調養違": 22,
    "姙娠臨將産": 22,
    "語\n姙娠數墮": 22,
    "爲婦女妊養": 44,
    "産後利候\n産後": 44,
    "産勞傷榮衛": 44,
    "利候\n産勞傷": 44,
    "産後滯利候\n産後": 44,
    "産後客熱利": 44,
    "藴瘀　積久": 44,
    "腫候\n臟氣宿虚": 44,
    "産後陰道開候\n子臟": 44,
    "産後遺尿候\n": 44,
    "候論述産後遺": 44,
    "産後淋候\n": 44,
    "候\n夫産傷損": 44,
    "語\n本候詳論産後": 44,
    "産後欬嗽候\n": 44,
    "産後時氣熱": 44,
    "傷寒候\n觸": 44,
    "語\n産後傷寒": 44,
    "宿經傷暑熱": 44,
    "熱則肢體煩": 44,
    "産後目瞑候\n目": 44,
    "産後耳聾候\n腎氣": 44,
    "瘡候\n産則": 44,
    "結積無子候": 38,
    "積氣結搏於子臟": 38,
    "煩滿候\n煩滿": 38,
    "皮寬膇膇然": 38,
    "金瘡敗壞候\n婦": 38,
    "體虚爲風邪": 38,
    "白秃候\n頭瘡": 38,
    "卒腫候\n夫腫": 38,
    "則時時體熱": 38,
    "瘧候\n夫瘧": 38,
    "從具體證候論": 10,
    "熱則傷爛眥": 39,
    "目膚翳候\n陰陽": 39,
    "從目眥染漸": 39,
    "爲膚翳覆瞳子": 39,
    "臨床應仔細": 39,
    "風熱痰飲漬": 39,
    "瀉臟腑熱邪": 39,
    "證多屬熱屬實": 39,
    "目皰瘡候\n目": 39,
    "目膿漏候\n目": 39,
    "爲暴風客熱": 39,
    "癢濕候養生方導": 7,
    "謂勞傷腎氣": 7,
    "産後乳無汁": 30,
    "悶候\n運悶": 30,
    "語\n本候論述産後": 30,
    "\n夫産損動腑臟": 30,
    "餘疾候\n産後": 30,
    "産後虚羸候": 30,
    "産則勞損腑臟": 30,
    "論癰腫潰膿": 18,
    "與氣腫連類": 18,
    "漿　毒腫頂": 18,
    "腫候\n毒腫": 18,
    "腫潰後候\n凡癰腫": 18,
    "遊腫候\n遊腫": 18,
    "徧身熠熠然": 18,
    "腫色澤鮮明": 18,
    "孫詒讓閒詁": 4,
    "腑臟氣否塞": 4,
    "機論述較詳": 11,
    "候\n腑臟冷熱": 11,
    "則僅對肌膚": 16,
    "腦濕候\n腦濕": 16,
    "與前後諸候": 16,
    "風候養生方導": 16,
    "陽氣盡則臥": 16,
    "陰氣盡則寤": 16,
    "濕熱藴結腸": 6,
    "與日光曝曬": 6,
    "赤皰币币然": 6,
    "支滿候\n姙娠經": 42,
    "姙娠子煩候\n臟": 42,
    "隨經絡虚處": 42,
    "語\n本候論述子": 42,
    "濕熱鬱結爲": 42,
    "姙娠痙候\n體虚": 42,
    "姙婦素體肝腎陰虚": 42,
    "子癎發生時": 42,
    "轉動勞羸　猶言": 42,
    "語\n本候論姙娠": 42,
    "姙娠墮胎後": 126,
    "姙娠胎動安": 42,
    "子臟宿挾疹": 8,
    "孔候\n産子": 8,
    "惡風瑟縮貌": 28,
    "從風聲轉義": 28,
    "桃葉條引蘇頌": 28,
    "發則壯熱煩悶": 28,
    "栝蔞惡乾薑": 28,
    "東海王良夫": 28,
    "隴西辛長緒": 28,
    "山東士諸公": 28,
    "從勞則發温": 28,
    "賴家親見迫奪": 28,
    "温藥與疾爭結": 28,
    "屬太陽經絶": 28,
    "梔子芒硝湯": 28,
    "東周齊國湣王": 28,
    "關問題論述": 28,
    "石發身體腫": 28,
    "祕難候\n將適": 28,
    "發瘡候\n將適": 28,
    "脹滿候\n居處": 28,
    "養生方條文": 15,
    "劉輝\n孫世發": 15,
    "蟲食腑臟傷敗": 5,
    "濕邪驟然積": 5,
    "臨困　猶言": 5,
    "夜夢顛倒　": 5,
    "語\n本候標題論": 22,
    "白髮候養生方補": 22,
    "據本書養生方導": 22,
    "風乘虚隨脈": 22,
    "牙齒蟲候\n牙齒蟲": 22,
    "牙蟲候\n牙蟲": 22,
    "言齒齲病連滯": 22,
    "屬春時陽氣": 44,
    "據本書卷七傷寒": 44,
    "少陰脈貫腎絡": 44,
    "陰陽諸經傳": 44,
    "熱與穀氣相": 44,
    "時氣噦候\n伏熱": 44,
    "據本書卷七傷寒噦候": 44,
    "時氣發斑候\n夫熱": 44,
    "發斑爲熱毒": 44,
    "時氣瘙瘡候\n夫": 44,
    "爲風氣散逸": 44,
    "據本書卷八傷寒濕": 44,
    "利候\n夫熱": 44,
    "黄候\n夫時": 44,
    "易候\n夫時氣": 44,
    "鄭讀烈假爲厲瘕": 17,
    "語\n本候首論癥瘕": 17,
    "次論癥與瘕": 17,
    "與臟氣相搏結": 17,
    "語\n暴癥發": 17,
    "關經絡腑臟": 17,
    "記載頗爲詳細": 6,
    "金瘡初傷候\n夫": 24,
    "金瘡候論小兒金刃": 24,
    "謂斷腸縫合處": 24,
    "漢代名醫華佗": 24,
    "與現代創傷": 24,
    "金瘡驚腫候\n夫金瘡": 24,
    "癰腫候\n夫金瘡": 24,
    "縫合時松緊適": 24,
    "變證發生後": 24,
    "與傷寒大異": 38,
    "噦候\n伏熱": 38,
    "肛爛見腑臟": 38,
    "陰陽易候\n陰陽": 38,
    "統稱爲疫癘": 38,
    "疫癘皰瘡候\n熱": 38,
    "雖暴壯熱煩滿": 38,
    "濕熱雜毒惡氣": 38,
    "爲廣義傷寒": 27,
    "皮膚毫毛聳": 27,
    "熱病斑瘡候\n夫熱": 27,
    "臟六腑井滎俞": 27,
    "勞復候\n夫": 27,
    "醫學數據庫": 1,
    "\n標準書號": 1,
    "屬印裝質量問題請與": 1,
    "許仁則文尚": 7,
    "牡痔候\n肛邊": 7,
    "牝痔候\n肛邊腫": 7,
    "脈痔候\n肛邊": 7,
    "腸痔候\n肛邊腫": 7,
    "張收嘗為猘": 6,
    "風經五臟驚悸": 8,
    "驚悸候\n夫": 8,
    "語\n本候詳細論": 12,
    "與灸足陽明別豐隆": 14,
    "保義郎頓公": 14,
    "張付藥數貼": 14,
    "予隨朝承應": 14,
    "目內眥赤發牽睛": 9,
    "氣則生為癰瘍": 3,
    "楊後山公祖": 7,
    "李漸庵公祖": 7,
    "脈氣將危絕": 7,
    "錦衣張少泉公": 7,
    "王会泉公亚": 7,
    "寒暑風雨溫涼燥濕": 2,
    "班固序艺文志": 2,
    "與夫陷中宛宛": 1,
    "謂誅伐無過": 2,
    "蓋憂思喜怒飲食動": 2,
    "阏注羸痼斯": 2,
    "\n六十三難": 2,
    "彰厥旨昔皇甫玄晏": 2,
    "絡脈與厥陰": 2,
    "寫陽補陰經": 3,
    "顳顬目挈脈": 2,
    "湧泉與陰陵泉": 2,
    "無實實虛虛": 1,
    "衡居爲二痏": 1,
    "夏月陽氣盡": 1,
    "問虛實寒熱": 1,
    "痿枢折挈胫": 2,
    "陽氣盡陰氣": 1,
    "風寒濕氣客": 1,
    "俞跗医缓扁鹊秦": 1,
    "子發為癲疾": 1,
    "結絡堅緊火": 1,
    "聾氣痞聽會針": 1,
    "金門聽會疾": 1,
    "皮內隨針氣": 1,
    "須針瀉三隂": 1,
    "懸鍾二陵三隂": 1,
    "閉澀大敦燒": 1,
    "撚針尋子午": 1,
    "\n况夫隂陽": 4,
    "俞以寫陰邪": 1,
    "風氣濡微細": 1,
    "臍風須然谷": 1,
    "厥熱湧泉清": 1,
    "兌端獨瀉太陽經": 1,
    "暑則氣淖澤": 1,
    "與鹿豕狉狉然": 1,
    "陽主生陰主殺": 1,
    "風則為長針": 1,
    "緩節監監然": 1,
    "頭項強承漿": 1,
    "癇發癲狂兮": 1,
    "與陰諸絡會": 1,
    "夫過關過節": 1,
    "蓋經絡晝夜": 1,
    "长桑君天星": 1,
    "季胁本侠脊": 1,
    "寒水克君火": 7,
    "云雨昏暝埃": 12,
    "陈立明先生": 1,
    "景岳金水六君": 2,
    "新城新藏氏": 14,
    "阿兰金兹勒": 8,
    "芦墟迮耕石": 6,
    "Thmas winis": 10,
    "泽姆斯维力斯": 10,
    "隋·甄立言": 1,
    "托马斯·威廉": 1,
    "小腸痃癖氣": 68,
    "補藥麝臍圓": 68,
    "補藥麝臍圓\n麝臍": 68,
    "扁鵲玉壺丹": 73,
    "澀精金鎖丹": 68,
    "\n救生圓\n": 68,
    "煉蜜圓桐子": 68,
    "當舍證從脈": 1,
    "飢飽勞役則敗": 1,
    "察聲色形證": 1,
    "周錫瓚跋云": 10,
    "孫星衍序云": 5,
    "太上延年萬勝": 5,
    "後愛子倉舒": 5,
    "從陰陽否格": 5,
    "察聲色形證決": 6,
    "張藥房題詩": 5,
    "文瑞樓石印本": 5,
    "高孝兩朝諱": 5,
    "經勘誤訂訛": 1,
    "屬孫本顯誤": 1,
    "實爲艱辛倍": 1,
    "蓋五臟爲陰": 1,
    "\n𣦢\n𧌒\n論": 1,
    "程國彭則歸結": 1,
    "實爲本書論": 1,
    "凡屬印裝質量問題請與": 1,
    "論突變脈候": 1,
    "\n𣲆\n本論爲": 1,
    "論腎臟虚實寒熱": 2,
    "腎臟虚實寒熱": 2,
    "腎脈來喘喘": 2,
    "腎臟諸證候": 2,
    "賴診察形證脈氣": 1,
    "小腸實則傷熱": 1,
    "論將絶則髮": 1,
    "次論憑脈運": 1,
    "論癰疽瘡腫": 1,
    "癰疽瘡腫發": 1,
    "論肝臟虚實寒熱": 1,
    "\n足厥陰肝爲風木": 1,
    "論肺臟虚實寒熱": 1,
    "寒熱諸證臨": 1,
    "實則時夢築垣牆": 1,
    "四論腳氣與氣腳": 1,
    "爲氣腳與腳氣": 1,
    "次論膽腑虚實寒熱": 1,
    "論膽虚實寒熱": 1,
    "脈證實爲風痺": 1,
    "實則謂經絡閉澀": 1,
    "瓚本眉批云": 1,
    "宋本醫學書": 1,
    "無論陽厥陰厥": 1,
    "温補脾腎爲": 1,
    "對陽貴陰賤": 1,
    "爲總論陰陽": 1,
    "爲本書總論": 1,
    "儿稚阴稚阳": 26,
    "郑钦安阳复": 6,
    "棣孙君文毅": 2,
    "傅疮痍疥癞": 3,
    "方證譌謬不倫": 5,
    "幸賴趙開美": 5,
    "宋秘閣林億": 5,
    "唐顔師古讀": 5,
    "\n4.摶與搏": 5,
    "子目條文云": 10,
    "醫家皇甫謐": 5,
    "金成無己凡": 5,
    "編次仲景遺論": 5,
    "採仲景舊論": 8,
    "爲仲景遺言": 5,
    "闡發仲景遺言": 5,
    "夫陽盛陰虚": 5,
    "錢超塵\n語譯": 5,
    "錢超塵\n二": 5,
    "應宗梔子乾薑湯": 2,
    "與禹餘粮丸": 2,
    "語\n此條應與": 2,
    "對太陽中風證": 2,
    "語\n本條論": 12,
    "宋　林　億": 34,
    "沈　琳仝校\n": 21,
    "黄連瀉心湯證": 9,
    "薑瀉心湯證": 9,
    "語\n此條論": 18,
    "復與柴胡湯": 9,
    "陰陽氣並竭": 13,
    "語\n證爲熱痞": 9,
    "赤石脂禹餘粮湯": 9,
    "語\n本條舉誤": 9,
    "語\n本證爲": 9,
    "與瀉心湯證": 9,
    "爲風寒濕痺": 9,
    "陽明府實燥熱": 1,
    "陽明府實痞滿": 1,
    "屬大承氣湯證": 1,
    "屬茵蔯蒿湯證": 1,
    "屬小承氣湯證": 3,
    "屬調胃承氣湯": 1,
    "與大承氣湯": 1,
    "\n夫陽盛陰虚": 3,
    "莫見此傾危": 3,
    "語\n讀本條當詳參": 3,
    "明趙開美摹": 1,
    "荆淮海岱雜齊": 1,
    "趙開美序\n": 1,
    "數脉當遲緩": 4,
    "語\n本條當": 4,
    "語\n傷寒欬": 2,
    "論太陽經邪": 2,
    "\n太陽陽明": 2,
    "梔子生薑豉湯": 2,
    "梔子乾薑湯": 6,
    "\n傷寒陽脉濇": 2,
    "與小建中湯": 2,
    "語\n本條與": 4,
    "陽明兩經合": 2,
    "應見二陽經": 2,
    "黄連湯證爲": 2,
    "陽明實熱燥結證": 2,
    "屬當歸四逆湯": 2,
    "語\n本條脉證": 2,
    "語\n本條證情": 2,
    "\n趺陽脉遲": 2,
    "傷寒發熱頭": 2,
    "傷寒脉陰陽": 2,
    "無太陽柴胡證": 2,
    "\n藏結無陽證": 2,
    "沈　琳仝校\n辨陽明": 2,
    "\n陽明熱證": 2,
    "梔子豉湯證": 2,
    "梔子蘗皮湯證": 2,
    "與調胃承氣湯": 8,
    "\n傷寒瘀熱": 2,
    "語\n本條論述陽明": 2,
    "語\n風為陽": 2,
    "飽則微煩頭眩": 2,
    "語\n本證病機": 2,
    "昔時仲景傷寒": 3,
    "語\n本條爲": 14,
    "屬梔子豉湯": 4,
    "屬梔子豉湯證": 20,
    "屬旋復代赭湯": 4,
    "屬梔子厚朴湯": 4,
    "這爲後世論": 4,
    "屬調胃承氣湯證": 4,
    "後十九條則闡": 5,
    "語\n太陽中風證爲": 5,
    "爲太陽經氣": 5,
    "爲固陽攝陰": 5,
    "見微惡風寒": 5,
    "與翕翕發熱": 5,
    "語\n本條論述": 5,
    "語\n本條義": 5,
    "躁煩必發讝語": 1,
    "十餘日振慄": 1,
    "煩躁爲驚狂": 1,
    "補述大承氣湯證": 1,
    "湯證症狀重": 1,
    "語\n從本條": 1,
    "\n夫實則讝語": 1,
    "語\n陽明裏實證": 1,
    "論陽明熱證": 1,
    "小青龍湯證": 4,
    "太陽陽明合": 2,
    "大青龍湯發": 2,
    "湯隨證良驗": 2,
    "語\n本條運": 1,
    "允稱言簡意賅": 1,
    "遲則陰氣盛": 1,
    "諸陽浮數爲": 1,
    "諸陰遲濇爲": 2,
    "扁鵲倉公無": 4,
    "陽虚陰竭證則": 4,
    "與太陽傷寒證": 4,
    "當據脉證爲": 4,
    "語\n太陽傷": 4,
    "語\n本條見證": 4,
    "語\n本條論少陰陽氣鬱閉": 4,
    "語\n本證與陽明": 4,
    "據元廣勤書堂": 1,
    "吳茱萸湯證": 2,
    "黄連人參湯": 2,
    "語\n本條爲厥陰": 2,
    "\n傷寒脉遲": 2,
    "寒先厥後發熱": 2,
    "釋爲陽氣爲邪": 2,
    "斷本證爲陽": 2,
    "兩條論厥陰熱利證": 2,
    "噦與腹滿並見": 2,
    "屬印裝質量問題請與本社市場營銷": 1,
    "陽明濕熱發黄": 1,
    "茵蔯蒿湯爲": 1,
    "語\n本證當": 1,
    "與大承氣湯證": 1,
    "僅爲陽明燥熱壅滯": 1,
    "語\n此爲實熱": 1,
    "語\n證爲寒濕": 1,
    "論濕熱發黄證": 1,
    "茵蔯蒿湯證爲熱": 1,
    "湯證爲濕熱": 1,
    "語\n傷寒厥證": 1,
    "氣機鬱抑爲": 1,
    "語\n本條諸證": 1,
    "語\n本條補述少陽": 1,
    "討論並與傷寒": 1,
    "語\n證屬陽": 1,
    "語\n本條論傷": 1,
    "語\n上條論": 1,
    "語\n本條言風濕": 1,
    "當節勞静養": 1,
    "語\n本條論傷寒": 1,
    "伍青春玉容": 2,
    "723873": 5,
    "648637": 2,
    "647577": 1,
    "82182": 1,
    "子夜寒战鼓栗": 1,
    "夫宫商角徵羽": 2,
    "二没食子酰基": 87,
    "没食子酰基": 220,
    "苯甲酰戈米辛": 12,
    "\n丹参酮ⅡA": 23,
    "艾里莫芬烷": 27,
    "磺酰罗丹明": 4,
    "胡蔓藤碱丁": 6,
    "唐松草亭碱": 28,
    "贝加尔唐松定碱": 14,
    "贝加尔唐松灵碱": 28,
    "沉寒痼冷伏": 9,
    "12743": 1,
    "丑寅卯辰巳": 5,
    "午未申酉戌亥": 7,
    "050704": 9,
    "050412": 9,
    "050402": 9,
    "050903": 9,
    "辨厥利呕哕": 2,
    "　　　　　　　　　": 14,
    "　　　　　　　": 11,
    "威汉代医简": 14,
    "　　　　　　　　": 12,
    "付子卅果凡": 1,
    "唐京兆华原": 7,
    "劉氏倡火熱": 18,
    "首論傷寒雙": 18,
    "浪華書肆田緣叔平": 18,
    "筆劃數爲序": 18,
    "\n五臟濕屬": 6,
    "寒濕\n夫裏": 6,
    "與名醫張子": 14,
    "張氏這種觀點": 14,
    "三邪理論\n對": 14,
    "繼承並擷採": 14,
    "矯庸醫恃補": 14,
    "爲贄幣瑞節": 16,
    "當歸丸\n當歸": 12,
    "饋予　饋贈": 16,
    "蹙踘張承應": 16,
    "蹴蹋爲戲樂": 16,
    "熱勝寒則陰": 1,
    "詭詐譎怪　": 1,
    "昔聞山東楊": 1,
    "蓋厥陰與衝": 1,
    "夫遺溺閉癃": 1,
    "\n昔審言爲": 1,
    "\n少陰司天": 1,
    "\n太陰司天": 1,
    "\n陽明司天": 1,
    "\n太陽司天": 1,
    "濕復則鱗見": 1,
    "編\n傷寒雙": 7,
    "風淫末疾　風邪": 7,
    "云憂恚氣結": 1,
    "攪藥數百餘轉": 19,
    "無垢軟帛揾": 19,
    "金絲膏\n貼": 30,
    "唾津調塗紙": 30,
    "布條子約纏": 30,
    "\n生肌斂瘡藥": 30,
    "萬聖神應丹": 30,
    "東南爲頭圍": 30,
    "臘月雀腦子": 30,
    "\n善應膏藥": 30,
    "小兒癬雜瘡": 30,
    "將臘月猫糞": 30,
    "塗燒湯火瘡": 30,
    "雞翎掃燙處": 30,
    "臘猪脂調塗": 30,
    "繞車輪數匝": 8,
    "\n太腸脛腫": 8,
    "眥赤發牽睛": 21,
    "稱爲烏頭閥閲": 21,
    "陽明大腸經": 21,
    "武陽仇天祥": 21,
    "\n傷寒極熱": 21,
    "安喜趙君玉": 21,
    "\n惡寒實熱": 21,
    "濕熱與宿穀": 12,
    "窈滿中綿綿": 12,
    "君怪無烏梅": 12,
    "穎臯韓吉卿": 12,
    "瀕海鹵斥　": 2,
    "蓋性無毒則": 2,
    "藥物種類衆": 2,
    "藴畜濁惡熱": 2,
    "小兒瘡疱丹熛癮疹": 1,
    "對仲景學説": 1,
    "啟玄子注云": 2,
    "\n解利傷寒濕": 1,
    "\n予嘗見世醫": 1,
    "慎勿車載馬": 1,
    "豈知種種客熱": 1,
    "烏頭藥\n細針沙蕎大麥釅": 8,
    "謂譖言漸進": 6,
    "\n謗峻藥\n": 6,
    "傷寒疫氣動時輒": 6,
    "少陽客氣勝": 1,
    "變炎烈沸騰": 1,
    "言憂則氣結": 14,
    "何足應變無窮": 14,
    "洛陽孫伯英": 14,
    "棠谿欒彦剛": 14,
    "進食丸\n牽牛": 34,
    "當丸\n蝱蟲": 34,
    "書生鼎足題": 1,
    "併與聖散子": 10,
    "選甚癱風與": 10,
    "頭項遍腫連": 10,
    "爲厥陰風木": 5,
    "詵詵丸\n療婦": 7,
    "萆麻子\n研爛": 7,
    "碁盤利開摻藥": 10,
    "陰暑丁火\n": 12,
    "體無膏澤　身體肌膚乾": 12,
    "聞木聲則惕": 12,
    "獨閉户塞牖": 12,
    "緑礬　藜蘆": 10,
    "芍藥蘗皮丸\n芍藥": 13,
    "湧嗽\n楊壽": 8,
    "堅諱　堅決隱瞞": 8,
    "秋庚辛採子": 9,
    "荆三稜　廣荗": 9,
    "芍藥當歸\n": 9,
    "何首烏　防風": 9,
    "號泣爲強良": 1,
    "鐵鈴木壺雜戲": 1,
    "子發爲巔疾": 1,
    "夫瘧疾連歲": 1,
    "五苓與益元": 1,
    "夫小兒風熱涎嗽": 1,
    "夫小兒瘡疥風癬": 1,
    "從遊張君仲傑": 1,
    "經則子午君": 1,
    "熱藥爲補哉": 1,
    "聰明莫己若": 1,
    "實與愚夫殆": 1,
    "對醫藥理論": 1,
    "\n遍訪醫門": 1,
    "仲景十棗湯": 1,
    "體陰陽氣血動態": 1,
    "丹熛瘡疹發": 1,
    "薑附湯\n乾薑": 8,
    "長安中浩穰": 14,
    "\n標本運氣": 14,
    "陽明從中濕": 14,
    "\n風從火斷": 14,
    "徹開軒岐無縫鎖": 14,
    "謝軒岐萬世恩": 14,
    "\n瘡癤瘤腫": 2,
    "三唾毒腫隨": 2,
    "勅斬蛜蜥滅": 1,
    "枳殻丸\n商枳殻　牽牛頭": 16,
    "爲君火主熱": 7,
    "爲陽實陰虚": 7,
    "積久石熱結": 7,
    "夫陰陽興衰": 7,
    "謂瀉實補衰": 7,
    "黄連　栝萋": 7,
    "婦人五勞七傷": 7,
    "霍司承君祥處復見": 7,
    "\n牙宣藥\n撥": 4,
    "諸般食飲無": 5,
    "付儒醫聞忠": 2,
    "\n頭風眩運": 1,
    "余屢見孕婦利膿": 4,
    "兩目轉昏濇": 4,
    "風暖處頻浴": 1,
    "備急丹\n暑門獨": 6,
    "防風通聖散": 6,
    "防風當歸飲子": 6,
    "午飯併夜飯": 6,
    "\n昔維陽府判趙": 1,
    "監察陳威卿": 1,
    "風烏犀鐵彈丸": 1,
    "將陽經爲熱": 1,
    "熱則筋弛縱": 1,
    "屬五運六氣": 1,
    "當丁壬屬木": 1,
    "余調承氣湯": 1,
    "闕一則飲食廢": 1,
    "王太僕註云": 1,
    "厥疾獲瘳記": 1,
    "余昔過夏邑": 1,
    "軟金丸諸藥": 1,
    "發過米飲調": 2,
    "夏月積熱暑": 1,
    "夫癭囊腫悶": 1,
    "高良薑山梔子": 2,
    "\n諸氣憤鬱": 5,
    "\n瀉利惡寒": 1,
    "小兒風熱涎嗽": 1,
    "瀉肝經風熱鬱": 1,
    "防風湯\n防風": 15,
    "聖眼藥\n蕤仁": 6,
    "綫絹細濾過": 6,
    "預計嬰兒將": 1,
    "梔子茵蒿湯": 1,
    "足三陽從頭": 1,
    "燔灸　燔針": 1,
    "屬甲乙風木": 1,
    "體氣機調暢": 1,
    "廣腸　乙狀結腸": 1,
    "爲支滿鶩溏": 1,
    "蓋謂戊己見": 1,
    "\n凡風衝泣": 1,
    "爲飲食麤糲": 1,
    "無勝則無復": 1,
    "伊令伯德修": 1,
    "袁　斌　高　雪": 2,
    "谢　纬　谢　慧": 2,
    "栀豉杏仁芩": 1,
    "CTG ATG ATG CCC ACC AAA GTC": 11,
    "\n爪兰枫斗": 37,
    "保罗·塞缪尔森": 1,
    "翁文学具茨": 6,
    "缪希雍仲淳甫": 16,
    "方　高存之": 1,
    "余诊毕论云": 1,
    "俞观察　阳明": 1,
    "方　　药\n": 16,
    "袁蜜山景云": 81,
    "胡司马少泉": 78,
    "\n子　　嗽": 39,
    "\n子　　痫\n": 39,
    "\n子　　喑\n喑音": 39,
    "　　痢\n凡": 39,
    "张公三君葆华": 16,
    "\n风　　痧\n": 110,
    "\n暑　　痧\n": 110,
    "阴　　痧\n": 110,
    "阳　　痧\n": 110,
    "乌　　痧\n": 110,
    "\n泻　　痧\n": 110,
    "哕痧\n痧凌": 110,
    "慕抚军天颜": 21,
    "刘诚意伯言": 1,
    "胡名迦拘勒": 1,
    "异戊酰氧基": 1,
    "  Maxim": 2,
    "环己肽ⅩⅢ": 1,
    "环己肽ⅩⅣ": 1,
    "环己肽ⅩⅤ": 1,
    "环己肽ⅩⅥ": 1,
    "尻股膝髀腨䯒": 2,
    "卯酉少阴君火": 13,
    "蛭虻蛴漆芍": 1,
    "芩连丹柏药荷": 1,
    "     ": 4,
    "\nOGTT": 1,
    "陈久蛇鳞煆": 1,
    "黄云笼翠岫": 5,
    "窃以动植形生": 1,
    "文\n禀乞饬": 2,
    "丁小　痧子": 2,
    "薛小　痧子": 2,
    "宋右　暑湿": 1,
    "\n子午卯酉": 1,
    "王老先生　": 1,
    "郑传笈云仲甫": 31,
    "殷步湘彤卿甫": 1,
    "柳梢袅袅飐": 1,
    "钱存济堂丸散膏丹": 1,
    "寅申主少阳": 1,
    "\n子午少阴君": 1,
    "寅午未酉戌亥": 1,
    "阳明司卯酉": 1,
    "金老谈京大戟": 30,
    "金老谈使君子": 17,
    "翁有良辨云": 19,
    "金老谈川贝母": 16,
    "金老谈常山": 14,
    "金老谈柏子仁": 52,
    "金老谈泽兰": 65,
    "金老谈狗脊": 15,
    "金老谈白薇": 52,
    "金老谈益智仁": 30,
    "金老谈石决明": 46,
    "金老谈穿山龙": 13,
    "金老谈苏合香": 13,
    "金老谈谷芽": 16,
    "金老谈远志": 45,
    "\nSOJIA": 13,
    "\nFirestein": 9,
    "何高风隐德": 13,
    "\n糊　　斗\n": 30,
    "\n笔　　觇\n": 30,
    "\n墨　　匣\n": 30,
    "\n念　珠\n": 36,
    "\n松　轩\n": 5,
    "宫商角徵羽": 3,
    "商角徵羽宫": 1,
    "秦誓诅楚文": 11,
    "唐太宗李碑": 11,
    "\n文　履\n": 25,
    "黄\n玉宝相": 11,
    "魁魋魓魒尊帝星君": 1,
    "昔鲁定公母": 1,
    "昔宋英宗皇帝": 1,
    "文通龙忠迪": 2,
    "恢兮爰集兹": 1,
    "092270": 6,
    "　　　　 ": 2,
    "　　　　　　": 11,
    "元明八大家": 5,
    "60895": 1,
    "\nMTET": 14,
    "\n源候\n夫": 103,
    "\nUchida": 7,
    "世界中医药联合会睡眠医学专业委员会常务理事": 1,
    "中华中医药学会急诊分会委员": 1,
    "北京中医急诊专业委员会顾问": 1,
    "国家食品药品监督管理局国家基本药物评审专家": 1,
    "北京中医药学会常务理事": 1,
    "北京中医药学会妇科专业委员会主任委员": 1,
    "《北京中医药》杂志编委会委员": 1,
    "\n": 152,
    "037641": 1,
    "0016222": 13,
    "0067557": 6,
    "0039879": 14,
    "名古屋玄医": 14,
    "丹波元胤氏": 14,
    "金元滑伯仁": 14,
    "024436": 4,
    "水花儿": 3,
    "芷柏": 1,
    "肤腠虚": 1,
    "封狼胥": 101,
    "寇攘": 101,
    "裨阳": 18,
    "温养天癸": 18,
    "宣痹通阳": 31,
    "绿蕚梅": 14,
    "寒凝精稠": 9,
    "伍萆薢": 9,
    "擂鼓": 8,
    "悉瘥": 6
}