{"6个月": 33127, "30分钟": 87058, "6小时内": 2111, "24小时内": 10844, "4小时内": 1122, "12小时后": 2167, "48小时": 6313, "6天后": 931, "10小时后": 636, "10天": 30662, "3小时后": 1364, "14天": 12161, "24秒": 72, "6小时以内": 154, "14天内": 402, "3分钟内": 531, "5分钟以上": 386, "3～12个月": 345, "3～6个月": 6045, "近3个月": 2709, "2小时": 30813, "3分钟": 8725, "10分钟": 30638, "15分钟内": 803, "15秒钟": 71, "14小时内": 56, "1天内": 861, "24小时": 33797, "2分钟内": 515, "5分钟": 23780, "1～2个月": 3140, "1～3个月": 2025, "1个月": 50712, "3小时内": 1683, "1小时以上": 1936, "前2个月": 154, "前1个月": 480, "48小时内": 4233, "5分钟以下": 26, "10分钟以上": 311, "30分钟内": 2306, "15分钟后": 3702, "4小时": 8607, "25分钟后": 210, "45分钟内": 54, "6～18个月": 101, "2天": 22397, "一个月": 8861, "15分钟": 20837, "30天": 9577, "60分钟以上": 238, "3个月": 59222, "每3个月": 1481, "10小时": 1690, "6分钟": 1554, "2分钟": 9761, "45分钟": 1806, "20天": 9136, "1小时": 39775, "7天": 36429, "3天内": 3411, "3天": 49382, "2个月": 31017, "72小时": 3218, "10天左右": 1883, "2～3个月": 5466, "10分钟后": 5322, "9个月": 4138, "4～6个月": 824, "40分钟": 6548, "3天以上": 698, "超过6个月": 1095, "20分钟": 15855, "2分钟后": 1402, "1分钟后": 1780, "5天后": 5860, "1分钟": 23585, "2天后": 5148, "8分钟": 994, "24小时后": 7517, "12秒": 199, "20秒": 1011, "20秒以上": 42, "24小时以上": 542, "15天": 11927, "30分钟左右": 2227, "5分钟后": 5224, "25秒": 154, "5天内": 2163, "3小时": 8766, "15天后": 1217, "6小时": 7829, "12小时": 6791, "30分钟后": 7363, "8小时内": 1030, "20分钟后": 2501, "4小时后": 2718, "1": 224, "10天后": 4626, "每个月": 1266, "224天": 2, "3个多月": 1077, "7天内": 2041, "5分钟内": 2109, "6小时以上": 1069, "15个月": 586, "2天以上": 578, "10分钟左右": 2968, "2～6个月": 406, "4天": 9550, "6～12个月": 872, "2.5～3个月": 7, "3.5个月": 178, "1秒后": 30, "第3个月": 551, "第5个月": 13, "7天后": 6288, "6天": 7567, "2天内": 2317, "1小时内": 2079, "12小时以上": 573, "2秒": 405, "15秒": 729, "60分钟后": 791, "7天左右": 761, "1天": 15318, "1天多": 67, "5天": 28518, "3天前": 3032, "7天前": 337, "30秒": 5176, "半个月": 6826, "7天以上": 1482, "10天前": 1645, "11天": 1346, "8天": 3000, "42天": 924, "5天前": 1680, "8个月": 3941, "1分钟左右": 1136, "6.3个月": 40, "14个月": 286, "20天前": 590, "18天": 1055, "43天": 239, "4个月": 9285, "3天以内": 604, "4天以后": 81, "30分钟以上": 1514, "20分钟左右": 1251, "四五个月": 314, "五个月": 290, "3天后": 10188, "28天": 3770, "48天": 334, "1小时后": 5495, "4天后": 3189, "120分钟": 1828, "120分钟后": 71, "1天后": 1709, "4天前": 956, "30天后": 1292, "7个月": 2730, "2小时后": 4504, "2天前": 1966, "8小时": 3605, "50天左右": 66, "29天": 296, "35天": 931, "3分钟后": 1198, "5个月": 5700, "2小时左右": 1225, "6～7个月": 73, "5分钟左右": 1411, "两个多月": 678, "近1个月": 2707, "1个多月": 730, "两个月": 5404, "10个月": 2305, "近两个月": 568, "三个月": 4634, "近2个月": 1863, "怀孕3个月": 552, "18天前": 4, "六七个月": 139, "40天": 1855, "9天": 2041, "9天前": 55, "四五个小时": 305, "三四个小时": 195, "五六个小时": 256, "一个多月": 1050, "两三个月": 477, "45天": 1416, "30天左右": 211, "6天前": 393, "两三个小时": 126, "近四五个月": 3, "近几个月": 204, "三个多月": 251, "超过3个月": 785, "16天以后": 1, "11天前": 133, "50分钟": 988, "17天": 425, "17天前": 65, "四个多月": 146, "80天左右": 69, "10秒内": 255, "2分钟以内": 22, "十几个小时": 109, "6～7个小时": 25, "6小时后": 2294, "最近2个月": 9, "四个月": 655, "13天后": 68, "32天": 405, "下个月": 79, "下一个月": 111, "50天之后": 13, "5～6个月": 496, "8～12个月": 47, "4～5个月": 491, "3～4个月": 1893, "8～9个月": 156, "9～10个月": 56, "12个月": 3257, "12～18个月": 130, "1～6个月": 535, "二三个月": 122, "7～12个月": 93, "前3个月": 1083, "4～10个月": 46, "6～24个月": 42, "7～8个月": 222, "2个多月": 634, "60分钟": 2142, "1小时左右": 1688, "12天": 2642, "10天以来": 9, "8天前": 266, "19.3个月": 5, "12.1个月": 5, "19.4个月": 5, "15.0个月": 5, "20.9个月": 10, "11.9个月": 5, "13.2个月": 5, "4~6个月": 597, "14.6个月": 9, "8.7个月": 25, "10.7个月": 5, "8.6个月": 5, "7.4个月": 5, "14.7个月": 5, "6.1个月": 5, "11.17个月": 8, "16.17个月": 8, "8~10个月": 43, "33.13个月": 8, "20.87个月": 8, "2~3个月": 1979, "5秒": 2275, "3天左右": 612, "4分钟后": 84, "49天": 196, "1天前": 540, "1~2个月": 1258, "26天": 243, "近4个月": 298, "3~6个月": 2544, "28天后": 374, "3~5个月": 127, "36.67个月": 1, "21.47个月": 14, "20.0个月": 1, "14.8个月": 1, "5~7个月": 13, "7~9个月": 86, "10天内": 1325, "24小时之内": 381, "48小时后": 3886, "20个小时": 4, "不低于8个小时": 4, "36小时后": 179, "35天前": 25, "3天之后": 193, "近一个月": 780, "40天前": 247, "几个月": 3019, "50天": 1099, "50天后": 98, "八九个月": 92, "半个小时": 1039, "10分钟以内": 90, "近十四个月": 33, "一两个月": 187, "近14个月": 33, "25天前": 136, "前两三个月": 33, "12小时左右": 175, "近20个小时": 26, "4个小时": 307, "30分钟以内": 213, "10": 56, "近8个月": 89, "10个小时": 151, "70天": 188, "4个多月": 413, "近5个月": 184, "3小时左右": 207, "2小后": 8, "10天之后": 32, "15天前": 202, "6个小时": 326, "8个小时": 168, "4天左右": 96, "3个小时": 436, "12小时内": 2236, "5个小时": 222, "36小时内": 285, "40分钟后": 803, "2小时内": 2402, "40分钟内": 314, "45天后": 394, "40分钟左右": 423, "1个多小时": 154, "5小时": 2900, "20天内": 266, "40天以上": 41, "14天前": 13, "4天之后": 12, "前两个月": 151, "21天": 8498, "23天前": 23, "50天前": 75, "13天": 896, "近10个月": 229, "六七个小时": 350, "24天左右": 42, "22个月": 84, "一个小时": 627, "七八个月": 483, "62天前": 16, "39天前": 16, "43天前": 16, "42天前": 16, "100天前": 16, "怀孕4个月": 54, "怀孕四个月": 35, "80天": 216, "29天前": 18, "12天前": 128, "70天前": 5, "20天左右": 187, "34天前": 11, "半个多月": 162, "15分钟左右": 1307, "16天": 801, "51天": 126, "近1个小时": 6, "12小时以": 6, "2小时之内": 45, "三四个月": 158, "近四个月": 23, "40天左右": 176, "4天以上": 211, "10年": 8, "38天": 231, "7个": 7, "前4个月": 24, "22天": 1060, "16个月": 238, "18个月": 1482, "36天": 323, "怀孕2个月": 47, "45天前": 14, "10小时以上": 113, "20多个小时": 6, "10小时左右": 105, "20秒钟以上": 5, "10天以上": 382, "12个小时": 172, "29秒后": 1, "20天之后": 16, "30秒后": 394, "45分钟左右": 57, "10秒后": 182, "六个月": 704, "不超过6～8个月": 2, "一3个月": 20, "25天": 1226, "23天": 514, "9小时": 248, "17小时": 112, "近三个月": 132, "11个月": 818, "第2个月": 501, "3~4个小时": 34, "9天后": 222, "19天": 357, "孕3个月": 239, "72天": 63, "31天": 463, "怀孕三个月": 107, "2个小时": 953, "33天": 225, "18天左右": 49, "25分钟": 1408, "138分钟": 6, "18天以后": 17, "超过4个小时": 3, "四十秒": 21, "13个月": 207, "2小时以后": 63, "5个多月": 168, "14小时": 140, "最后一个月": 111, "8小时后": 1506, "5秒钟": 453, "30秒左右": 169, "16天后": 94, "2～4个月": 511, "最近3个月": 163, "360天": 64, "0分钟": 123, "7小时": 525, "\n4个月": 1, "72小时后": 1089, "8分钟左右": 69, "不超过1个月": 109, "超过1个月": 712, "7小时后": 220, "5秒后": 403, "2~5个月": 112, "5~6个月": 212, "4~5个月": 223, "2~6个月": 170, "6~7个月": 118, "6~10个月": 30, "8~12个月": 66, "15秒后": 186, "3~4个月": 485, "9~10个月": 214, "15~18个月": 84, "7~8个月": 111, "这个月": 226, "9~12个月": 120, "12~21个月": 22, "1~3个月": 544, "10~12个月": 68, "11~12个月": 31, "13~17个月": 62, "13~14个月": 31, "15~17个月": 31, "18~23个月": 62, "18~20个月": 31, "21~23个月": 31, "24~30个月": 62, "24个月": 720, "30个月": 212, "12~15个月": 52, "6~8个月": 118, "21~24个月": 62, "16~18个月": 31, "27个月": 23, "4~10个月": 27, "8~11个月": 4, "12~24个月": 159, "6~9个月": 173, "5秒以内": 112, "前几个月": 10, "40日～3个月": 1, "第一个月": 238, "10分钟内": 975, "6分钟内": 203, "第1个月": 692, "70秒": 56, "6小时之内": 775, "20分钟以内": 38, "4～12个月": 127, "4～18个月": 74, "90天": 1949, "1小时以内": 142, "2分钟以上": 286, "3秒": 1532, "40": 8, "80分钟": 129, "10小时内": 114, "10秒钟内": 49, "29分钟后": 44, "4分钟内": 105, "1分钟内": 418, "2秒以上": 35, "1600毫秒": 5, "48小时以上": 252, "14天后": 1563, "2～5个月": 180, "4.5个月": 76, "1.5个月": 188, "6小时左右": 279, "九个月": 261, "6～8个月": 196, "150分钟以上": 40, "二个月": 236, "3～5个月": 431, "1～4个月": 57, "1～23个月": 4, "1～17个月": 3, "25天后": 142, "20天后": 1381, "53天": 61, "一二个月": 15, "6至12个月": 1, "47天": 199, "10秒": 1825, "25分钟左右": 99, "20分钟以上": 176, "36小时以后": 106, "2分钟左右": 438, "90分钟": 1029, "1秒": 346, "2秒左右": 82, "2个多小时": 82, "3小时前": 116, "前半个月": 39, "5天之内": 35, "七个月": 199, "5天之后": 4, "4~5个小时": 14, "6~7小时": 1, "7小时左右": 120, "第二个月": 212, "3个天": 2, "366天": 19, "十二个月": 525, "365天": 170, "18小时": 440, "前六个月": 1, "六个": 1, "3夜": 32, "2小时以上": 1734, "240分钟": 59, "360分钟": 17, "两个小时": 512, "72小时内": 1136, "第24个月": 27, "三个小时": 69, "五六个月": 190, "第七个月": 14, "3分钟左右": 492, "16个小时": 33, "76天": 35, "60天后": 226, "250天": 6, "491天": 3, "前几个小时": 14, "72秒": 16, "每两个月": 100, "每三个月": 61, "五、六个月": 2, "7天以内": 271, "超过两个月": 79, "122.25个月": 16, "123.21个月": 16, "个把钟头": 6, "18天后": 179, "二十个小时": 1, "20小时": 497, "近一个小时": 2, "近十个月": 18, "二十几个小时": 2, "8个多月": 117, "6个多月": 197, "两个多小时": 73, "一个多小时": 197, "280天之后": 1, "3": 79, "5秒钟内": 66, "1秒以上": 14, "4天内": 817, "20秒内": 59, "1分钟以上": 460, "56天": 207, "超过2个月": 414, "零6个月": 18, "6分钟后": 108, "零9个月": 45, "10天以后": 63, "74天": 96, "50秒": 99, "8小时以上": 324, "20分钟内": 572, "分钟以上": 1, "4小时左右": 548, "上个月": 79, "2~3个小时": 186, "10秒钟": 405, "30分钟以后": 10, "2小时前": 202, "39分钟": 7, "35分钟之内": 11, "15天内": 421, "28分钟": 44, "17天以后": 27, "23个月": 43, "3分钟以上": 122, "十五个月": 11, "80分钟后": 24, "怀孕7个月": 57, "怀孕2个多月": 1, "27天": 369, "17个月": 141, "孕2个月": 36, "近一个多月": 4, "最近1个月": 100, "5次以上": 1, "4分钟左右": 10, "最近一个月": 142, "10秒钟左右": 3, "7个小时": 52, "20小时左右": 54, "3小时以上": 476, "60分钟内": 838, "141天左右": 1, "18~22个月": 1, "16小时后": 185, "235天左右": 1, "150分钟内": 108, "2周~6个月": 1, "150分钟": 196, "120分钟内": 59, "90分钟内": 118, "不超过3个月": 101, "6~12个月": 1250, "2天以后": 87, "13天前": 17, "5天以后": 65, "3~9个月": 2, "15个小时": 1, "八个月": 230, "120小时": 153, "60天": 1305, "29个月": 176, "28个月": 59, "14天之内": 13, "14天以上": 14, "1~6个月": 429, "5天左右": 490, "60秒内": 128, "0小时": 118, "12天后": 237, "30秒内": 276, "10天以内": 146, "近6个月": 299, "40天后": 225, "1小时前": 318, "5小时左右": 160, "5个多小时": 35, "零8个月": 34, "5~6个小时": 8, "80天前": 1, "52天": 113, "90分钟后": 110, "3分多钟": 1, "7": 15, "孕6个月": 57, "10秒左右": 20, "十个月": 349, "260天前": 16, "294天": 16, "36小时之内": 18, "20小时以上": 42, "20～22个小时": 2, "28天之前": 4, "28天内": 41, "48秒": 35, "9个多月": 36, "488小时": 1, "80小时内": 1, "300小时左右": 1, "二个小时": 1, "十多个月": 1, "16天至6个月": 34, "1秒钟": 188, "2~8个月": 32, "8小时左右": 251, "4小时以上": 668, "2秒钟后": 17, "4分钟": 1006, "三至六个月": 11, "58个月": 34, "15分钟以上": 344, "13小时": 61, "30天以上": 43, "14天左右": 506, "45天以上": 3, "55天以上": 3, "65天以上": 9, "5小时内": 291, "168小时": 33, "41小时内": 4, "16小时": 426, "60天以内": 58, "109天": 10, "21天之内": 9, "第7个月": 22, "前6个月": 75, "27天内": 2, "2～8个月": 2, "42天内": 42, "56天内": 5, "35分钟": 121, "5天以内": 182, "八三个月": 19, "36个月": 229, "5～7个月": 100, "12～15个月": 30, "9～12个月": 52, "零七个月": 30, "6天内": 415, "2小": 47, "96小时内": 60, "6天之内": 136, "36小时以内": 102, "5分钟以内": 90, "1天左右": 47, "4～7个月": 50, "280天": 87, "不超过2个月": 60, "96小时以上": 218, "10日": 90, "每2个月": 115, "12分钟": 189, "3秒以上": 180, "10日内": 2, "每2个小时": 41, "每1个小时": 9, "近7个月": 54, "6.5个月": 253, "7个多月": 62, "45分钟后": 159, "30分钟之内": 35, "15天左右": 417, "19小时后": 4, "4小时以内": 90, "15分钟以前": 34, "9小时后": 96, "7分钟后": 167, "50分钟后": 123, "68小时": 20, "76分钟": 27, "8天后": 808, "8分钟后": 247, "18小时后": 88, "1小时之内": 60, "5小时后": 603, "29天后": 1, "11天后": 45, "3周": 1, "10分钟前": 4, "4小时前": 24, "7分钟": 586, "几个小时": 99, "1秒以后": 6, "6秒钟": 12, "42秒后": 8, "17小时后": 29, "第6个月": 148, "第4个月": 129, "10多个小时": 1, "1秒之内": 1, "8秒": 48, "2秒钟": 37, "6000秒内": 1, "7天以后": 50, "五个小时": 11, "一两个小时": 105, "5秒左右": 36, "3～4个小时": 87, "5～6个小时": 81, "1个周": 7, "1到2个月": 2, "2个周": 4, "超过一个月": 82, "23天左右": 1, "1个小时": 1176, "1天之后": 8, "30秒钟左右": 10, "3天以来": 3, "96小时后": 163, "21天后": 1152, "21天内": 129, "30小时": 124, "96小时": 158, "20个月": 137, "23天内": 7, "2～3个小时": 135, "22小时": 35, "5": 10, "75": 13, "200天": 45, "2～7个月": 48, "9～30个月": 20, "90天后": 108, "16小时内": 42, "75分钟": 129, "41天": 139, "7小时内": 33, "4小": 24, "10个": 5, "48小时时": 5, "15分钟之内": 60, "255天后": 10, "255天之后": 5, "3天6例": 14, "36小时": 686, "45天以内": 9, "23天后": 32, "8天内": 154, "1星期后": 1, "78天": 17, "15小时左右": 2, "19天后": 5, "210天": 4, "46天": 313, "70天后": 60, "35天后": 88, "80天后": 53, "零一个月": 1, "240天": 18, "14分钟": 9, "120天": 151, "160天": 15, "9～11个月": 1, "4": 93, "2.76个月": 1, "0.28个月": 1, "2.92个月": 1, "0.18个月": 1, "3.04个月": 1, "0.12个月": 1, "0.8个月": 1, "0.25个月": 1, "十五天以上": 32, "5天多": 65, "7天多": 65, "7~12个月": 180, "6周~6个月": 4, "0.5～1个小时": 15, "15天以下": 40, "15天以上": 146, "60秒": 575, "每6个月": 422, "每12个月": 39, "1～21个月": 9, "6～23个月": 10, "七八个小时": 42, "8天以后": 6, "57天": 56, "300天以上": 3, "2小时以内": 129, "3~12个月": 183, "三至四个月": 2, "五至六个月": 1, "后半个月": 171, "56小时": 1, "8天左右": 89, "80天以上": 2, "120天左右": 16, "55天后": 24, "20小时后": 196, "168小时后": 31, "1～2个小时": 221, "30天内": 217, "20天～10个月": 26, "5～2个月": 11, "1.5～8.0个月": 11, "115天": 6, "3～9个月": 35, "25天内": 42, "7秒": 9, "18秒": 75, "24天": 402, "55天": 60, "孕5个月": 56, "每一个月": 78, "19个月": 17, "前一个月": 95, "54天": 54, "24分钟内": 37, "24分钟": 97, "90秒": 112, "7天之内": 232, "72小时以内": 800, "63个月": 19, "5.8个月": 19, "31.4个月": 64, "18.0个月": 64, "39天": 177, "48小": 56, "6～13个月": 5, "1分钟许": 8, "2~2.5个月": 1, "6～9个月": 145, "6周～6个月": 5, "27小时": 67, "117秒": 4, "100天": 442, "140天": 24, "15小时以上": 1, "八九个小时": 86, "3天之内": 80, "2.5个月": 164, "3天以后": 119, "3晚": 6, "38天后": 9, "6天以内": 10, "24～48个小时": 10, "9天内": 179, "24小时左右": 597, "146天": 31, "578天": 31, "5小时以上": 305, "8分钟内": 36, "0.5～6个小时": 47, "32小时": 111, "1～12个月": 55, "6～15个月": 70, "120小时后": 172, "16小时时": 12, "24小时以后": 60, "17天内": 13, "12～36个月": 28, "64小时": 9, "20天以内": 45, "90天以内": 33, "120天以内": 27, "95天": 95, "10～20个月": 66, "60天以上": 30, "90天以上": 119, "8小时以后": 14, "36小时以上": 26, "3～24个月": 43, "58天": 120, "6天以上": 124, "12～16个月": 19, "19～24个月": 19, "1.7个月": 19, "48分钟后": 18, "124小时后": 18, "60分钟左右": 61, "5天至2个月": 12, "24": 12, "25小时": 57, "5～23个月": 9, "77": 14, "5～11个月": 39, "22天内": 38, "12天内": 88, "24小时以内": 516, "11天左右": 42, "100天后": 124, "1天～27个月": 21, "18天～3个月": 7, "190天": 15, "3小时时": 9, "68天": 50, "62天": 67, "3小时之内": 30, "72小时以上": 39, "5天～3个月": 12, "60秒后": 115, "11小时后": 16, "前三个月": 280, "115分钟": 2, "5小时前": 31, "2～9个月": 49, "10秒之内": 18, "60秒之内": 18, "8秒左右": 12, "5秒钟后": 32, "好几个月": 27, "3秒钟内": 1, "5秒之内": 177, "5秒以上": 114, "十二个小时": 33, "二十四个小时": 22, "下两个月": 13, "六个多小时": 1, "6秒": 361, "每2小时": 21, "1周内": 37, "1~8个月": 6, "2~4个月": 229, "4~12个月": 269, "2~10个月": 5, "50秒内": 40, "20秒后": 116, "15小时内": 18, "5~30个月": 10, "12~30个月": 10, "1.5~24个月": 10, "6~24个月": 32, "3-6个月": 27, "2到3个钟点": 5, "1.5~2个月": 5, "2~9个月": 3, "5~15个月": 6, "47小时": 46, "2天右": 59, "5天左": 15, "14天以后": 374, "75天后": 3, "最近几个月": 3, "88天": 11, "112天": 11, "79天": 28, "6～8个小时": 216, "少于6个月": 46, "4~6个小时": 15, "3-5个月": 2, "300": 5, "90分钟左右": 6, "15秒以上": 57, "48小时左右": 74, "20秒以内": 14, "10秒以内": 27, "15秒内": 76, "21天前": 6, "\n2个月": 1, "20小时内": 47, "70天以上": 1, "15小时": 103, "62天以上": 1, "1小时以后": 40, "10～20个小时": 1, "3～5个小时": 1, "24天前": 25, "19天前": 1, "38天前": 16, "16天前": 4, "27天前": 44, "20天～1个月": 2, "7天～1个月": 2, "37天": 330, "34天": 252, "孕1个月": 2, "7～8个小时": 11, "44天": 162, "六、七个": 1, "孕4个月": 32, "50天到70天": 1, "86天": 3, "近9个月": 17, "孕8个月": 4, "15天～3个月": 6, "2～4个小时": 142, "21天～2个月": 1, "8～9个小时": 8, "60天左右": 60, "77天": 17, "64天": 20, "20天以上": 178, "21个月": 197, "20天至2个月": 2, "63天": 36, "71天": 34, "12": 1, "大半个月": 1, "350天": 6, "6分钟以上": 87, "40分钟前": 15, "6小时前": 135, "12小时之内": 27, "18小时内": 42, "3秒以内": 40, "过去3个月": 40, "不少于2个月": 16, "不少于1个月": 121, "12小时以内": 81, "48小时以内": 291, "57分钟": 33, "30秒以上": 33, "1小时40分钟后": 18, "9秒": 19, "46天左右": 14, "28天左右": 108, "六十个月": 1, "9个小时": 16, "1440分钟": 21, "四个小时": 29, "500天": 1, "32个小时": 1, "50个小时": 1, "26秒": 1, "354天": 28, "355天": 120, "12～14个月": 10, "二、三个月": 191, "　3个月": 11, "180天后": 16, "不少于3个月": 205, "1小": 14, "200分钟": 4, "50分钟以上": 40, "孕三个月": 24, "10天之内": 85, "3秒钟之内": 47, "3秒钟": 87, "怀孕6个月": 51, "61天": 46, "31天左右": 18, "12个天": 20, "少于3个月": 44, "六个小时": 60, "26天后": 29, "28小时后": 21, "17秒": 7, "65秒": 7, "35秒": 8, "19秒": 7, "4秒": 241, "2周~1个月": 7, "1～1.5个月": 151, "1.5～6个月": 93, "3小时以内": 96, "1.6个月": 49, "不超过12个月": 22, "14天以内": 20, "6周～3个月": 104, "1天以内": 11, "1天　　": 11, "4～8个月": 7, "八个多月": 4, "第三个月": 193, "40分钟以上": 204, "六、七个小时": 15, "15分钟以后": 9, "十几个月": 5, "六到八个月": 5, "10～12个月": 10, "每5个小时": 1, "40秒": 169, "70分钟": 74, "140分钟": 48, "480分钟": 9, "240分钟后": 4, "180分钟": 219, "1天24小时": 16, "30分钟前": 31, "23分钟": 4, "9天以上": 26, "40分钟到1个小时": 10, "七八九个月": 55, "三五个月": 219, "2～19个月": 10, "53.4个月": 30, "7.5个月": 17, "10个多月": 59, "9.7个月": 20, "2880天": 45, "11小时": 87, "413天": 15, "413天以后": 15, "28小时": 43, "420天": 16, "十个多月": 35, "前14天左右": 8, "少于3~6个月": 2, "1~4个月": 53, "45秒": 131, "第0个月": 30, "120秒后": 9, "4小时后内": 4, "60小时": 22, "32分钟": 35, "\n1个月": 3, "\n4天前": 1, "66毫秒内": 46, "30秒钟": 232, "2天以内": 12, "7小时以上": 6, "1～24个月": 10, "18～24个月": 41, "73例": 4, "95.": 2, "1秒钟内": 43, "2秒后": 26, "3秒内": 101, "8～15个月": 12, "30分钟～1小时": 89, "每隔1个月": 4, "6天以后": 7, "1～15个月": 2, "210分钟": 2, "9分钟": 134, "3钟左右": 1, "12～24个月": 6, "6天左右": 109, "1548小时": 3, "800小时": 3, "2250小时": 3, "600小时": 3, "180天": 531, "45天内": 127, "60天内": 152, "100小时": 3, "1000小时": 14, "500小时": 26, "300个小时": 1, "200小时": 1, "15分钟。": 11, "20分钟。": 3, "300小时": 2, "21天左右": 138, "2个钟头": 5, "6个钟头": 5, "180分钟以上": 8, "3小时40分钟": 17, "18~24个月": 108, "12~32个月": 1, "50例": 23, "2.6个月": 85, "42天以后": 23, "135天": 26, "2.67个月": 38, "94天": 33, "3～10个月": 69, "1周～3个月": 11, "23小时": 231, "41小时": 26, "70分钟后": 38, "2.47个月": 21, "30分钟～2小时": 31, "5天以上": 177, "21分钟": 20, "175例": 40, "35天内": 23, "4～9个月": 21, "2周～2个月": 44, "2周～1个月": 282, "5天天后": 10, "3～8个月": 30, "1天以上": 72, "10天～2个月": 17, "25天左右": 52, "上半个月": 18, "下半个月": 3, "46小时": 18, "76小时": 20, "21小时": 69, "89分钟左右": 13, "1天～2个月": 18, "24.83个月": 8, "40天内": 21, "3～18个月": 163, "7～10个月": 17, "20天以后": 39, "7天～2个月": 6, "132天": 1, "304天": 6, "10日～1个月": 3, "15天以内": 43, "3～23个月": 2, "83天": 4, "26小时": 68, "84天": 8, "250分钟": 2, "48小时以后": 12, "四五六七四个月": 13, "91天": 2, "66天": 15, "37天左右": 14, "63天前": 1, "38": 1, "30天~4个月": 2, "15天之后": 84, "40秒后": 42, "1天之内": 65, "三两个月": 31, "2": 136, "前一个小时": 19, "0分钟后": 25, "5秒内": 129, "孕五六个月": 10, "孕7个月": 26, "48天左右": 3, "30天～3个月": 5, "65天": 65, "32天左右": 8, "超过4个月": 30, "82天": 38, "30～5个月": 3, "12天左右": 39, "89天": 3, "孕两个月": 16, "九个多月": 6, "怀孕九个月": 2, "孕九个月": 1, "近九个月": 1, "近五个月": 3, "五三个月": 31, "8小时以内": 86, "4—6个月": 10, "1—2个月": 4, "近五六个月": 2, "零四个月": 2, "六个多月": 1, "两、三个月": 3, "34天后": 6, "121天": 5, "15天至1个月": 1, "4～16个月": 1, "住院1个月": 8, "50分钟左右": 81, "过去6个月": 32, "16天以上": 89, "17天后": 40, "5～12个月": 57, "5～36个月": 38, "五个多月": 40, "4.8个月": 46, "9～32个月": 46, "57个月": 46, "74个月": 46, "2.8个月": 109, "10.5个月": 98, "12.2个月": 93, "10～11个月": 93, "4.9个月": 174, "3.0个月": 93, "1.8个月": 97, "4天　": 59, "292天": 104, "236天": 104, "近12个月": 97, "198天": 138, "5.5个月": 148, "8.3个月": 67, "5.3个月": 103, "15.3个月": 67, "12.3个月": 67, "超过三个月": 260, "1～2.5个月": 51, "133天": 51, "30小时内": 68, "8～10个月": 73, "2天一": 25, "59天": 107, "不少于18个月": 32, "73个月": 32, "3至6个月": 48, "15分钟左": 33, "16.0个月": 66, "7.6个月": 66, "每隔3个月": 96, "10～13个月": 21, "3～11个月": 2, "18天以上": 14, "73天": 20, "100天内": 87, "超过18个月": 2, "9秒后": 3, "16小时以上": 12, "零两个月": 2, "24小": 9, "4～5个小时": 40, "7～9个月": 9, "4～72个小时": 16, "15分钟～3个小时": 16, "1秒内": 49, "1分钟之内": 76, "1秒以内": 6, "180秒": 19, "4小时15分钟": 6, "2小时10分钟后": 14, "第四个月": 32, "二、三个小时": 2, "孕七个月": 2, "2小时10分": 1, "孕二个月": 1, "一、二个月": 1, "怀孕前三个月": 16, "3秒后": 11, "10天左右后": 4, "30小时以上": 5, "11天～1个月": 1, "270天": 10, "第14个月": 1, "124天": 4, "30天以内": 59, "30天至1.5个月": 1, "2～16个月": 1, "前二个月": 2, "20分钟前": 24, "8月份一个月": 15, "零八个月": 12, "3天3夜": 30, "上半个钟头": 8, "30日后": 14, "20天间": 1, "好几个钟头": 1, "24个小时": 23, "两个多钟头": 1, "下两个小时": 1, "一1个月": 4, "30秒钟内": 1, "9～10个小时": 1, "2个余月": 4, "35分钟后": 27, "七、八个小时": 13, "上几个月": 49, "162天": 24, "最后几个月": 9, "三、四个小时": 15, "半个多小时": 19, "1小时以前": 4, "17个小时": 4, "每两三个月": 6, "两到三个月": 2, "十一个月": 17, "200天后": 1, "4小时以后": 52, "不超过21个小时": 1, "前10个月": 1, "8小时前": 23, "75天": 161, "26.7个月": 5, "13~39个月": 5, "14~139个月": 5, "56个月": 100, "1~55个月": 1, "4~19.5个月": 1, "2个": 7, "40天～3个月": 7, "4～6个小时": 2, "105天": 26, "3天上午": 3, "2天多": 6, "每1个月": 28, "15～24个月": 23, "24～42个月": 23, "320天内": 23, "近2月": 1, "10小时前": 5, "14天以下": 24, "30毫秒以内": 21, "32小时内": 33, "1秒左右": 60, "250小时": 21, "2周后": 1, "每个小时": 49, "数个月": 3, "3～15个月": 5, "过去一个月": 5, "100分钟": 47, "10分钟/小时": 4, "20分钟/小时": 2, "这一个月": 203, "怀孕两个月": 8, "十个小时": 16, "第五个月": 11, "第六个月": 3, "第八个月": 3, "第九个月": 10, "第十个月": 2, "怀孕七个月": 22, "怀孕几个月": 5, "上8个小时": 1, "好几个小时": 37, "上一个月": 3, "48分钟": 2, "上几个小时": 8, "三到五个月": 2, "2~4个小时": 4, "某一个月": 1, "少于1个月": 5, "67天后": 1, "五七个月": 175, "七、八个月": 149, "3天多": 41, "近1天左右": 1, "310天": 2, "177天": 2, "183天": 93, "182天": 3, "122天": 2, "5小时左": 1, "26天前": 1, "9小时以上": 31, "85天": 2, "最近两个月": 11, "这几个月": 24, "29天左右": 12, "206天": 12, "32个月": 27, "68秒": 1, "54秒": 33, "76天前": 2, "上三个月": 1, "每隔两个小时": 1, "一个星期": 1, "4天以前": 28, "9～15个月": 27, "8小时之内": 43, "少于18个月": 16, "242天": 8, "超过四个月": 24, "48小时之内": 313, "近3个多月": 2, "每隔一个月": 51, "2天左右": 88, "3分钟之内": 1, "20天以来": 1, "26个月": 85, "68个月": 41, "6.9个月": 35, "51个月": 25, "59个月": 4, "166天": 12, "40个月": 48, "11.8个月": 5, "13.0个月": 5, "24小时。": 5, "10天间": 79, "3~10个月": 62, "153个月": 4, "172个月": 4, "31个月": 51, "37个月": 8, "39个月": 12, "58天后": 13, "72个月": 13, "过去三个月": 13, "4天以内": 80, "h小时内": 23, "6.8个月": 76, "8天以内": 10, "4.2个月": 26, "50个月": 15, "43个月": 27, "6~11个月": 6, "150天": 23, "118个月": 4, "82个月": 4, "130个月": 4, "34个月": 31, "12~28个月": 8, "33~50个月": 8, "60个月": 10, "11~18个月": 8, "13分钟": 14, "61个月": 39, "超过12个月": 59, "22天后": 52, "超过5个月": 5, "5.2个月": 5, "91个月": 11, "8.8个月": 11, "15.5个月": 11, "140个月": 5, "1小时左": 3, "23小时内": 33, "第12个月": 81, "3.6个月": 86, "7.2个月": 5, "近120个月": 5, "53个月": 17, "38个月": 36, "300天": 8, "6~18个月": 69, "32~46个月": 8, "1~15个月": 8, "2~38个月": 8, "33~101个月": 8, "42个月": 8, "1.5~30个月": 8, "13~120个月": 12, "26~40个月": 12, "102个月": 2, "5~37个月": 5, "不超过4个月": 5, "33个月": 6, "55个月": 3, "92个月": 3, "25个月": 92, "46个月": 33, "48个月": 3, "2.9个月": 3, "6.7个月": 23, "32~50个月": 9, "45~75个月": 9, "11~19个月": 9, "11~22个月": 9, "3~11个月": 33, "36个多月": 4, "40小时": 295, "12.7个月": 1, "518天": 1, "49个月": 1, "3天一": 1, "146小时": 1, "63小时": 1, "怀孕六个月": 4, "11～17个月": 1, "超过三四个小时": 1, "\n两个月": 1, "1秒钟左右": 18, "第8个月": 7, "不超过6个月": 132, "1.2小时": 6, "6天之后": 13, "14秒": 5, "29秒": 16, "42秒": 15, "90秒钟": 5, "120秒": 17, "30天之内": 28, "1～8个月": 8, "怀孕两个多月": 1, "怀孕5个月": 26, "10天至6个月": 1, "90天内": 41, "12天以后": 132, "14 天": 10, "7~10个月": 17, "1.5~6个月": 17, "6个": 5, "12小时前": 47, "7小时前": 1, "怀孕六七个月": 2, "怀孕八个月": 10, "下12个月": 1, "3小时候": 1, "5小时候": 1, "怀孕四个多月": 1, "1小时候": 24, "35小时": 67, "近3个多小时": 1, "1天多前": 1, "不小于6个月": 1, "不少于6个月": 8, "167天以来": 3, "50日后": 3, "67天": 48, "28天前": 13, "3天~3.5个月": 11, "不超过24个小时": 1, "1~2个小时": 52, "4个多小时": 1, "近3个小时": 2, "不超过6个小时": 1, "14天右": 1, "10秒以上": 35, "2.3个月": 91, "2.35个月": 14, "8个多小时": 1, "两个": 3, "前三个多月": 2, "前四五个月": 12, "七个小时": 1, "15秒钟以上": 12, "60天以后": 6, "63天后": 10, "6～10个月": 67, "36天后": 28, "30个小时": 3, "3个多小时": 16, "1～7个月": 77, "7.3个月": 7, "4秒内": 23, "16分钟": 92, "16～48个月": 6, "3.2个月": 6, "4.7个月": 8, "3～69个月": 8, "6～38个月": 8, "10.3个月": 8, "10.2个月": 18, "1周～2个月": 24, "12个钟点": 9, "不少于3～6个月": 9, "每4个月": 69, "几个钟头": 11, "9天以来": 1, "四五个钟头": 2, "15天以后": 20, "小时之内": 3, "11天内": 19, "8.5个月": 26, "65": 4, "9.5个月": 39, "75天左右": 16, "少于三个月": 9, "14.5个月": 4, "14个多月": 1, "57天后": 2, "130天左右": 2, "130天": 2, "零4个月": 40, "48天后": 10, "10个多小时": 32, "100天以上": 14, "42小时": 58, "49小时": 7, "近11个小时": 17, "每两个小时": 12, "上四五个小时": 4, "18.7个月": 23, "19.7个月": 19, "6～27个月": 38, "78个月": 20, "5.75个月": 20, "11.1个月": 20, "16～20个月": 6, "17分钟": 12, "29分钟": 31, "18.2个月": 6, "15.8个月": 17, "零1个月": 26, "7.0个月": 11, "6.07个月": 11, "4.17个月": 11, "17.2个月": 11, "12.4个月": 11, "43.67个月": 2, "47.15个月": 2, "1075天": 7, "1～5个月": 25, "13.78个月": 9, "8.84个月": 9, "20.8个月": 5, "每隔5个月": 5, "52秒": 25, "105天左右": 19, "两至三个月": 1, "1小时多": 16, "7~8个小时": 58, "5秒钟左右": 1, "87天": 89, "过去12个月": 121, "前8个月": 22, "5～8个月": 11, "11～12个月": 11, "13～18个月": 11, "19～23个月": 11, "5.4个月": 15, "3.3个月": 15, "8.03个月": 2, "1.69个月": 4, "8~40个月": 4, "7.97个月": 4, "9.2个月": 147, "5.87个月": 8, "一、两个月": 1, "1分钟以内": 86, "30天至3个月": 3, "30天至2个月": 8, "3～5个多月": 4, "69天": 11, "37天～6个月": 5, "7天～3个月": 5, "10多天": 7, "48天之后": 4, "97天": 7, "2天之后": 3, "13": 1, "每隔三个月": 1, "五个\n": 2, "三、五个月": 2, "六、七个月": 7, "2周～6个月": 65, "7天之后": 74, "104天": 43, "这个天": 44, "46秒": 79, "1小时许": 21, "720天": 12, "80秒": 12, "635天": 12, "72小时前": 24, "96小时前": 12, "8~9个小时": 38, "1~3个小时": 20, "440分钟": 28, "43分钟": 120, "30分": 68, "12小": 15, "70分钟左右": 4, "2～3个周": 7, "196天": 2, "近二个月": 1, "5～7个小时": 9, "44小时": 15, "零3个月": 39, "36500天": 39, "一二个钟头": 25, "2天之间": 4, "121小时": 20, "26分钟后": 7, "30分钟　": 1, "15": 4, "30钟": 3, "35天以后": 17, "零2个月": 35, "零7个月": 27, "零5个月": 45, "零10个月": 33, "零11个月": 24, "一个天": 1, "6～7个小": 1, "6～66个月": 30, "5分钟以后": 57, "3～20个月": 7, "第1个小时": 9, "两个到四个小时": 6, "20分钟以后": 18, "170分钟": 16, "76秒": 1, "75天内": 1, "近22个月": 1, "38天内": 1, "1～3个小时": 21, "6个多小时": 36, "二三个小时": 108, "4个": 36, "10～25个月": 27, "20": 10, "24小时前": 13, "10秒钟后": 83, "26～38个月": 3, "怀孕8个月": 25, "70天左右": 11, "118天": 15, "18分钟": 118, "3秒左右": 3, "168天": 5, "106天": 5, "57天前": 1, "8": 28, "720分钟": 33, "每四个小时": 19, "83小时": 15, "72小时之内": 49, "29小时": 14, "9小时候": 14, "16天左右": 14, "9天左右": 56, "17天左右": 7, "145分钟": 6, "40小时后": 53, "怀孕9个月": 21, "4天晚上": 6, "5分钟前": 1, "7秒钟后": 8, "6秒后": 8, "14小时左右": 28, "33小时": 11, "前9个月": 12, "18~32个月": 11, "1.0小时内": 28, "54个月": 3, "5.5~14.0个月": 1, "37小时": 1, "50分钟内": 32, "最多三个月": 20, "低于3个月": 68, "60小时内": 68, "18小时以上": 23, "1～10个月": 56, "96天": 21, "0.5个月": 13, "34小时": 386, "1~12个月": 26, "10日后": 12, "30秒~1分钟": 7, "7个小时以上": 8, "6~7个小时": 5, "1~2分钟": 5, "10余个小时": 7, "超过两个小时": 12, "20小时前": 36, "前两个小时": 2, "上三四个小时": 7, "6~30个月": 5, "10~14个小时": 5, "5~3": 5, "6小后": 1, "3周~8个月": 13, "1~20个月": 5, "24~36个小时": 6, "4日后": 15, "0.5~1个小时": 5, "每隔2个月": 6, "0.5个小时": 52, "19": 1, "30小时后": 42, "28天以内": 5, "近三四个月": 4, "1天以后": 6, "10天至1个月": 22, "4分钟以上": 8, "103天": 26, "4秒以上": 68, "58天内": 43, "1500小时": 2, "近5个小时": 10, "0天": 109, "65秒钟": 32, "45秒钟": 128, "10分钟以前": 32, "十个天": 56, "10个天": 31, "40多天": 101, "近两个多月": 67, "一": 67, "28天多": 4, "半个": 7, "21天以上": 39, "22天左右": 5, "40天至3个月": 18, "49天前": 1, "八、九三个月": 4, "108天": 2, "二至三个月": 3, "120秒内": 4, "50天外": 2, "6小": 3, "26天以后": 4, "180分钟后": 2, "75秒": 19, "24天后": 57, "250毫秒": 3, "5天上午": 2, "18～20个月": 4, "340天左右": 4, "115秒": 4, "上1个小时": 11, "10天后以上": 1, "200天以上": 7, "30天之后": 26, "18～22个月": 5, "360天后": 4, "4小时时": 36, "1毫秒": 3, "1周后": 3, "21～26个月": 1, "72秒后": 1, "72秒以下": 1, "30天左右后": 3, "42天左右": 3, "10毫秒": 1, "24天内": 1, "1.5～3个月": 1, "128小时": 1, "50天以上": 4, "45分钟以上": 32, "不超过两个月": 46, "70小时": 43, "330小时": 43, "19小时": 47, "32小时左右": 68, "4周～36个月": 55, "最后3个月": 26, "4~8个月": 1, "1分左右": 23, "8小时候": 30, "15秒左右": 12, "17~18个月": 7, "240天以上": 1, "1天~1个月": 2, "二十七个月": 2, "152天": 20, "44分钟": 5, "400年": 5, "11两个月": 5, "28秒": 6, "29天多": 5, "一个小月": 5, "47个月": 5, "383天": 10, "384天": 10, "354天左右": 5, "384天左右": 5, "36秒": 2, "26秒钟": 2, "十九个月": 1, "15小时以内": 2, "1天之中": 11, "下2个月": 1, "57天以上": 12, "5分钟之内": 55, "7天以下": 14, "28天以上": 14, "3天以下": 18, "120小时内": 49, "住院3个月": 44, "2～12个月": 2, "10.8个月": 4, "每四个月": 4, "4小时之内": 1, "25": 21, "近七个月": 4, "零九个月": 2, "1至2个月": 8, "7分钟内": 38, "12分钟后": 11, "280天左右": 79, "26分钟": 34, "56天后": 11, "55分钟": 25, "3~8个月": 33, "6~36个月": 7, "2分钟30秒": 107, "12例": 28, "1个": 33, "1～55个月": 14, "3000小时": 9, "28小时内": 17, "11秒": 15, "60分钟以内": 21, "42小时后": 2, "前10小时内": 1, "10分钟以后": 87, "112小时": 34, "8天以上": 4, "1小时45分钟": 1, "3小时50分钟": 1, "26小时后": 1, "32小时后": 2, "3小": 17, "61秒": 1, "78秒": 1, "1个时": 6, "60小时后": 11, "11天之前": 10, "161天": 9, "4天之内": 1, "5天~3个月": 14, "3天2夜": 2, "一16个月": 2, "42天后": 4, "32天后": 8, "15天之内": 29, "22分钟后": 43, "80分钟以上": 20, "10天1": 8, "20秒钟": 21, "90天左右": 10, "20分钟之内": 58, "孕9个月": 2, "30": 1, "42小时内": 19, "28分钟多": 15, "28分钟左右": 15, "1.5个小时": 135, "超过2个小时": 9, "27天后": 2, "十五天左右": 6, "九天左右": 6, "前二个小时": 9, "7天至两个月": 1, "5~7个小时": 35, "300分钟/周": 16, "七到八个小时": 5, "过去几个月": 2, "23小时后": 24, "4～46个月": 83, "173天": 56, "3.67个月": 53, "4.91个月": 53, "1.24个月": 53, "41.293个月": 53, "25.2个月": 53, "18.5个月": 53, "37分钟": 49, "13.44个月": 50, "7.4～19个月": 50, "16至20个月": 29, "4.8～24.4个月": 22, "3.4～15.2个月": 22, "21天之间": 19, "40天～6个月": 7, "怀孕五个月": 13, "四、五个月": 15, "35天左右": 53, "过去11个月": 7, "25天以上": 5, "47天后": 14, "13天左右": 15, "38小时后": 25, "36小时左右": 65, "300天左右": 15, "150天以上": 15, "3个时": 44, "近10个小时": 1, "\n3个月": 3, "超过9个月": 46, "15小时前": 7, "近三个多月": 7, "三个来月": 5, "六十个天": 1, "十四个月": 41, "三十六个月": 30, "116天": 21, "117天": 6, "60秒以内": 20, "1个星期至1个月": 27, "2小时至8小时": 14, "385天": 4, "14天之后": 3, "1天,后": 4, "\n几个月": 2, "2小时30分钟": 3, "40秒左右": 4, "2小时30分": 4, "10～131个月": 9, "98分钟": 18, "62分钟": 18, "超过8个月": 2, "8秒钟": 3, "14小时后": 204, "22分钟": 15, "27分钟": 46, "160分钟": 33, "1～18个月": 30, "1小时以": 2, "49秒": 1, "第十四个月": 9, "超过3～4个月": 5, "93分钟": 5, "102分钟": 5, "45天左右": 11, "近六个月": 1, "二至四个月": 1, "一至两个月": 1, "一至三个月": 2, "100": 6, "一到三个月": 1, "近二十个小时": 1, "40秒钟后": 14, "五六七三个月": 12, "3～7个月": 21, "4.1个月": 36, "十六个月": 7, "24天之内": 1, "29小时之内": 1, "不超过18个月": 100, "10分钟分钟": 35, "8天晚上": 15, "个把小时": 1, "最近5个月": 4, "一二个小时": 19, "十七个月": 2, "每3个小时": 1, "4个小时时": 1, "20秒左右": 4, "1～9个月": 3, "6～120个月": 9, "2分钟之内": 12, "4秒后": 19, "365天5小时": 10, "50天以后": 6, "217天": 23, "16小时左右": 7, "12~18个月": 34, "8~9个月": 66, "1362小时左右": 21, "320天": 15, "1362小时": 15, "2.5个小时": 6, "2天2夜": 21, "1天1夜": 21, "9天之后": 38, "上半个小时": 2, "9分钟内": 13, "4小时间": 13, "5分钟以前": 8, "120分钟以上": 20, "5分钟外": 5, "4小时8分钟": 1, "15小时后": 1, "6分钟左右": 23, "2小时血": 1, "50小时": 12, "20秒钟后": 1, "50秒左右": 1, "8～12个小时": 1, "10钟": 2, "最近6个月": 91, "10个周月": 20, "23天以上": 25, "9": 5, "20多天": 5, "12分钟左右": 5, "180天内": 2, "14小时以上": 1, "2周~2个月": 4, "10次": 2, "2周~4个月": 4, "每隔两个月": 3, "一到两个小时": 35, "怀孕三四个月": 10, "2秒钟内": 10, "数十个小时": 6, "三个天": 1, "上年五个月": 5, "十三个月": 1, "44天内": 26, "92天": 26, "107小时": 10, "280分钟": 11, "76小时内": 10, "72小时时": 18, "282小时": 17, "8~20个月": 8, "96小": 11, "12小时时": 16, "58分钟": 58, "1小时之后": 21, "超过24个月": 7, "300分钟": 32, "4~67个月": 30, "0.0005分钟": 9, "125.0083分钟": 9, "1426.7556分钟": 9, "144天": 12, "20.2个月": 5, "3~22个月": 12, "24小时时": 3, "433天": 9, "295天": 9, "492天": 9, "376天": 9, "3~30个月": 6, "344.049分钟": 5, "1秒钟以内": 46, "10天到1个月": 1, "最近三个月": 99, "0秒": 20, "三、四个月": 25, "0分钟以内": 9, "2～10个月": 21, "41分钟": 1, "零几个月": 1, "116分钟": 1, "近4个小时": 1, "65分钟": 1, "过去4个月": 1, "7小时之内": 3, "168小时以后": 1, "22天以后": 2, "31小时": 6, "9～24个月": 22, "16分钟左右": 2, "24分钟左右": 2, "23分钟左右": 2, "26分钟左右": 3, "17分钟左右": 1, "150天后": 12, "9小时内": 35, "10天一": 19, "2秒内": 25, "3周至8个月": 6, "7天间": 10, "那一个月": 1, "住院两个月": 1, "9小时左右": 1, "3秒钟后": 5, "6~10个小时": 2, "04个月": 19, "52小时": 11, "30～40分钟内": 2, "60分钟之内": 37, "5个周": 2, "4个周": 1, "1.5小时以上": 1, "十几个钟头": 1, "24小时1天": 1, "26个小时": 1, "9秒之内": 298, "7～64个月": 14, "前8个小时": 30, "1～4个小时": 36, "40秒内": 23, "不超过8个月": 20, "上3个月": 9, "73小时": 12, "每12个小时": 12, "不低于2个小时": 1, "不超过72个小时": 10, "9.3个月": 20, "5～72个月": 20, "96个小时": 11, "近18个月": 5, "240分钟左右": 4, "3～109个月": 3, "72个小时": 7, "2个小时以内": 2, "2个小": 2, "70个小时": 23, "9分钟后": 30, "81天": 2, "九三个月": 2, "怀孕二个月": 1, "超过几个月": 59, "52个月": 138, "2~24个月": 55, "24小时到48小时": 51, "初3个月": 45, "两个 月": 17, "新近几个月": 12, "6 个月": 4, "3 个月": 2, "2 个月": 1, "1 个月": 1, "20～30分钟": 34, "1天1": 60, "7天至2个月": 13, "15分钟以内": 30, "三五七个月": 39, "八九个钟头": 2, "1夜后": 17, "1小时30分钟": 3, "20天之内": 1, "54小时": 1, "11分钟": 10, "40天以内": 1, "99分钟": 14, "100天之后": 5, "后两个月": 1, "1周～1个月": 5, "第1天前6小时": 1, "4小时左右内": 95, "9～27个月": 34, "126天": 18, "过去六个月": 148, "6～20个月": 13, "前20个月": 13, "8～19个月": 13, "17～18个月": 13, "50小时后": 17, "40分钟之内": 6, "40分钟以内": 14, "45个月": 4, "72天后": 1, "160天后": 1, "5小时30分钟": 1, "180分钟内": 1, "1.5～2.5个月": 1, "103分钟": 1, "1.5小时左右": 1, "26小时以上": 1, "14个小时": 3, "275分钟": 1, "30分钟以前": 1, "100秒": 2, "5.7个月": 2, "83分钟": 1, "39小时": 1, "19分钟后": 1, "8个钟头": 1, "1小时10分钟": 1, "40小时以上": 114, "孕前4个月": 9, "7~60个月": 12, "30.8个月": 12, "6~72个月": 12, "34.9个月": 12, "5.5~62.3个月": 13, "24.5个月": 13, "4.1~60.7个月": 13, "23.8个月": 13, "6~34个月": 13, "5~36个月": 13, "2.5~18个月": 13, "3~60个月": 9, "　2个月": 3, "14~30个月": 4, "不少于1个小时": 3, "99天": 2, "不超过3~6个月": 7, "不超过一个小时": 2, "25天以前": 1, "24天以前": 1, "36天以后": 1, "23天以前": 1, "37天以后": 1, "33天内": 1, "37天内": 1, "1~5个月": 3, "8~16个月": 2, "24分钟后": 2, "2周至1个月": 2, "五六三个月": 12, "38分钟": 20, "23分钟内": 2, "40分钟以后": 2, "50分钟以后": 1, "49天内": 6, "3至4个小时": 2, "4周～6个月": 1, "每天晚上2个小时": 1, "2分钟以后": 8, "小时后": 16, "14小时以内": 12, "27个小时": 15, "1至3个月": 15, "农历十二个月": 1, "不超过一个月": 1, "周至六个月": 1, "二个多月": 1, "二个多小时": 1, "近13个小时": 1, "40多个小时": 1, "每二个小时": 1, "19~20个月": 6, "8.1个月": 1, "11.7个月": 1, "29.6个月": 1, "15.2个月": 1, "3天1夜": 1, "8月3个月": 5, "最近四个月": 1, "28天以后": 18, "十多个小时": 2, "一个": 2, "不超过三个月": 75, "超过十二个小时": 2, "\n一个月": 2, "11点钟左右": 2, "15min": 14, "26.5个月": 1, "7～18个月": 1, "15日内": 1, "26天内": 1, "5天5夜": 24, "90": 19, "3天夜": 12, "500秒": 13, "间隔一个月": 1, "15天至1月": 11, "50天至2月": 9, "40天至4个月": 8, "45天～5个月": 8, "40天～4个月": 4, "40天～2个月": 4, "32天之间": 3, "30天至6个月": 2, "45天至2个月": 2, "30天～5月": 1, "36天至6个月": 1, "12小时以后": 5, "5分钟～2小时": 1, "6": 1, "两三个钟头": 1, "两个钟头": 1, "45天之后": 1, "7个钟头": 1, "20天月": 4, "22天前": 8, "平均3个月": 3, "9.5～13.8个月": 139, "417天": 139, "265天": 139, "13.7个月": 139, "12.03个月": 139, "10.92个月": 139, "8.46个月": 139, "小时以上": 148, "20秒之内": 147, "两到四个小时": 4, "10分钟之内": 3, "过去4个星期": 17, "过去1个月": 17, "8分钟以内": 43, "最少3个月": 1, "第16个月": 1, "2~6个小时": 13, "2~8个小时": 1, "6~8个小时": 3, "298天": 3, "260天": 3, "超过3个小时": 1, "16天之间": 44, "50天之间": 14, "八、九个月": 7, "怀孕1个月": 14, "每隔4个月": 19, "不超过11个月": 6, "0.1个月": 23, "360个月": 23, "49.59个月": 23, "128天": 14, "153天": 14, "175天": 14, "零三个月": 1, "七个多月": 5, "3小时以后": 16, "不超2个小时": 24, "13秒": 6, "5分钟左": 18, "1小时末": 24, "0.5~26个月": 7, "6天5晚": 6, "15天~3个月": 18}